Workbook
Name Gewicht_bedOK: Einstellungen!$C$5
Name Ampel_gruen: Einstellungen!$C$6
Name Ampel_gelb: Einstellungen!$C$7
Name KO_aktiv: Einstellungen!$C$8
Name Ziel_Verfuegbarkeit: Einstellungen!$C$11
Name Grenz_IHKQ: Einstellungen!$C$12
Name Risiko_hoch: Einstellungen!$C$13
Name Risiko_mittel: Einstellungen!$C$14
Name Kapitel_Liste: Einstellungen!$B$18:$B$31
Name L_Geltung: Einstellungen!$A$65:$A$66
Name L_JaNein: Einstellungen!$B$65:$B$66
Name L_Krit: Einstellungen!$C$65:$C$67
Name L_Obs: Einstellungen!$D$65:$D$68
Name L_Support: Einstellungen!$E$65:$E$68
Name L_Ausweich: Einstellungen!$F$65:$F$67
Name L_Option: Einstellungen!$G$65:$G$69
Name Aud_Nr: Audit!$A$9:$A$106
Name Aud_Kapitel: Audit!$B$9:$B$106
Name Aud_Punkt: Audit!$C$9:$C$106
Name Aud_Gew: Audit!$F$9:$F$106
Name Aud_KO: Audit!$G$9:$G$106
Name Aud_Bew: Audit!$H$9:$H$106
Name Aud_Massn: Audit!$J$9:$J$106
Name Aud_Verantw: Audit!$K$9:$K$106
Name Aud_Termin: Audit!$L$9:$L$106
Name Aud_Status: Audit!$N$9:$N$106
Name Aud_MNr: Audit!$O$9:$O$106
Name Aud_NIO: Audit!$Q$9:$Q$106
Name Anl_Eq: 'Anlagenübersicht'!$B$5:$B$34
Name Anl_Name: 'Anlagenübersicht'!$C$5:$C$34
Name Anl_Krit: 'Anlagenübersicht'!$H$5:$H$34
Name Anl_Engpass: 'Anlagenübersicht'!$I$5:$I$34
Name Anl_Verf: 'Anlagenübersicht'!$J$5:$J$34
Name Anl_Obs: 'Anlagenübersicht'!$M$5:$M$34
Name Anl_Support: 'Anlagenübersicht'!$N$5:$N$34
Name Anl_Ausweich: 'Anlagenübersicht'!$O$5:$O$34
Name Anl_Notfall: 'Anlagenübersicht'!$P$5:$P$34
Name Anl_W: 'Anlagenübersicht'!$Q$5:$Q$34
Name Anl_A: 'Anlagenübersicht'!$R$5:$R$34
Name Anl_RZ: 'Anlagenübersicht'!$S$5:$S$34
Name Anl_RK: 'Anlagenübersicht'!$T$5:$T$34
Name Anl_Option: 'Anlagenübersicht'!$U$5:$U$34
Name Anl_Invest: 'Anlagenübersicht'!$V$5:$V$34
Name Anl_Key: 'Anlagenübersicht'!$Z$5:$Z$34
Name ET_Teil: 'Kritische Ersatzteile'!$C$5:$C$44
Name ET_Allein: 'Kritische Ersatzteile'!$F$5:$F$44
Name ET_Status: 'Kritische Ersatzteile'!$M$5:$M$44

Sheet Dashboard
B1: Anlagenzustandsanalyse | R1: Dashboard · Bewertung
B2: Auswertung der Blätter „Audit“, „Anlagenübersicht“ und „Kritische Ersatzteile“. Alle Werte berechnen sich automatisch – Eingaben nur in diesen Blättern.
B3: Werk / Standort | H3: Anlage / Maschinengruppe | N3: Datum | Q3: Auditor | U3: Geltungsbereich
B4: =IF(Audit!$C$3="","–",Audit!$C$3) | H4: =IF(Audit!$C$4="","–",Audit!$C$4) | N4: =IF(Audit!$E$3="","–",Audit!$E$3) | Q4: =IF(Audit!$E$4="","–",Audit!$E$4) | U4: =IF(Audit!$E$5="","–",Audit!$E$5)
B6: Gesamtergebnis
B7: Erfüllungsgrad | E7: Gesamtbewertung | H7: Prüfpunkte bewertet | K7: N.I.O | N7: bed. OK | Q7: K.O.-Verstöße | T7: Maßnahmen offen | W7: Maßnahmen erledigt
B8: =Audit!$P$4 | E8: =Audit!$P$5 | H8: =(COUNTA(Aud_Punkt)-Audit!$N$4)&" / "&COUNTA(Aud_Punkt) | K8: =Audit!$J$4 | N8: =Audit!$K$4 | Q8: =Audit!$O$4 | T8: =COUNTIF(Aud_Status,"offen")+COUNTIF(Aud_Status,"überfällig") | W8: =COUNTIF(Aud_Status,"erledigt")&" / "&COUNT(Aud_MNr)
B9: ="Ziel: ≥ "&TEXT(Ampel_gruen,"0%") | E9: ="grün ab "&TEXT(Ampel_gruen,"0%")&" · gelb ab "&TEXT(Ampel_gelb,"0%") | H9: =IFERROR(TEXT((COUNTA(Aud_Punkt)-Audit!$N$4)/COUNTA(Aud_Punkt),"0%")&" bewertet","") | K9: ="nicht erfüllt" | N9: ="teilweise erfüllt" | Q9: ="K.O.-Punkte mit N.I.O" | T9: ="davon überfällig: "&COUNTIF(Aud_Status,"überfällig") | W9: =IFERROR(TEXT(COUNTIF(Aud_Status,"erledigt")/COUNT(Aud_MNr),"0%")&" umgesetzt","keine Maßnahmen")
B11: Ergebnis je Kapitel | S11: Verteilung der Bewertungen | AA11: Hilfswerte (nicht ändern)
B12: Kapitel | H12: Punkte | I12: N.I.O | J12: bed. OK | K12: OK | L12: n. b. | M12: offen | N12: Erfüllungsgrad | P12: Ampel | AB12: gut | AC12: mittel | AD12: kritisch | AE12: Rang-Schlüssel | AG12: Bewertung | AH12: Anzahl
B13: =Einstellungen!$B$18 | H13: =COUNTIFS(Aud_Kapitel,$B13,Aud_Punkt,"?*") | I13: =COUNTIFS(Aud_Kapitel,$B13,Aud_Bew,"N.I.O") | J13: =COUNTIFS(Aud_Kapitel,$B13,Aud_Bew,"bed. OK") | K13: =COUNTIFS(Aud_Kapitel,$B13,Aud_Bew,"OK") | L13: =COUNTIFS(Aud_Kapitel,$B13,Aud_Bew,"n. b.") | M13: =H13-SUM(I13:L13) | N13: =IFERROR((SUMIFS(Aud_Gew,Aud_Kapitel,$B13,Aud_Bew,"OK")+Gewicht_bedOK*SUMIFS(Aud_Gew,Aud_Kapitel,$B13,Aud_Bew,"bed. OK"))/(SUMIFS(Aud_Gew,Aud_Kapitel,$B13,Aud_Bew,"N.I.O")+SUMIFS(Aud_Gew,Aud_Kapitel,$B13,Aud_Bew,"bed. OK")+SUMIFS(Aud_Gew,Aud_Kapitel,$B13,Aud_Bew,"OK")),"") | P13: =IF($N13="","nicht bewertet",IF(AND(KO_aktiv="ja",COUNTIFS(Aud_Kapitel,$B13,Aud_KO,"K.O.",Aud_Bew,"N.I.O")>0),"kritisch (K.O.)",IF($N13>=Ampel_gruen,"gut",IF($N13>=Ampel_gelb,"mittel","kritisch")))) | AB13: =IF($N13="","",IF($N13>=Ampel_gruen,$N13,"")) | AC13: =IF($N13="","",IF(AND($N13>=Ampel_gelb,$N13<Ampel_gruen),$N13,"")) | AD13: =IF($N13="","",IF($N13<Ampel_gelb,$N13,"")) | AE13: =IF($N13="","",$N13+ROW()/100000) | AG13: N.I.O | AH13: =I27
B14: =Einstellungen!$B$19 | H14: =COUNTIFS(Aud_Kapitel,$B14,Aud_Punkt,"?*") | I14: =COUNTIFS(Aud_Kapitel,$B14,Aud_Bew,"N.I.O") | J14: =COUNTIFS(Aud_Kapitel,$B14,Aud_Bew,"bed. OK") | K14: =COUNTIFS(Aud_Kapitel,$B14,Aud_Bew,"OK") | L14: =COUNTIFS(Aud_Kapitel,$B14,Aud_Bew,"n. b.") | M14: =H14-SUM(I14:L14) | N14: =IFERROR((SUMIFS(Aud_Gew,Aud_Kapitel,$B14,Aud_Bew,"OK")+Gewicht_bedOK*SUMIFS(Aud_Gew,Aud_Kapitel,$B14,Aud_Bew,"bed. OK"))/(SUMIFS(Aud_Gew,Aud_Kapitel,$B14,Aud_Bew,"N.I.O")+SUMIFS(Aud_Gew,Aud_Kapitel,$B14,Aud_Bew,"bed. OK")+SUMIFS(Aud_Gew,Aud_Kapitel,$B14,Aud_Bew,"OK")),"") | P14: =IF($N14="","nicht bewertet",IF(AND(KO_aktiv="ja",COUNTIFS(Aud_Kapitel,$B14,Aud_KO,"K.O.",Aud_Bew,"N.I.O")>0),"kritisch (K.O.)",IF($N14>=Ampel_gruen,"gut",IF($N14>=Ampel_gelb,"mittel","kritisch")))) | AB14: =IF($N14="","",IF($N14>=Ampel_gruen,$N14,"")) | AC14: =IF($N14="","",IF(AND($N14>=Ampel_gelb,$N14<Ampel_gruen),$N14,"")) | AD14: =IF($N14="","",IF($N14<Ampel_gelb,$N14,"")) | AE14: =IF($N14="","",$N14+ROW()/100000) | AG14: bed. OK | AH14: =J27
B15: =Einstellungen!$B$20 | H15: =COUNTIFS(Aud_Kapitel,$B15,Aud_Punkt,"?*") | I15: =COUNTIFS(Aud_Kapitel,$B15,Aud_Bew,"N.I.O") | J15: =COUNTIFS(Aud_Kapitel,$B15,Aud_Bew,"bed. OK") | K15: =COUNTIFS(Aud_Kapitel,$B15,Aud_Bew,"OK") | L15: =COUNTIFS(Aud_Kapitel,$B15,Aud_Bew,"n. b.") | M15: =H15-SUM(I15:L15) | N15: =IFERROR((SUMIFS(Aud_Gew,Aud_Kapitel,$B15,Aud_Bew,"OK")+Gewicht_bedOK*SUMIFS(Aud_Gew,Aud_Kapitel,$B15,Aud_Bew,"bed. OK"))/(SUMIFS(Aud_Gew,Aud_Kapitel,$B15,Aud_Bew,"N.I.O")+SUMIFS(Aud_Gew,Aud_Kapitel,$B15,Aud_Bew,"bed. OK")+SUMIFS(Aud_Gew,Aud_Kapitel,$B15,Aud_Bew,"OK")),"") | P15: =IF($N15="","nicht bewertet",IF(AND(KO_aktiv="ja",COUNTIFS(Aud_Kapitel,$B15,Aud_KO,"K.O.",Aud_Bew,"N.I.O")>0),"kritisch (K.O.)",IF($N15>=Ampel_gruen,"gut",IF($N15>=Ampel_gelb,"mittel","kritisch")))) | AB15: =IF($N15="","",IF($N15>=Ampel_gruen,$N15,"")) | AC15: =IF($N15="","",IF(AND($N15>=Ampel_gelb,$N15<Ampel_gruen),$N15,"")) | AD15: =IF($N15="","",IF($N15<Ampel_gelb,$N15,"")) | AE15: =IF($N15="","",$N15+ROW()/100000) | AG15: OK | AH15: =K27
B16: =Einstellungen!$B$21 | H16: =COUNTIFS(Aud_Kapitel,$B16,Aud_Punkt,"?*") | I16: =COUNTIFS(Aud_Kapitel,$B16,Aud_Bew,"N.I.O") | J16: =COUNTIFS(Aud_Kapitel,$B16,Aud_Bew,"bed. OK") | K16: =COUNTIFS(Aud_Kapitel,$B16,Aud_Bew,"OK") | L16: =COUNTIFS(Aud_Kapitel,$B16,Aud_Bew,"n. b.") | M16: =H16-SUM(I16:L16) | N16: =IFERROR((SUMIFS(Aud_Gew,Aud_Kapitel,$B16,Aud_Bew,"OK")+Gewicht_bedOK*SUMIFS(Aud_Gew,Aud_Kapitel,$B16,Aud_Bew,"bed. OK"))/(SUMIFS(Aud_Gew,Aud_Kapitel,$B16,Aud_Bew,"N.I.O")+SUMIFS(Aud_Gew,Aud_Kapitel,$B16,Aud_Bew,"bed. OK")+SUMIFS(Aud_Gew,Aud_Kapitel,$B16,Aud_Bew,"OK")),"") | P16: =IF($N16="","nicht bewertet",IF(AND(KO_aktiv="ja",COUNTIFS(Aud_Kapitel,$B16,Aud_KO,"K.O.",Aud_Bew,"N.I.O")>0),"kritisch (K.O.)",IF($N16>=Ampel_gruen,"gut",IF($N16>=Ampel_gelb,"mittel","kritisch")))) | AB16: =IF($N16="","",IF($N16>=Ampel_gruen,$N16,"")) | AC16: =IF($N16="","",IF(AND($N16>=Ampel_gelb,$N16<Ampel_gruen),$N16,"")) | AD16: =IF($N16="","",IF($N16<Ampel_gelb,$N16,"")) | AE16: =IF($N16="","",$N16+ROW()/100000) | AG16: n. b. | AH16: =L27
B17: =Einstellungen!$B$22 | H17: =COUNTIFS(Aud_Kapitel,$B17,Aud_Punkt,"?*") | I17: =COUNTIFS(Aud_Kapitel,$B17,Aud_Bew,"N.I.O") | J17: =COUNTIFS(Aud_Kapitel,$B17,Aud_Bew,"bed. OK") | K17: =COUNTIFS(Aud_Kapitel,$B17,Aud_Bew,"OK") | L17: =COUNTIFS(Aud_Kapitel,$B17,Aud_Bew,"n. b.") | M17: =H17-SUM(I17:L17) | N17: =IFERROR((SUMIFS(Aud_Gew,Aud_Kapitel,$B17,Aud_Bew,"OK")+Gewicht_bedOK*SUMIFS(Aud_Gew,Aud_Kapitel,$B17,Aud_Bew,"bed. OK"))/(SUMIFS(Aud_Gew,Aud_Kapitel,$B17,Aud_Bew,"N.I.O")+SUMIFS(Aud_Gew,Aud_Kapitel,$B17,Aud_Bew,"bed. OK")+SUMIFS(Aud_Gew,Aud_Kapitel,$B17,Aud_Bew,"OK")),"") | P17: =IF($N17="","nicht bewertet",IF(AND(KO_aktiv="ja",COUNTIFS(Aud_Kapitel,$B17,Aud_KO,"K.O.",Aud_Bew,"N.I.O")>0),"kritisch (K.O.)",IF($N17>=Ampel_gruen,"gut",IF($N17>=Ampel_gelb,"mittel","kritisch")))) | AB17: =IF($N17="","",IF($N17>=Ampel_gruen,$N17,"")) | AC17: =IF($N17="","",IF(AND($N17>=Ampel_gelb,$N17<Ampel_gruen),$N17,"")) | AD17: =IF($N17="","",IF($N17<Ampel_gelb,$N17,"")) | AE17: =IF($N17="","",$N17+ROW()/100000) | AG17: offen | AH17: =M27
B18: =Einstellungen!$B$23 | H18: =COUNTIFS(Aud_Kapitel,$B18,Aud_Punkt,"?*") | I18: =COUNTIFS(Aud_Kapitel,$B18,Aud_Bew,"N.I.O") | J18: =COUNTIFS(Aud_Kapitel,$B18,Aud_Bew,"bed. OK") | K18: =COUNTIFS(Aud_Kapitel,$B18,Aud_Bew,"OK") | L18: =COUNTIFS(Aud_Kapitel,$B18,Aud_Bew,"n. b.") | M18: =H18-SUM(I18:L18) | N18: =IFERROR((SUMIFS(Aud_Gew,Aud_Kapitel,$B18,Aud_Bew,"OK")+Gewicht_bedOK*SUMIFS(Aud_Gew,Aud_Kapitel,$B18,Aud_Bew,"bed. OK"))/(SUMIFS(Aud_Gew,Aud_Kapitel,$B18,Aud_Bew,"N.I.O")+SUMIFS(Aud_Gew,Aud_Kapitel,$B18,Aud_Bew,"bed. OK")+SUMIFS(Aud_Gew,Aud_Kapitel,$B18,Aud_Bew,"OK")),"") | P18: =IF($N18="","nicht bewertet",IF(AND(KO_aktiv="ja",COUNTIFS(Aud_Kapitel,$B18,Aud_KO,"K.O.",Aud_Bew,"N.I.O")>0),"kritisch (K.O.)",IF($N18>=Ampel_gruen,"gut",IF($N18>=Ampel_gelb,"mittel","kritisch")))) | AB18: =IF($N18="","",IF($N18>=Ampel_gruen,$N18,"")) | AC18: =IF($N18="","",IF(AND($N18>=Ampel_gelb,$N18<Ampel_gruen),$N18,"")) | AD18: =IF($N18="","",IF($N18<Ampel_gelb,$N18,"")) | AE18: =IF($N18="","",$N18+ROW()/100000)
B19: =Einstellungen!$B$24 | H19: =COUNTIFS(Aud_Kapitel,$B19,Aud_Punkt,"?*") | I19: =COUNTIFS(Aud_Kapitel,$B19,Aud_Bew,"N.I.O") | J19: =COUNTIFS(Aud_Kapitel,$B19,Aud_Bew,"bed. OK") | K19: =COUNTIFS(Aud_Kapitel,$B19,Aud_Bew,"OK") | L19: =COUNTIFS(Aud_Kapitel,$B19,Aud_Bew,"n. b.") | M19: =H19-SUM(I19:L19) | N19: =IFERROR((SUMIFS(Aud_Gew,Aud_Kapitel,$B19,Aud_Bew,"OK")+Gewicht_bedOK*SUMIFS(Aud_Gew,Aud_Kapitel,$B19,Aud_Bew,"bed. OK"))/(SUMIFS(Aud_Gew,Aud_Kapitel,$B19,Aud_Bew,"N.I.O")+SUMIFS(Aud_Gew,Aud_Kapitel,$B19,Aud_Bew,"bed. OK")+SUMIFS(Aud_Gew,Aud_Kapitel,$B19,Aud_Bew,"OK")),"") | P19: =IF($N19="","nicht bewertet",IF(AND(KO_aktiv="ja",COUNTIFS(Aud_Kapitel,$B19,Aud_KO,"K.O.",Aud_Bew,"N.I.O")>0),"kritisch (K.O.)",IF($N19>=Ampel_gruen,"gut",IF($N19>=Ampel_gelb,"mittel","kritisch")))) | AB19: =IF($N19="","",IF($N19>=Ampel_gruen,$N19,"")) | AC19: =IF($N19="","",IF(AND($N19>=Ampel_gelb,$N19<Ampel_gruen),$N19,"")) | AD19: =IF($N19="","",IF($N19<Ampel_gelb,$N19,"")) | AE19: =IF($N19="","",$N19+ROW()/100000)
B20: =Einstellungen!$B$25 | H20: =COUNTIFS(Aud_Kapitel,$B20,Aud_Punkt,"?*") | I20: =COUNTIFS(Aud_Kapitel,$B20,Aud_Bew,"N.I.O") | J20: =COUNTIFS(Aud_Kapitel,$B20,Aud_Bew,"bed. OK") | K20: =COUNTIFS(Aud_Kapitel,$B20,Aud_Bew,"OK") | L20: =COUNTIFS(Aud_Kapitel,$B20,Aud_Bew,"n. b.") | M20: =H20-SUM(I20:L20) | N20: =IFERROR((SUMIFS(Aud_Gew,Aud_Kapitel,$B20,Aud_Bew,"OK")+Gewicht_bedOK*SUMIFS(Aud_Gew,Aud_Kapitel,$B20,Aud_Bew,"bed. OK"))/(SUMIFS(Aud_Gew,Aud_Kapitel,$B20,Aud_Bew,"N.I.O")+SUMIFS(Aud_Gew,Aud_Kapitel,$B20,Aud_Bew,"bed. OK")+SUMIFS(Aud_Gew,Aud_Kapitel,$B20,Aud_Bew,"OK")),"") | P20: =IF($N20="","nicht bewertet",IF(AND(KO_aktiv="ja",COUNTIFS(Aud_Kapitel,$B20,Aud_KO,"K.O.",Aud_Bew,"N.I.O")>0),"kritisch (K.O.)",IF($N20>=Ampel_gruen,"gut",IF($N20>=Ampel_gelb,"mittel","kritisch")))) | AB20: =IF($N20="","",IF($N20>=Ampel_gruen,$N20,"")) | AC20: =IF($N20="","",IF(AND($N20>=Ampel_gelb,$N20<Ampel_gruen),$N20,"")) | AD20: =IF($N20="","",IF($N20<Ampel_gelb,$N20,"")) | AE20: =IF($N20="","",$N20+ROW()/100000)
B21: =Einstellungen!$B$26 | H21: =COUNTIFS(Aud_Kapitel,$B21,Aud_Punkt,"?*") | I21: =COUNTIFS(Aud_Kapitel,$B21,Aud_Bew,"N.I.O") | J21: =COUNTIFS(Aud_Kapitel,$B21,Aud_Bew,"bed. OK") | K21: =COUNTIFS(Aud_Kapitel,$B21,Aud_Bew,"OK") | L21: =COUNTIFS(Aud_Kapitel,$B21,Aud_Bew,"n. b.") | M21: =H21-SUM(I21:L21) | N21: =IFERROR((SUMIFS(Aud_Gew,Aud_Kapitel,$B21,Aud_Bew,"OK")+Gewicht_bedOK*SUMIFS(Aud_Gew,Aud_Kapitel,$B21,Aud_Bew,"bed. OK"))/(SUMIFS(Aud_Gew,Aud_Kapitel,$B21,Aud_Bew,"N.I.O")+SUMIFS(Aud_Gew,Aud_Kapitel,$B21,Aud_Bew,"bed. OK")+SUMIFS(Aud_Gew,Aud_Kapitel,$B21,Aud_Bew,"OK")),"") | P21: =IF($N21="","nicht bewertet",IF(AND(KO_aktiv="ja",COUNTIFS(Aud_Kapitel,$B21,Aud_KO,"K.O.",Aud_Bew,"N.I.O")>0),"kritisch (K.O.)",IF($N21>=Ampel_gruen,"gut",IF($N21>=Ampel_gelb,"mittel","kritisch")))) | AB21: =IF($N21="","",IF($N21>=Ampel_gruen,$N21,"")) | AC21: =IF($N21="","",IF(AND($N21>=Ampel_gelb,$N21<Ampel_gruen),$N21,"")) | AD21: =IF($N21="","",IF($N21<Ampel_gelb,$N21,"")) | AE21: =IF($N21="","",$N21+ROW()/100000)
B22: =Einstellungen!$B$27 | H22: =COUNTIFS(Aud_Kapitel,$B22,Aud_Punkt,"?*") | I22: =COUNTIFS(Aud_Kapitel,$B22,Aud_Bew,"N.I.O") | J22: =COUNTIFS(Aud_Kapitel,$B22,Aud_Bew,"bed. OK") | K22: =COUNTIFS(Aud_Kapitel,$B22,Aud_Bew,"OK") | L22: =COUNTIFS(Aud_Kapitel,$B22,Aud_Bew,"n. b.") | M22: =H22-SUM(I22:L22) | N22: =IFERROR((SUMIFS(Aud_Gew,Aud_Kapitel,$B22,Aud_Bew,"OK")+Gewicht_bedOK*SUMIFS(Aud_Gew,Aud_Kapitel,$B22,Aud_Bew,"bed. OK"))/(SUMIFS(Aud_Gew,Aud_Kapitel,$B22,Aud_Bew,"N.I.O")+SUMIFS(Aud_Gew,Aud_Kapitel,$B22,Aud_Bew,"bed. OK")+SUMIFS(Aud_Gew,Aud_Kapitel,$B22,Aud_Bew,"OK")),"") | P22: =IF($N22="","nicht bewertet",IF(AND(KO_aktiv="ja",COUNTIFS(Aud_Kapitel,$B22,Aud_KO,"K.O.",Aud_Bew,"N.I.O")>0),"kritisch (K.O.)",IF($N22>=Ampel_gruen,"gut",IF($N22>=Ampel_gelb,"mittel","kritisch")))) | AB22: =IF($N22="","",IF($N22>=Ampel_gruen,$N22,"")) | AC22: =IF($N22="","",IF(AND($N22>=Ampel_gelb,$N22<Ampel_gruen),$N22,"")) | AD22: =IF($N22="","",IF($N22<Ampel_gelb,$N22,"")) | AE22: =IF($N22="","",$N22+ROW()/100000)
B23: =Einstellungen!$B$28 | H23: =COUNTIFS(Aud_Kapitel,$B23,Aud_Punkt,"?*") | I23: =COUNTIFS(Aud_Kapitel,$B23,Aud_Bew,"N.I.O") | J23: =COUNTIFS(Aud_Kapitel,$B23,Aud_Bew,"bed. OK") | K23: =COUNTIFS(Aud_Kapitel,$B23,Aud_Bew,"OK") | L23: =COUNTIFS(Aud_Kapitel,$B23,Aud_Bew,"n. b.") | M23: =H23-SUM(I23:L23) | N23: =IFERROR((SUMIFS(Aud_Gew,Aud_Kapitel,$B23,Aud_Bew,"OK")+Gewicht_bedOK*SUMIFS(Aud_Gew,Aud_Kapitel,$B23,Aud_Bew,"bed. OK"))/(SUMIFS(Aud_Gew,Aud_Kapitel,$B23,Aud_Bew,"N.I.O")+SUMIFS(Aud_Gew,Aud_Kapitel,$B23,Aud_Bew,"bed. OK")+SUMIFS(Aud_Gew,Aud_Kapitel,$B23,Aud_Bew,"OK")),"") | P23: =IF($N23="","nicht bewertet",IF(AND(KO_aktiv="ja",COUNTIFS(Aud_Kapitel,$B23,Aud_KO,"K.O.",Aud_Bew,"N.I.O")>0),"kritisch (K.O.)",IF($N23>=Ampel_gruen,"gut",IF($N23>=Ampel_gelb,"mittel","kritisch")))) | AB23: =IF($N23="","",IF($N23>=Ampel_gruen,$N23,"")) | AC23: =IF($N23="","",IF(AND($N23>=Ampel_gelb,$N23<Ampel_gruen),$N23,"")) | AD23: =IF($N23="","",IF($N23<Ampel_gelb,$N23,"")) | AE23: =IF($N23="","",$N23+ROW()/100000)
B24: =Einstellungen!$B$29 | H24: =COUNTIFS(Aud_Kapitel,$B24,Aud_Punkt,"?*") | I24: =COUNTIFS(Aud_Kapitel,$B24,Aud_Bew,"N.I.O") | J24: =COUNTIFS(Aud_Kapitel,$B24,Aud_Bew,"bed. OK") | K24: =COUNTIFS(Aud_Kapitel,$B24,Aud_Bew,"OK") | L24: =COUNTIFS(Aud_Kapitel,$B24,Aud_Bew,"n. b.") | M24: =H24-SUM(I24:L24) | N24: =IFERROR((SUMIFS(Aud_Gew,Aud_Kapitel,$B24,Aud_Bew,"OK")+Gewicht_bedOK*SUMIFS(Aud_Gew,Aud_Kapitel,$B24,Aud_Bew,"bed. OK"))/(SUMIFS(Aud_Gew,Aud_Kapitel,$B24,Aud_Bew,"N.I.O")+SUMIFS(Aud_Gew,Aud_Kapitel,$B24,Aud_Bew,"bed. OK")+SUMIFS(Aud_Gew,Aud_Kapitel,$B24,Aud_Bew,"OK")),"") | P24: =IF($N24="","nicht bewertet",IF(AND(KO_aktiv="ja",COUNTIFS(Aud_Kapitel,$B24,Aud_KO,"K.O.",Aud_Bew,"N.I.O")>0),"kritisch (K.O.)",IF($N24>=Ampel_gruen,"gut",IF($N24>=Ampel_gelb,"mittel","kritisch")))) | AB24: =IF($N24="","",IF($N24>=Ampel_gruen,$N24,"")) | AC24: =IF($N24="","",IF(AND($N24>=Ampel_gelb,$N24<Ampel_gruen),$N24,"")) | AD24: =IF($N24="","",IF($N24<Ampel_gelb,$N24,"")) | AE24: =IF($N24="","",$N24+ROW()/100000)
B25: =Einstellungen!$B$30 | H25: =COUNTIFS(Aud_Kapitel,$B25,Aud_Punkt,"?*") | I25: =COUNTIFS(Aud_Kapitel,$B25,Aud_Bew,"N.I.O") | J25: =COUNTIFS(Aud_Kapitel,$B25,Aud_Bew,"bed. OK") | K25: =COUNTIFS(Aud_Kapitel,$B25,Aud_Bew,"OK") | L25: =COUNTIFS(Aud_Kapitel,$B25,Aud_Bew,"n. b.") | M25: =H25-SUM(I25:L25) | N25: =IFERROR((SUMIFS(Aud_Gew,Aud_Kapitel,$B25,Aud_Bew,"OK")+Gewicht_bedOK*SUMIFS(Aud_Gew,Aud_Kapitel,$B25,Aud_Bew,"bed. OK"))/(SUMIFS(Aud_Gew,Aud_Kapitel,$B25,Aud_Bew,"N.I.O")+SUMIFS(Aud_Gew,Aud_Kapitel,$B25,Aud_Bew,"bed. OK")+SUMIFS(Aud_Gew,Aud_Kapitel,$B25,Aud_Bew,"OK")),"") | P25: =IF($N25="","nicht bewertet",IF(AND(KO_aktiv="ja",COUNTIFS(Aud_Kapitel,$B25,Aud_KO,"K.O.",Aud_Bew,"N.I.O")>0),"kritisch (K.O.)",IF($N25>=Ampel_gruen,"gut",IF($N25>=Ampel_gelb,"mittel","kritisch")))) | AB25: =IF($N25="","",IF($N25>=Ampel_gruen,$N25,"")) | AC25: =IF($N25="","",IF(AND($N25>=Ampel_gelb,$N25<Ampel_gruen),$N25,"")) | AD25: =IF($N25="","",IF($N25<Ampel_gelb,$N25,"")) | AE25: =IF($N25="","",$N25+ROW()/100000)
B26: =Einstellungen!$B$31 | H26: =COUNTIFS(Aud_Kapitel,$B26,Aud_Punkt,"?*") | I26: =COUNTIFS(Aud_Kapitel,$B26,Aud_Bew,"N.I.O") | J26: =COUNTIFS(Aud_Kapitel,$B26,Aud_Bew,"bed. OK") | K26: =COUNTIFS(Aud_Kapitel,$B26,Aud_Bew,"OK") | L26: =COUNTIFS(Aud_Kapitel,$B26,Aud_Bew,"n. b.") | M26: =H26-SUM(I26:L26) | N26: =IFERROR((SUMIFS(Aud_Gew,Aud_Kapitel,$B26,Aud_Bew,"OK")+Gewicht_bedOK*SUMIFS(Aud_Gew,Aud_Kapitel,$B26,Aud_Bew,"bed. OK"))/(SUMIFS(Aud_Gew,Aud_Kapitel,$B26,Aud_Bew,"N.I.O")+SUMIFS(Aud_Gew,Aud_Kapitel,$B26,Aud_Bew,"bed. OK")+SUMIFS(Aud_Gew,Aud_Kapitel,$B26,Aud_Bew,"OK")),"") | P26: =IF($N26="","nicht bewertet",IF(AND(KO_aktiv="ja",COUNTIFS(Aud_Kapitel,$B26,Aud_KO,"K.O.",Aud_Bew,"N.I.O")>0),"kritisch (K.O.)",IF($N26>=Ampel_gruen,"gut",IF($N26>=Ampel_gelb,"mittel","kritisch")))) | AB26: =IF($N26="","",IF($N26>=Ampel_gruen,$N26,"")) | AC26: =IF($N26="","",IF(AND($N26>=Ampel_gelb,$N26<Ampel_gruen),$N26,"")) | AD26: =IF($N26="","",IF($N26<Ampel_gelb,$N26,"")) | AE26: =IF($N26="","",$N26+ROW()/100000)
B27: Gesamt | H27: =SUM(H13:H26) | I27: =SUM(I13:I26) | J27: =SUM(J13:J26) | K27: =SUM(K13:K26) | L27: =SUM(L13:L26) | M27: =SUM(M13:M26) | N27: =Audit!$P$4 | P27: =Audit!$P$5
B29: Erfüllungsgrad je Kapitel | O29: Bewertungen je Kapitel (Anzahl Prüfpunkte)
B49: Erfüllungsgrad = Σ(Gewicht × Wertung) ÷ Σ(Gewicht) der bewerteten Punkte. Gewicht „bed. OK“, Ampelgrenzen und K.O.-Regel: Blatt „Einstellungen“.
B51: Größter Handlungsbedarf (5 Kapitel mit dem niedrigsten Erfüllungsgrad) | O51: Umsetzungsstand der Maßnahmen
B52: Rang | C52: Kapitel | I52: Erfüllungsgrad | K52: N.I.O | L52: bed. OK | O52: Status | S52: Anzahl | U52: Anteil | AF52: k-kleinster | AG52: Position
B53: =IF($AG53="","",1) | C53: =IF($AG53="","",INDEX($B$13:$B$26,$AG53)) | I53: =IF($AG53="","",INDEX($N$13:$N$26,$AG53)) | K53: =IF($AG53="","",INDEX($I$13:$I$26,$AG53)) | L53: =IF($AG53="","",INDEX($J$13:$J$26,$AG53)) | O53: überfällig | S53: =COUNTIF(Aud_Status,"überfällig") | U53: =IFERROR(S53/$S$56,0) | AF53: =IFERROR(SMALL($AE$13:$AE$26,1),"") | AG53: =IF($AF53="","",MATCH($AF53,$AE$13:$AE$26,0))
B54: =IF($AG54="","",2) | C54: =IF($AG54="","",INDEX($B$13:$B$26,$AG54)) | I54: =IF($AG54="","",INDEX($N$13:$N$26,$AG54)) | K54: =IF($AG54="","",INDEX($I$13:$I$26,$AG54)) | L54: =IF($AG54="","",INDEX($J$13:$J$26,$AG54)) | O54: offen | S54: =COUNTIF(Aud_Status,"offen") | U54: =IFERROR(S54/$S$56,0) | AF54: =IFERROR(SMALL($AE$13:$AE$26,2),"") | AG54: =IF($AF54="","",MATCH($AF54,$AE$13:$AE$26,0))
B55: =IF($AG55="","",3) | C55: =IF($AG55="","",INDEX($B$13:$B$26,$AG55)) | I55: =IF($AG55="","",INDEX($N$13:$N$26,$AG55)) | K55: =IF($AG55="","",INDEX($I$13:$I$26,$AG55)) | L55: =IF($AG55="","",INDEX($J$13:$J$26,$AG55)) | O55: erledigt | S55: =COUNTIF(Aud_Status,"erledigt") | U55: =IFERROR(S55/$S$56,0) | AF55: =IFERROR(SMALL($AE$13:$AE$26,3),"") | AG55: =IF($AF55="","",MATCH($AF55,$AE$13:$AE$26,0))
B56: =IF($AG56="","",4) | C56: =IF($AG56="","",INDEX($B$13:$B$26,$AG56)) | I56: =IF($AG56="","",INDEX($N$13:$N$26,$AG56)) | K56: =IF($AG56="","",INDEX($I$13:$I$26,$AG56)) | L56: =IF($AG56="","",INDEX($J$13:$J$26,$AG56)) | O56: Gesamt | S56: =SUM(S53:S55) | U56: =IF(S56=0,"keine Maßnahmen","Maßnahmen aus N.I.O und bed. OK") | AF56: =IFERROR(SMALL($AE$13:$AE$26,4),"") | AG56: =IF($AF56="","",MATCH($AF56,$AE$13:$AE$26,0))
B57: =IF($AG57="","",5) | C57: =IF($AG57="","",INDEX($B$13:$B$26,$AG57)) | I57: =IF($AG57="","",INDEX($N$13:$N$26,$AG57)) | K57: =IF($AG57="","",INDEX($I$13:$I$26,$AG57)) | L57: =IF($AG57="","",INDEX($J$13:$J$26,$AG57)) | AF57: =IFERROR(SMALL($AE$13:$AE$26,5),"") | AG57: =IF($AF57="","",MATCH($AF57,$AE$13:$AE$26,0))
B58: Reihenfolge nach Erfüllungsgrad; bei Gleichstand zählt die Kapitelreihenfolge.
B60: Kritische Abweichungen – Prüfpunkte mit N.I.O
B61: Nr. | C61: Kapitel | G61: Check-Punkt | O61: Maßnahme / Bemerkung | T61: Verantwortlich | V61: Termin | X61: Status | AF61: Position
B62: =IF($AF62="","",INDEX(Aud_Nr,$AF62)) | C62: =IF($AF62="","",INDEX(Aud_Kapitel,$AF62)) | G62: =IF($AF62="","",INDEX(Aud_Punkt,$AF62)) | O62: =IF($AF62="","",IF(INDEX(Aud_Massn,$AF62)="","– fehlt –",INDEX(Aud_Massn,$AF62))) | T62: =IF($AF62="","",IF(INDEX(Aud_Verantw,$AF62)="","– fehlt –",INDEX(Aud_Verantw,$AF62))) | V62: =IF($AF62="","",IF(INDEX(Aud_Termin,$AF62)="","– fehlt –",INDEX(Aud_Termin,$AF62))) | X62: =IF($AF62="","",INDEX(Aud_Status,$AF62)) | AF62: =IFERROR(MATCH(1,Aud_NIO,0),"")
B63: =IF($AF63="","",INDEX(Aud_Nr,$AF63)) | C63: =IF($AF63="","",INDEX(Aud_Kapitel,$AF63)) | G63: =IF($AF63="","",INDEX(Aud_Punkt,$AF63)) | O63: =IF($AF63="","",IF(INDEX(Aud_Massn,$AF63)="","– fehlt –",INDEX(Aud_Massn,$AF63))) | T63: =IF($AF63="","",IF(INDEX(Aud_Verantw,$AF63)="","– fehlt –",INDEX(Aud_Verantw,$AF63))) | V63: =IF($AF63="","",IF(INDEX(Aud_Termin,$AF63)="","– fehlt –",INDEX(Aud_Termin,$AF63))) | X63: =IF($AF63="","",INDEX(Aud_Status,$AF63)) | AF63: =IFERROR(MATCH(2,Aud_NIO,0),"")
B64: =IF($AF64="","",INDEX(Aud_Nr,$AF64)) | C64: =IF($AF64="","",INDEX(Aud_Kapitel,$AF64)) | G64: =IF($AF64="","",INDEX(Aud_Punkt,$AF64)) | O64: =IF($AF64="","",IF(INDEX(Aud_Massn,$AF64)="","– fehlt –",INDEX(Aud_Massn,$AF64))) | T64: =IF($AF64="","",IF(INDEX(Aud_Verantw,$AF64)="","– fehlt –",INDEX(Aud_Verantw,$AF64))) | V64: =IF($AF64="","",IF(INDEX(Aud_Termin,$AF64)="","– fehlt –",INDEX(Aud_Termin,$AF64))) | X64: =IF($AF64="","",INDEX(Aud_Status,$AF64)) | AF64: =IFERROR(MATCH(3,Aud_NIO,0),"")
B65: =IF($AF65="","",INDEX(Aud_Nr,$AF65)) | C65: =IF($AF65="","",INDEX(Aud_Kapitel,$AF65)) | G65: =IF($AF65="","",INDEX(Aud_Punkt,$AF65)) | O65: =IF($AF65="","",IF(INDEX(Aud_Massn,$AF65)="","– fehlt –",INDEX(Aud_Massn,$AF65))) | T65: =IF($AF65="","",IF(INDEX(Aud_Verantw,$AF65)="","– fehlt –",INDEX(Aud_Verantw,$AF65))) | V65: =IF($AF65="","",IF(INDEX(Aud_Termin,$AF65)="","– fehlt –",INDEX(Aud_Termin,$AF65))) | X65: =IF($AF65="","",INDEX(Aud_Status,$AF65)) | AF65: =IFERROR(MATCH(4,Aud_NIO,0),"")
B66: =IF($AF66="","",INDEX(Aud_Nr,$AF66)) | C66: =IF($AF66="","",INDEX(Aud_Kapitel,$AF66)) | G66: =IF($AF66="","",INDEX(Aud_Punkt,$AF66)) | O66: =IF($AF66="","",IF(INDEX(Aud_Massn,$AF66)="","– fehlt –",INDEX(Aud_Massn,$AF66))) | T66: =IF($AF66="","",IF(INDEX(Aud_Verantw,$AF66)="","– fehlt –",INDEX(Aud_Verantw,$AF66))) | V66: =IF($AF66="","",IF(INDEX(Aud_Termin,$AF66)="","– fehlt –",INDEX(Aud_Termin,$AF66))) | X66: =IF($AF66="","",INDEX(Aud_Status,$AF66)) | AF66: =IFERROR(MATCH(5,Aud_NIO,0),"")
B67: =IF($AF67="","",INDEX(Aud_Nr,$AF67)) | C67: =IF($AF67="","",INDEX(Aud_Kapitel,$AF67)) | G67: =IF($AF67="","",INDEX(Aud_Punkt,$AF67)) | O67: =IF($AF67="","",IF(INDEX(Aud_Massn,$AF67)="","– fehlt –",INDEX(Aud_Massn,$AF67))) | T67: =IF($AF67="","",IF(INDEX(Aud_Verantw,$AF67)="","– fehlt –",INDEX(Aud_Verantw,$AF67))) | V67: =IF($AF67="","",IF(INDEX(Aud_Termin,$AF67)="","– fehlt –",INDEX(Aud_Termin,$AF67))) | X67: =IF($AF67="","",INDEX(Aud_Status,$AF67)) | AF67: =IFERROR(MATCH(6,Aud_NIO,0),"")
B68: =IF($AF68="","",INDEX(Aud_Nr,$AF68)) | C68: =IF($AF68="","",INDEX(Aud_Kapitel,$AF68)) | G68: =IF($AF68="","",INDEX(Aud_Punkt,$AF68)) | O68: =IF($AF68="","",IF(INDEX(Aud_Massn,$AF68)="","– fehlt –",INDEX(Aud_Massn,$AF68))) | T68: =IF($AF68="","",IF(INDEX(Aud_Verantw,$AF68)="","– fehlt –",INDEX(Aud_Verantw,$AF68))) | V68: =IF($AF68="","",IF(INDEX(Aud_Termin,$AF68)="","– fehlt –",INDEX(Aud_Termin,$AF68))) | X68: =IF($AF68="","",INDEX(Aud_Status,$AF68)) | AF68: =IFERROR(MATCH(7,Aud_NIO,0),"")
B69: =IF($AF69="","",INDEX(Aud_Nr,$AF69)) | C69: =IF($AF69="","",INDEX(Aud_Kapitel,$AF69)) | G69: =IF($AF69="","",INDEX(Aud_Punkt,$AF69)) | O69: =IF($AF69="","",IF(INDEX(Aud_Massn,$AF69)="","– fehlt –",INDEX(Aud_Massn,$AF69))) | T69: =IF($AF69="","",IF(INDEX(Aud_Verantw,$AF69)="","– fehlt –",INDEX(Aud_Verantw,$AF69))) | V69: =IF($AF69="","",IF(INDEX(Aud_Termin,$AF69)="","– fehlt –",INDEX(Aud_Termin,$AF69))) | X69: =IF($AF69="","",INDEX(Aud_Status,$AF69)) | AF69: =IFERROR(MATCH(8,Aud_NIO,0),"")
B70: =IF($AF70="","",INDEX(Aud_Nr,$AF70)) | C70: =IF($AF70="","",INDEX(Aud_Kapitel,$AF70)) | G70: =IF($AF70="","",INDEX(Aud_Punkt,$AF70)) | O70: =IF($AF70="","",IF(INDEX(Aud_Massn,$AF70)="","– fehlt –",INDEX(Aud_Massn,$AF70))) | T70: =IF($AF70="","",IF(INDEX(Aud_Verantw,$AF70)="","– fehlt –",INDEX(Aud_Verantw,$AF70))) | V70: =IF($AF70="","",IF(INDEX(Aud_Termin,$AF70)="","– fehlt –",INDEX(Aud_Termin,$AF70))) | X70: =IF($AF70="","",INDEX(Aud_Status,$AF70)) | AF70: =IFERROR(MATCH(9,Aud_NIO,0),"")
B71: =IF($AF71="","",INDEX(Aud_Nr,$AF71)) | C71: =IF($AF71="","",INDEX(Aud_Kapitel,$AF71)) | G71: =IF($AF71="","",INDEX(Aud_Punkt,$AF71)) | O71: =IF($AF71="","",IF(INDEX(Aud_Massn,$AF71)="","– fehlt –",INDEX(Aud_Massn,$AF71))) | T71: =IF($AF71="","",IF(INDEX(Aud_Verantw,$AF71)="","– fehlt –",INDEX(Aud_Verantw,$AF71))) | V71: =IF($AF71="","",IF(INDEX(Aud_Termin,$AF71)="","– fehlt –",INDEX(Aud_Termin,$AF71))) | X71: =IF($AF71="","",INDEX(Aud_Status,$AF71)) | AF71: =IFERROR(MATCH(10,Aud_NIO,0),"")
B72: =IF(Audit!$J$4=0,"Keine Prüfpunkte mit N.I.O bewertet.",IF(Audit!$J$4>10,"Weitere N.I.O-Punkte: "&(Audit!$J$4-10)&" – vollständige Liste (N.I.O und bed. OK) im Blatt „Maßnahmen“.","Vollständige Liste (N.I.O und bed. OK) im Blatt „Maßnahmen“."))
B75: Anlagenrisiko, kritische Ersatzteile und Investitionsbedarf (NEU – aus „Anlagenübersicht“ und „Kritische Ersatzteile“)
B76: Anlagen erfasst | E76: Risiko hoch | H76: Risiko mittel | K76: Risiko gering | N76: A-Anlagen ohne Notfallplan | Q76: Obsoleszenzrisiken | T76: Krit. Ersatzteile auffällig | W76: Investitionsbedarf
B77: =COUNTIF(Anl_Eq,"?*") | E77: =COUNTIF(Anl_RK,"hoch") | H77: =COUNTIF(Anl_RK,"mittel") | K77: =COUNTIF(Anl_RK,"gering") | N77: =COUNTIFS(Anl_Krit,"A",Anl_Notfall,"nein") | Q77: =COUNTIF(Anl_Obs,"abgekündigt")+COUNTIF(Anl_Obs,"nicht mehr lieferbar") | T77: =COUNTIF(ET_Status,"?*")-COUNTIF(ET_Status,"in Ordnung") | W77: =SUM(Anl_Invest)
B78: =COUNTIF(Anl_Krit,"A")&" A · "&COUNTIF(Anl_Krit,"B")&" B · "&COUNTIF(Anl_Krit,"C")&" C" | E78: ="Risikozahl ≥ "&Risiko_hoch | H78: ="Risikozahl ≥ "&Risiko_mittel | K78: ="nicht bewertet: "&(COUNTIF(Anl_Eq,"?*")-COUNTIF(Anl_RK,"?*")) | N78: ="Pflicht nach IATF 6.1.2.3" | Q78: ="Anlagen mit abgekündigten Komp." | T78: ="von "&COUNTIF(ET_Teil,"?*")&" erfassten Teilen" | W78: ="Summe geschätzt (Anlagenübersicht)"
B80: Risikomatrix (Anzahl Anlagen) | M80: Top 5 Anlagen nach Risikozahl
B81: Zelle = Anzahl Anlagen; Farbe = Risikoklasse (W × A).
B82: Ausfall- wahrschein- lichkeit (W) | D82: 5 | E82: =COUNTIFS(Anl_W,5,Anl_A,1) | F82: =COUNTIFS(Anl_W,5,Anl_A,2) | G82: =COUNTIFS(Anl_W,5,Anl_A,3) | H82: =COUNTIFS(Anl_W,5,Anl_A,4) | I82: =COUNTIFS(Anl_W,5,Anl_A,5) | M82: Rang | N82: Equipment-Nr. | P82: Anlage | T82: Krit. | U82: W | V82: A | W82: W × A | X82: Risikoklasse | AF82: k-größter | AG82: Position
D83: 4 | E83: =COUNTIFS(Anl_W,4,Anl_A,1) | F83: =COUNTIFS(Anl_W,4,Anl_A,2) | G83: =COUNTIFS(Anl_W,4,Anl_A,3) | H83: =COUNTIFS(Anl_W,4,Anl_A,4) | I83: =COUNTIFS(Anl_W,4,Anl_A,5) | M83: =IF($AG83="","",1) | N83: =IF($AG83="","",INDEX(Anl_Eq,$AG83)) | P83: =IF($AG83="","",INDEX(Anl_Name,$AG83)) | T83: =IF($AG83="","",INDEX(Anl_Krit,$AG83)) | U83: =IF($AG83="","",INDEX(Anl_W,$AG83)) | V83: =IF($AG83="","",INDEX(Anl_A,$AG83)) | W83: =IF($AG83="","",INDEX(Anl_RZ,$AG83)) | X83: =IF($AG83="","",INDEX(Anl_RK,$AG83)) | AF83: =IFERROR(LARGE(Anl_Key,1),"") | AG83: =IF($AF83="","",MATCH($AF83,Anl_Key,0))
D84: 3 | E84: =COUNTIFS(Anl_W,3,Anl_A,1) | F84: =COUNTIFS(Anl_W,3,Anl_A,2) | G84: =COUNTIFS(Anl_W,3,Anl_A,3) | H84: =COUNTIFS(Anl_W,3,Anl_A,4) | I84: =COUNTIFS(Anl_W,3,Anl_A,5) | M84: =IF($AG84="","",2) | N84: =IF($AG84="","",INDEX(Anl_Eq,$AG84)) | P84: =IF($AG84="","",INDEX(Anl_Name,$AG84)) | T84: =IF($AG84="","",INDEX(Anl_Krit,$AG84)) | U84: =IF($AG84="","",INDEX(Anl_W,$AG84)) | V84: =IF($AG84="","",INDEX(Anl_A,$AG84)) | W84: =IF($AG84="","",INDEX(Anl_RZ,$AG84)) | X84: =IF($AG84="","",INDEX(Anl_RK,$AG84)) | AF84: =IFERROR(LARGE(Anl_Key,2),"") | AG84: =IF($AF84="","",MATCH($AF84,Anl_Key,0))
D85: 2 | E85: =COUNTIFS(Anl_W,2,Anl_A,1) | F85: =COUNTIFS(Anl_W,2,Anl_A,2) | G85: =COUNTIFS(Anl_W,2,Anl_A,3) | H85: =COUNTIFS(Anl_W,2,Anl_A,4) | I85: =COUNTIFS(Anl_W,2,Anl_A,5) | M85: =IF($AG85="","",3) | N85: =IF($AG85="","",INDEX(Anl_Eq,$AG85)) | P85: =IF($AG85="","",INDEX(Anl_Name,$AG85)) | T85: =IF($AG85="","",INDEX(Anl_Krit,$AG85)) | U85: =IF($AG85="","",INDEX(Anl_W,$AG85)) | V85: =IF($AG85="","",INDEX(Anl_A,$AG85)) | W85: =IF($AG85="","",INDEX(Anl_RZ,$AG85)) | X85: =IF($AG85="","",INDEX(Anl_RK,$AG85)) | AF85: =IFERROR(LARGE(Anl_Key,3),"") | AG85: =IF($AF85="","",MATCH($AF85,Anl_Key,0))
D86: 1 | E86: =COUNTIFS(Anl_W,1,Anl_A,1) | F86: =COUNTIFS(Anl_W,1,Anl_A,2) | G86: =COUNTIFS(Anl_W,1,Anl_A,3) | H86: =COUNTIFS(Anl_W,1,Anl_A,4) | I86: =COUNTIFS(Anl_W,1,Anl_A,5) | M86: =IF($AG86="","",4) | N86: =IF($AG86="","",INDEX(Anl_Eq,$AG86)) | P86: =IF($AG86="","",INDEX(Anl_Name,$AG86)) | T86: =IF($AG86="","",INDEX(Anl_Krit,$AG86)) | U86: =IF($AG86="","",INDEX(Anl_W,$AG86)) | V86: =IF($AG86="","",INDEX(Anl_A,$AG86)) | W86: =IF($AG86="","",INDEX(Anl_RZ,$AG86)) | X86: =IF($AG86="","",INDEX(Anl_RK,$AG86)) | AF86: =IFERROR(LARGE(Anl_Key,4),"") | AG86: =IF($AF86="","",MATCH($AF86,Anl_Key,0))
E87: 1 | F87: 2 | G87: 3 | H87: 4 | I87: 5 | M87: =IF($AG87="","",5) | N87: =IF($AG87="","",INDEX(Anl_Eq,$AG87)) | P87: =IF($AG87="","",INDEX(Anl_Name,$AG87)) | T87: =IF($AG87="","",INDEX(Anl_Krit,$AG87)) | U87: =IF($AG87="","",INDEX(Anl_W,$AG87)) | V87: =IF($AG87="","",INDEX(Anl_A,$AG87)) | W87: =IF($AG87="","",INDEX(Anl_RZ,$AG87)) | X87: =IF($AG87="","",INDEX(Anl_RK,$AG87)) | AF87: =IFERROR(LARGE(Anl_Key,5),"") | AG87: =IF($AF87="","",MATCH($AF87,Anl_Key,0))
E88: Auswirkung (A) | M88: Bei Gleichstand zählt die Reihenfolge im Blatt „Anlagenübersicht“.
B90: Investitionsbedarf nach empfohlener Option | M90: Kritische Ersatzteile – Bewertung
B91: Option | G91: Anlagen | I91: Investition (€) | M91: Bewertung | T91: Anzahl | V91: Bedeutung
B92: =Einstellungen!$G$65 | G92: =COUNTIF(Anl_Option,B92) | I92: =SUMIFS(Anl_Invest,Anl_Option,B92) | M92: Bestand unter Minimum | T92: =COUNTIF(ET_Status,M92) | V92: sofort nachbestellen
B93: =Einstellungen!$G$66 | G93: =COUNTIF(Anl_Option,B93) | I93: =SUMIFS(Anl_Invest,Anl_Option,B93) | M93: Bestand nicht erfasst | T93: =COUNTIF(ET_Status,M93) | V93: Ist-Bestand erfassen
B94: =Einstellungen!$G$67 | G94: =COUNTIF(Anl_Option,B94) | I94: =SUMIFS(Anl_Invest,Anl_Option,B94) | M94: obsolet ohne Ersatzlösung | T94: =COUNTIF(ET_Status,M94) | V94: Ersatzlösung / Retrofit klären
B95: =Einstellungen!$G$68 | G95: =COUNTIF(Anl_Option,B95) | I95: =SUMIFS(Anl_Invest,Anl_Option,B95) | M95: abgekündigt – Endbevorratung prüfen | T95: =COUNTIF(ET_Status,M95) | V95: Last-Time-Buy prüfen
B96: =Einstellungen!$G$69 | G96: =COUNTIF(Anl_Option,B96) | I96: =SUMIFS(Anl_Invest,Anl_Option,B96) | M96: Alleinlieferant – Lieferung absichern | T96: =COUNTIF(ET_Status,M96) | V96: Rahmenvertrag / Zweitquelle
B97: Gesamt | G97: =SUM(G92:G96) | I97: =SUM(Anl_Invest) | M97: in Ordnung | T97: =COUNTIF(ET_Status,M97) | V97: keine Maßnahme
B99: Risikozahl = Ausfallwahrscheinlichkeit (W, 1–5) × Auswirkung (A, 1–5); Skalen und Klassengrenzen im Blatt „Einstellungen“. Investitionswerte sind Schätzungen aus dem Blatt „Anlagenübersicht“.

Sheet Audit
A1: Anlagenzustandsanalyse – Checkliste
A2: Gelbe Felder ausfüllen. Bewertung je Prüfpunkt: N.I.O · bed. OK · OK · n. b. – die Auswertung steht im Blatt „Dashboard“. | J2: Ergebnis
A3: Werk / Standort | D3: Datum | J3: N.I.O | K3: bed. OK | L3: OK | M3: n. b. | N3: offen | O3: K.O. | P3: Erfüllungsgrad
A4: Anlage / Maschinengruppe | D4: Auditor | J4: =COUNTIF(Aud_Bew,"N.I.O") | K4: =COUNTIF(Aud_Bew,"bed. OK") | L4: =COUNTIF(Aud_Bew,"OK") | M4: =COUNTIF(Aud_Bew,"n. b.") | N4: =COUNTA(Aud_Punkt)-SUM(J4:M4) | O4: =COUNTIFS(Aud_KO,"K.O.",Aud_Bew,"N.I.O") | P4: =IFERROR((SUMIFS(Aud_Gew,Aud_Bew,"OK")+Gewicht_bedOK*SUMIFS(Aud_Gew,Aud_Bew,"bed. OK"))/(SUMIFS(Aud_Gew,Aud_Bew,"N.I.O")+SUMIFS(Aud_Gew,Aud_Bew,"bed. OK")+SUMIFS(Aud_Gew,Aud_Bew,"OK")),"")
A5: Equipment-Nr. (bei Gruppe: alle) | D5: Geltungsbereich | J5: Erfüllungsgrad = Σ(Gewicht × Wertung) ÷ Σ(Gewicht) der mit N.I.O, bed. OK oder OK bewerteten Punkte (OK = 100 %, bed. OK = Gewicht aus „Einstellungen“, N.I.O = 0 %). „n. b.“ und offene Punkte zählen nicht. K.O.-Punkt mit N.I.O ⇒ „kritisch (K.O.)“. | P5: =IF(P4="","nicht bewertet",IF(AND(KO_aktiv="ja",O4>0),"kritisch (K.O.)",IF(P4>=Ampel_gruen,"gut",IF(P4>=Ampel_gelb,"mittel","kritisch"))))
A6: Teilnehmer | D6: Kostenstelle / Bereich
A8: Nr. | B8: Kapitel | C8: Check-Punkt | D8: Check-Punkt (EN) | E8: Normbezug | F8: Gewicht | G8: K.O. | H8: Bewertung | I8: Nachweis / Evidenz | J8: Maßnahmen / Bemerkung | K8: Verantwortlich | L8: Termin | M8: Erledigt | N8: Status | O8: Maßn.-Nr. | P8: Herkunft | Q8: N.I.O-Nr.
A9: =IF(C9="","",COUNTA($C$9:C9)) | B9: Technischer Zustand | C9: Ist der allgemeine Zustand der Maschine in Ordnung (Sauberkeit, Umgebung, Kennzeichnung mit Anlagenbezeichnung / Equipment-Nr.)? | D9: Is the general condition of the machine in order (cleanliness, surroundings, labelling with machine name / equipment no.)? | E9: IATF 7.1.4.1 | F9: 1 | N9: =IF(OR(H9="N.I.O",H9="bed. OK"),IF(M9="ja","erledigt",IF(AND(L9<>"",L9<TODAY()),"überfällig","offen")),"") | O9: =IF(OR(H9="N.I.O",H9="bed. OK"),COUNTIF($H$9:H9,"N.I.O")+COUNTIF($H$9:H9,"bed. OK"),"") | P9: Vorlage M 1 / A1 B6 | Q9: =IF(H9="N.I.O",COUNTIF($H$9:H9,"N.I.O"),"")
A10: =IF(C10="","",COUNTA($C$9:C10)) | B10: Technischer Zustand | C10: Wird das Umfeld der Anlage in einem ordentlichen, sauberen und instand gehaltenen Zustand gehalten (5S, feste Plätze)? | D10: Is the area around the machine kept in an orderly, clean and well-maintained condition (5S, fixed locations)? | E10: IATF 7.1.4.1 | F10: 1 | N10: =IF(OR(H10="N.I.O",H10="bed. OK"),IF(M10="ja","erledigt",IF(AND(L10<>"",L10<TODAY()),"überfällig","offen")),"") | O10: =IF(OR(H10="N.I.O",H10="bed. OK"),COUNTIF($H$9:H10,"N.I.O")+COUNTIF($H$9:H10,"bed. OK"),"") | P10: Vorlage A1 B15 | Q10: =IF(H10="N.I.O",COUNTIF($H$9:H10,"N.I.O"),"")
A11: =IF(C11="","",COUNTA($C$9:C11)) | B11: Technischer Zustand | C11: Sind Funktion und Zustand der Mechanik in Ordnung (Führungen, Lager, Spindeln, Spiel) – bezogen auf die letzte Inspektion? | D11: Are function and condition of the mechanics in order (guides, bearings, spindles, backlash) – based on the last inspection? | E11: DIN 31051 | F11: 2 | N11: =IF(OR(H11="N.I.O",H11="bed. OK"),IF(M11="ja","erledigt",IF(AND(L11<>"",L11<TODAY()),"überfällig","offen")),"") | O11: =IF(OR(H11="N.I.O",H11="bed. OK"),COUNTIF($H$9:H11,"N.I.O")+COUNTIF($H$9:H11,"bed. OK"),"") | P11: Vorlage M 2.5 | Q11: =IF(H11="N.I.O",COUNTIF($H$9:H11,"N.I.O"),"")
A12: =IF(C12="","",COUNTA($C$9:C12)) | B12: Technischer Zustand | C12: Sind Funktion und Zustand der Hydraulik in Ordnung (Dichtheit, Ölzustand, Drücke, Filter)? | D12: Are function and condition of the hydraulics in order (tightness, oil condition, pressures, filters)? | E12: DIN 31051 | F12: 2 | N12: =IF(OR(H12="N.I.O",H12="bed. OK"),IF(M12="ja","erledigt",IF(AND(L12<>"",L12<TODAY()),"überfällig","offen")),"") | O12: =IF(OR(H12="N.I.O",H12="bed. OK"),COUNTIF($H$9:H12,"N.I.O")+COUNTIF($H$9:H12,"bed. OK"),"") | P12: Vorlage M 2.6 | Q12: =IF(H12="N.I.O",COUNTIF($H$9:H12,"N.I.O"),"")
A13: =IF(C13="","",COUNTA($C$9:C13)) | B13: Technischer Zustand | C13: Sind Funktion und Zustand der Pneumatik in Ordnung (Dichtheit, Wartungseinheit, Ventile)? | D13: Are function and condition of the pneumatics in order (tightness, service unit, valves)? | E13: DIN 31051 | F13: 2 | N13: =IF(OR(H13="N.I.O",H13="bed. OK"),IF(M13="ja","erledigt",IF(AND(L13<>"",L13<TODAY()),"überfällig","offen")),"") | O13: =IF(OR(H13="N.I.O",H13="bed. OK"),COUNTIF($H$9:H13,"N.I.O")+COUNTIF($H$9:H13,"bed. OK"),"") | P13: Vorlage M 2.7 | Q13: =IF(H13="N.I.O",COUNTIF($H$9:H13,"N.I.O"),"")
A14: =IF(C14="","",COUNTA($C$9:C14)) | B14: Technischer Zustand | C14: Sind Funktion und Zustand der Elektrik in Ordnung (Schaltschrank, Verkabelung, Klimatisierung, Sensorik)? | D14: Are function and condition of the electrics in order (control cabinet, wiring, air conditioning, sensors)? | E14: DIN 31051 | F14: 2 | N14: =IF(OR(H14="N.I.O",H14="bed. OK"),IF(M14="ja","erledigt",IF(AND(L14<>"",L14<TODAY()),"überfällig","offen")),"") | O14: =IF(OR(H14="N.I.O",H14="bed. OK"),COUNTIF($H$9:H14,"N.I.O")+COUNTIF($H$9:H14,"bed. OK"),"") | P14: Vorlage M 2.8 | Q14: =IF(H14="N.I.O",COUNTIF($H$9:H14,"N.I.O"),"")
A15: =IF(C15="","",COUNTA($C$9:C15)) | B15: Technischer Zustand | C15: Arbeiten Steuerung, Antriebe und Bedienpanel (HMI) zuverlässig, ohne wiederkehrende Fehlermeldungen? | D15: Do the control system, drives and operator panel (HMI) work reliably without recurring error messages? | E15: DIN 31051 | F15: 2 | N15: =IF(OR(H15="N.I.O",H15="bed. OK"),IF(M15="ja","erledigt",IF(AND(L15<>"",L15<TODAY()),"überfällig","offen")),"") | O15: =IF(OR(H15="N.I.O",H15="bed. OK"),COUNTIF($H$9:H15,"N.I.O")+COUNTIF($H$9:H15,"bed. OK"),"") | P15: NEU | Q15: =IF(H15="N.I.O",COUNTIF($H$9:H15,"N.I.O"),"")
A16: =IF(C16="","",COUNTA($C$9:C16)) | B16: Technischer Zustand | C16: Ist die Anlage frei von Auffälligkeiten wie Leckagen, ungewöhnlichen Geräuschen, Vibrationen oder Temperaturen (ggf. aus Zustandsüberwachung)? | D16: Is the machine free of abnormalities such as leaks, unusual noise, vibration or temperatures (from condition monitoring, if available)? | E16: DIN EN 13306 | F16: 2 | N16: =IF(OR(H16="N.I.O",H16="bed. OK"),IF(M16="ja","erledigt",IF(AND(L16<>"",L16<TODAY()),"überfällig","offen")),"") | O16: =IF(OR(H16="N.I.O",H16="bed. OK"),COUNTIF($H$9:H16,"N.I.O")+COUNTIF($H$9:H16,"bed. OK"),"") | P16: NEU | Q16: =IF(H16="N.I.O",COUNTIF($H$9:H16,"N.I.O"),"")
A17: =IF(C17="","",COUNTA($C$9:C17)) | B17: Technischer Zustand | C17: Sind Baujahr, Betriebsstunden und letzte Generalüberholung bekannt und dokumentiert? | D17: Are year of construction, operating hours and the last general overhaul known and documented? | E17: DIN EN 13306 | F17: 1 | N17: =IF(OR(H17="N.I.O",H17="bed. OK"),IF(M17="ja","erledigt",IF(AND(L17<>"",L17<TODAY()),"überfällig","offen")),"") | O17: =IF(OR(H17="N.I.O",H17="bed. OK"),COUNTIF($H$9:H17,"N.I.O")+COUNTIF($H$9:H17,"bed. OK"),"") | P17: NEU | Q17: =IF(H17="N.I.O",COUNTIF($H$9:H17,"N.I.O"),"")
A18: =IF(C18="","",COUNTA($C$9:C18)) | B18: Technischer Zustand | C18: Ist die Maschinen- bzw. Prozessfähigkeit (Cmk / Cpk) für die relevanten Merkmale nachgewiesen und stabil? | D18: Is machine / process capability (Cmk / Cpk) for the relevant characteristics proven and stable? | E18: IATF 9.1.1.1 | F18: 2 | N18: =IF(OR(H18="N.I.O",H18="bed. OK"),IF(M18="ja","erledigt",IF(AND(L18<>"",L18<TODAY()),"überfällig","offen")),"") | O18: =IF(OR(H18="N.I.O",H18="bed. OK"),COUNTIF($H$9:H18,"N.I.O")+COUNTIF($H$9:H18,"bed. OK"),"") | P18: NEU | Q18: =IF(H18="N.I.O",COUNTIF($H$9:H18,"N.I.O"),"")
A19: =IF(C19="","",COUNTA($C$9:C19)) | B19: Betriebsbereitschaft | C19: Ist die Anlage betriebsbereit und für die Produktion freigegeben – ohne Provisorien oder Überbrückungen? | D19: Is the machine ready for operation and released for production – without temporary fixes or bypasses? | E19: IATF 8.5.1.5 | F19: 2 | N19: =IF(OR(H19="N.I.O",H19="bed. OK"),IF(M19="ja","erledigt",IF(AND(L19<>"",L19<TODAY()),"überfällig","offen")),"") | O19: =IF(OR(H19="N.I.O",H19="bed. OK"),COUNTIF($H$9:H19,"N.I.O")+COUNTIF($H$9:H19,"bed. OK"),"") | P19: Vorlage A1 B18 (präzisiert) | Q19: =IF(H19="N.I.O",COUNTIF($H$9:H19,"N.I.O"),"")
A20: =IF(C20="","",COUNTA($C$9:C20)) | B20: Betriebsbereitschaft | C20: Gibt es eine festgelegte Vorgehensweise beim Rüsten (Rüstanweisung, Qualifikationsmatrix)? | D20: Is there a defined set-up procedure (set-up instruction, qualification matrix)? | E20: IATF 8.5.1.3 | F20: 1 | N20: =IF(OR(H20="N.I.O",H20="bed. OK"),IF(M20="ja","erledigt",IF(AND(L20<>"",L20<TODAY()),"überfällig","offen")),"") | O20: =IF(OR(H20="N.I.O",H20="bed. OK"),COUNTIF($H$9:H20,"N.I.O")+COUNTIF($H$9:H20,"bed. OK"),"") | P20: Vorlage M 3 | Q20: =IF(H20="N.I.O",COUNTIF($H$9:H20,"N.I.O"),"")
... A64: =IF(C64="","",COUNTA($C$9:C64)) | B64: Obsoleszenz & Herstellersupport | C64: Ist Fernwartung möglich bzw. sind alternative Dienstleister für die Anlage bekannt? | D64: Is remote service possible or are alternative service providers known for the machine? | E64: IATF 6.1.2.3 | F64: 1 | N64: =IF(OR(H64="N.I.O",H64="bed. OK"),IF(M64="ja","erledigt",IF(AND(L64<>"",L64<TODAY()),"überfällig","offen")),"") | O64: =IF(OR(H64="N.I.O",H64="bed. OK"),COUNTIF($H$9:H64,"N.I.O")+COUNTIF($H$9:H64,"bed. OK"),"") | P64: NEU | Q64: =IF(H64="N.I.O",COUNTIF($H$9:H64,"N.I.O"),"")
A65: =IF(C65="","",COUNTA($C$9:C65)) | B65: Sicherheit & Umwelt | C65: Sind die Sicherheitseinrichtungen an der Anlage vorhanden und wirksam (Schutzhauben, Schutztüren, Lichtgitter)? | D65: Are the safety devices on the machine present and effective (guards, safety doors, light curtains)? | E65: BetrSichV § 4 / § 6 | F65: 3 | G65: K.O. | N65: =IF(OR(H65="N.I.O",H65="bed. OK"),IF(M65="ja","erledigt",IF(AND(L65<>"",L65<TODAY()),"überfällig","offen")),"") | O65: =IF(OR(H65="N.I.O",H65="bed. OK"),COUNTIF($H$9:H65,"N.I.O")+COUNTIF($H$9:H65,"bed. OK"),"") | P65: Vorlage A1 B12 | Q65: =IF(H65="N.I.O",COUNTIF($H$9:H65,"N.I.O"),"")
A66: =IF(C66="","",COUNTA($C$9:C66)) | B66: Sicherheit & Umwelt | C66: Sind Not-Halt und Schutzeinrichtungen nachweislich in festgelegten Intervallen funktionsgeprüft? | D66: Are emergency stop and safety devices demonstrably function-tested at defined intervals? | E66: BetrSichV § 14 | F66: 3 | G66: K.O. | N66: =IF(OR(H66="N.I.O",H66="bed. OK"),IF(M66="ja","erledigt",IF(AND(L66<>"",L66<TODAY()),"überfällig","offen")),"") | O66: =IF(OR(H66="N.I.O",H66="bed. OK"),COUNTIF($H$9:H66,"N.I.O")+COUNTIF($H$9:H66,"bed. OK"),"") | P66: NEU | Q66: =IF(H66="N.I.O",COUNTIF($H$9:H66,"N.I.O"),"")
A67: =IF(C67="","",COUNTA($C$9:C67)) | B67: Sicherheit & Umwelt | C67: Liegen Gefährdungsbeurteilung und Betriebsanweisung aktuell vor; wurde die CE-Konformität nach wesentlichen Veränderungen bewertet? | D67: Are risk assessment and operating instructions up to date; was CE conformity assessed after substantial modifications? | E67: ArbSchG § 5 / BetrSichV § 3 | F67: 3 | G67: K.O. | N67: =IF(OR(H67="N.I.O",H67="bed. OK"),IF(M67="ja","erledigt",IF(AND(L67<>"",L67<TODAY()),"überfällig","offen")),"") | O67: =IF(OR(H67="N.I.O",H67="bed. OK"),COUNTIF($H$9:H67,"N.I.O")+COUNTIF($H$9:H67,"bed. OK"),"") | P67: NEU | Q67: =IF(H67="N.I.O",COUNTIF($H$9:H67,"N.I.O"),"")
A68: =IF(C68="","",COUNTA($C$9:C68)) | B68: Sicherheit & Umwelt | C68: Werden wiederkehrende Prüfungen fristgerecht durchgeführt (z. B. DGUV V3, Druckgeräte, Hebezeuge)? | D68: Are recurring inspections carried out on time (e.g. DGUV V3, pressure equipment, lifting gear)? | E68: BetrSichV § 14 / DGUV V3 | F68: 3 | G68: K.O. | N68: =IF(OR(H68="N.I.O",H68="bed. OK"),IF(M68="ja","erledigt",IF(AND(L68<>"",L68<TODAY()),"überfällig","offen")),"") | O68: =IF(OR(H68="N.I.O",H68="bed. OK"),COUNTIF($H$9:H68,"N.I.O")+COUNTIF($H$9:H68,"bed. OK"),"") | P68: NEU | Q68: =IF(H68="N.I.O",COUNTIF($H$9:H68,"N.I.O"),"")
A69: =IF(C69="","",COUNTA($C$9:C69)) | B69: Sicherheit & Umwelt | C69: Ist das Freischalten und Sichern gegen Wiedereinschalten anlagenspezifisch beschrieben (LOTO, Restenergien)? | D69: Is isolation and securing against restart described for this machine (LOTO, residual energies)? | E69: BetrSichV § 10 | F69: 2 | N69: =IF(OR(H69="N.I.O",H69="bed. OK"),IF(M69="ja","erledigt",IF(AND(L69<>"",L69<TODAY()),"überfällig","offen")),"") | O69: =IF(OR(H69="N.I.O",H69="bed. OK"),COUNTIF($H$9:H69,"N.I.O")+COUNTIF($H$9:H69,"bed. OK"),"") | P69: NEU | Q69: =IF(H69="N.I.O",COUNTIF($H$9:H69,"N.I.O"),"")
A70: =IF(C70="","",COUNTA($C$9:C70)) | B70: Sicherheit & Umwelt | C70: Sind Umweltaspekte beherrscht (keine Leckagen, Auffangwannen, Umgang mit wassergefährdenden Stoffen)? | D70: Are environmental aspects under control (no leaks, drip trays, handling of water-polluting substances)? | E70: AwSV / ISO 14001 | F70: 2 | N70: =IF(OR(H70="N.I.O",H70="bed. OK"),IF(M70="ja","erledigt",IF(AND(L70<>"",L70<TODAY()),"überfällig","offen")),"") | O70: =IF(OR(H70="N.I.O",H70="bed. OK"),COUNTIF($H$9:H70,"N.I.O")+COUNTIF($H$9:H70,"bed. OK"),"") | P70: NEU | Q70: =IF(H70="N.I.O",COUNTIF($H$9:H70,"N.I.O"),"")
A71: =IF(C71="","",COUNTA($C$9:C71)) | B71: Sicherheit & Umwelt | C71: Ist der Brandschutz an der Anlage gewährleistet (Löscheinrichtung, Absaugung, Filterreinigung)? | D71: Is fire protection at the machine ensured (extinguishing system, extraction, filter cleaning)? | E71: ASR A2.2 | F71: 1 | N71: =IF(OR(H71="N.I.O",H71="bed. OK"),IF(M71="ja","erledigt",IF(AND(L71<>"",L71<TODAY()),"überfällig","offen")),"") | O71: =IF(OR(H71="N.I.O",H71="bed. OK"),COUNTIF($H$9:H71,"N.I.O")+COUNTIF($H$9:H71,"bed. OK"),"") | P71: NEU | Q71: =IF(H71="N.I.O",COUNTIF($H$9:H71,"N.I.O"),"")
A72: =IF(C72="","",COUNTA($C$9:C72)) | B72: Produktionsrelevanz & Engpass | C72: Hat die Organisation ermittelt, ob die Anlage für Schlüsselprozesse notwendig ist (Schlüssel- / Engpassanlage)? | D72: Has the organisation determined whether the machine is necessary for key processes (key / bottleneck machine)? | E72: IATF 8.5.1.5 | F72: 2 | N72: =IF(OR(H72="N.I.O",H72="bed. OK"),IF(M72="ja","erledigt",IF(AND(L72<>"",L72<TODAY()),"überfällig","offen")),"") | O72: =IF(OR(H72="N.I.O",H72="bed. OK"),COUNTIF($H$9:H72,"N.I.O")+COUNTIF($H$9:H72,"bed. OK"),"") | P72: Vorlage A1 B13 (Teil) | Q72: =IF(H72="N.I.O",COUNTIF($H$9:H72,"N.I.O"),"")
A73: =IF(C73="","",COUNTA($C$9:C73)) | B73: Produktionsrelevanz & Engpass | C73: Ist die Anlage einer Kritikalitätsklasse (A / B / C) zugeordnet und ist die IH-Strategie daraus abgeleitet? | D73: Is the machine assigned to a criticality class (A / B / C) and is the maintenance strategy derived from it? | E73: DIN EN 13306 | F73: 2 | N73: =IF(OR(H73="N.I.O",H73="bed. OK"),IF(M73="ja","erledigt",IF(AND(L73<>"",L73<TODAY()),"überfällig","offen")),"") | O73: =IF(OR(H73="N.I.O",H73="bed. OK"),COUNTIF($H$9:H73,"N.I.O")+COUNTIF($H$9:H73,"bed. OK"),"") | P73: NEU | Q73: =IF(H73="N.I.O",COUNTIF($H$9:H73,"N.I.O"),"")
A74: =IF(C74="","",COUNTA($C$9:C74)) | B74: Produktionsrelevanz & Engpass | C74: Ist die Produktionsrelevanz dokumentiert (Kunden, Teilenummern, Umsatz- bzw. Stückzahlanteil)? | D74: Is the production relevance documented (customers, part numbers, share of sales / volume)? | E74: IATF 6.1.2.3 | F74: 1 | N74: =IF(OR(H74="N.I.O",H74="bed. OK"),IF(M74="ja","erledigt",IF(AND(L74<>"",L74<TODAY()),"überfällig","offen")),"") | O74: =IF(OR(H74="N.I.O",H74="bed. OK"),COUNTIF($H$9:H74,"N.I.O")+COUNTIF($H$9:H74,"bed. OK"),"") | P74: NEU | Q74: =IF(H74="N.I.O",COUNTIF($H$9:H74,"N.I.O"),"")
A75: =IF(C75="","",COUNTA($C$9:C75)) | B75: Produktionsrelevanz & Engpass | C75: Sind besondere Merkmale bzw. Sonderprozesse auf der Anlage bekannt und ist der IH-Umfang darauf abgestimmt? | D75: Are special characteristics / special processes on the machine known and is maintenance scope aligned with them? | E75: IATF 8.3.3.3 | F75: 1 | N75: =IF(OR(H75="N.I.O",H75="bed. OK"),IF(M75="ja","erledigt",IF(AND(L75<>"",L75<TODAY()),"überfällig","offen")),"") | O75: =IF(OR(H75="N.I.O",H75="bed. OK"),COUNTIF($H$9:H75,"N.I.O")+COUNTIF($H$9:H75,"bed. OK"),"") | P75: NEU | Q75: =IF(H75="N.I.O",COUNTIF($H$9:H75,"N.I.O"),"")
A76: =IF(C76="","",COUNTA($C$9:C76)) | B76: Produktionsrelevanz & Engpass | C76: Ist die Kapazitätsauslastung bekannt und gibt es Reserve, um Ausfälle nachzuholen? | D76: Is the capacity utilisation known and is there reserve capacity to recover from breakdowns? | E76: IATF 6.1.2.3 | F76: 1 | N76: =IF(OR(H76="N.I.O",H76="bed. OK"),IF(M76="ja","erledigt",IF(AND(L76<>"",L76<TODAY()),"überfällig","offen")),"") | O76: =IF(OR(H76="N.I.O",H76="bed. OK"),COUNTIF($H$9:H76,"N.I.O")+COUNTIF($H$9:H76,"bed. OK"),"") | P76: NEU | Q76: =IF(H76="N.I.O",COUNTIF($H$9:H76,"N.I.O"),"")
A77: =IF(C77="","",COUNTA($C$9:C77)) | B77: Ausweichfertigung & Notfall | C77: Gibt es eine Ausweichmöglichkeit (intern / extern) mit ausreichender Kapazität? | D77: Is there an alternative production option (internal / external) with sufficient capacity? | E77: IATF 6.1.2.3 | F77: 2 | N77: =IF(OR(H77="N.I.O",H77="bed. OK"),IF(M77="ja","erledigt",IF(AND(L77<>"",L77<TODAY()),"überfällig","offen")),"") | O77: =IF(OR(H77="N.I.O",H77="bed. OK"),COUNTIF($H$9:H77,"N.I.O")+COUNTIF($H$9:H77,"bed. OK"),"") | P77: NEU | Q77: =IF(H77="N.I.O",COUNTIF($H$9:H77,"N.I.O"),"")
A78: =IF(C78="","",COUNTA($C$9:C78)) | B78: Ausweichfertigung & Notfall | C78: Ist die Ausweichfertigung vom Kunden freigegeben (PPAP / PPF) und ist die Umstellzeit bekannt? | D78: Is the alternative production approved by the customer (PPAP / PPF) and is the changeover time known? | E78: IATF 8.5.6.1.1 | F78: 2 | N78: =IF(OR(H78="N.I.O",H78="bed. OK"),IF(M78="ja","erledigt",IF(AND(L78<>"",L78<TODAY()),"überfällig","offen")),"") | O78: =IF(OR(H78="N.I.O",H78="bed. OK"),COUNTIF($H$9:H78,"N.I.O")+COUNTIF($H$9:H78,"bed. OK"),"") | P78: NEU | Q78: =IF(H78="N.I.O",COUNTIF($H$9:H78,"N.I.O"),"")
A79: =IF(C79="","",COUNTA($C$9:C79)) | B79: Ausweichfertigung & Notfall | C79: Gibt es einen Notfallplan für den Ausfall dieser Anlage? | D79: Is there a contingency plan for a breakdown of this machine? | E79: IATF 6.1.2.3 | F79: 3 | G79: K.O. | N79: =IF(OR(H79="N.I.O",H79="bed. OK"),IF(M79="ja","erledigt",IF(AND(L79<>"",L79<TODAY()),"überfällig","offen")),"") | O79: =IF(OR(H79="N.I.O",H79="bed. OK"),COUNTIF($H$9:H79,"N.I.O")+COUNTIF($H$9:H79,"bed. OK"),"") | P79: NEU | Q79: =IF(H79="N.I.O",COUNTIF($H$9:H79,"N.I.O"),"")
A80: =IF(C80="","",COUNTA($C$9:C80)) | B80: Ausweichfertigung & Notfall | C80: Gibt es einen Wiederanlaufplan mit Zielzeit, Zuständigkeiten und Notfallkontakten (Hersteller, Dienstleister)? | D80: Is there a restart plan with target time, responsibilities and emergency contacts (manufacturer, service providers)? | E80: IATF 6.1.2.3 | F80: 2 | N80: =IF(OR(H80="N.I.O",H80="bed. OK"),IF(M80="ja","erledigt",IF(AND(L80<>"",L80<TODAY()),"überfällig","offen")),"") | O80: =IF(OR(H80="N.I.O",H80="bed. OK"),COUNTIF($H$9:H80,"N.I.O")+COUNTIF($H$9:H80,"bed. OK"),"") | P80: NEU | Q80: =IF(H80="N.I.O",COUNTIF($H$9:H80,"N.I.O"),"")
A81: =IF(C81="","",COUNTA($C$9:C81)) | B81: Ausweichfertigung & Notfall | C81: Wird der Notfallplan regelmäßig (mind. jährlich) getestet bzw. bewertet und aktualisiert? | D81: Is the contingency plan tested / reviewed and updated regularly (at least annually)? | E81: IATF 6.1.2.3 | F81: 1 | N81: =IF(OR(H81="N.I.O",H81="bed. OK"),IF(M81="ja","erledigt",IF(AND(L81<>"",L81<TODAY()),"überfällig","offen")),"") | O81: =IF(OR(H81="N.I.O",H81="bed. OK"),COUNTIF($H$9:H81,"N.I.O")+COUNTIF($H$9:H81,"bed. OK"),"") | P81: NEU | Q81: =IF(H81="N.I.O",COUNTIF($H$9:H81,"N.I.O"),"")
A82: =IF(C82="","",COUNTA($C$9:C82)) | B82: Ausweichfertigung & Notfall | C82: Ist ein Sicherheitsbestand an Fertigteilen bzw. ein Puffer für die erwartete Ausfallzeit festgelegt? | D82: Is a safety stock of finished parts or a buffer for the expected downtime defined? | E82: IATF 6.1.2.3 | F82: 1 | N82: =IF(OR(H82="N.I.O",H82="bed. OK"),IF(M82="ja","erledigt",IF(AND(L82<>"",L82<TODAY()),"überfällig","offen")),"") | O82: =IF(OR(H82="N.I.O",H82="bed. OK"),COUNTIF($H$9:H82,"N.I.O")+COUNTIF($H$9:H82,"bed. OK"),"") | P82: NEU | Q82: =IF(H82="N.I.O",COUNTIF($H$9:H82,"N.I.O"),"")
A83: =IF(C83="","",COUNTA($C$9:C83)) | B83: Ausweichfertigung & Notfall | C83: Sind IT- und Cyberrisiken berücksichtigt (Netzwerkanbindung, Virenschutz, Wiederherstellung)? | D83: Are IT and cyber risks considered (network connection, virus protection, recovery)? | E83: IATF 6.1.2.3 | F83: 1 | N83: =IF(OR(H83="N.I.O",H83="bed. OK"),IF(M83="ja","erledigt",IF(AND(L83<>"",L83<TODAY()),"überfällig","offen")),"") | O83: =IF(OR(H83="N.I.O",H83="bed. OK"),COUNTIF($H$9:H83,"N.I.O")+COUNTIF($H$9:H83,"bed. OK"),"") | P83: NEU | Q83: =IF(H83="N.I.O",COUNTIF($H$9:H83,"N.I.O"),"")
A84: =IF(C84="","",COUNTA($C$9:C84)) | B84: Dokumentation & Software | C84: Wird die technische Dokumentation verwaltet (Stücklisten, Maschinenbeschreibung, technische Zeichnungen)? | D84: Is the technical documentation managed (parts lists, machine description, technical drawings)? | E84: IATF 7.5 | F84: 2 | N84: =IF(OR(H84="N.I.O",H84="bed. OK"),IF(M84="ja","erledigt",IF(AND(L84<>"",L84<TODAY()),"überfällig","offen")),"") | O84: =IF(OR(H84="N.I.O",H84="bed. OK"),COUNTIF($H$9:H84,"N.I.O")+COUNTIF($H$9:H84,"bed. OK"),"") | P84: Vorlage M 2.4 / A1 B17 | Q84: =IF(H84="N.I.O",COUNTIF($H$9:H84,"N.I.O"),"")
A85: =IF(C85="","",COUNTA($C$9:C85)) | B85: Dokumentation & Software | C85: Liegen technische Dokumente auch für Werkzeuge und Ersatzteile vor (Zeichnungen, Stücklisten)? | D85: Are technical documents also available for tools and spare parts (drawings, parts lists)? | E85: IATF 7.5 | F85: 1 | N85: =IF(OR(H85="N.I.O",H85="bed. OK"),IF(M85="ja","erledigt",IF(AND(L85<>"",L85<TODAY()),"überfällig","offen")),"") | O85: =IF(OR(H85="N.I.O",H85="bed. OK"),COUNTIF($H$9:H85,"N.I.O")+COUNTIF($H$9:H85,"bed. OK"),"") | P85: Vorlage A1 F17 / J17 | Q85: =IF(H85="N.I.O",COUNTIF($H$9:H85,"N.I.O"),"")
A86: =IF(C86="","",COUNTA($C$9:C86)) | B86: Dokumentation & Software | C86: Ist die Dokumentation aktuell (Schaltpläne entsprechen dem Ist-Stand, Änderungsstand nach Umbauten)? | D86: Is the documentation up to date (wiring diagrams as built, revision status after modifications)? | E86: IATF 7.5.3 | F86: 2 | N86: =IF(OR(H86="N.I.O",H86="bed. OK"),IF(M86="ja","erledigt",IF(AND(L86<>"",L86<TODAY()),"überfällig","offen")),"") | O86: =IF(OR(H86="N.I.O",H86="bed. OK"),COUNTIF($H$9:H86,"N.I.O")+COUNTIF($H$9:H86,"bed. OK"),"") | P86: NEU | Q86: =IF(H86="N.I.O",COUNTIF($H$9:H86,"N.I.O"),"")
A87: =IF(C87="","",COUNTA($C$9:C87)) | B87: Dokumentation & Software | C87: Ist die Dokumentation im Störfall sofort zugänglich (digital / vor Ort) und liegt die Betriebsanleitung in Landessprache vor? | D87: Is the documentation immediately accessible in case of breakdown (digital / on site) and is the operating manual in the local language? | E87: IATF 7.5.3 | F87: 1 | N87: =IF(OR(H87="N.I.O",H87="bed. OK"),IF(M87="ja","erledigt",IF(AND(L87<>"",L87<TODAY()),"überfällig","offen")),"") | O87: =IF(OR(H87="N.I.O",H87="bed. OK"),COUNTIF($H$9:H87,"N.I.O")+COUNTIF($H$9:H87,"bed. OK"),"") | P87: NEU | Q87: =IF(H87="N.I.O",COUNTIF($H$9:H87,"N.I.O"),"")
A88: =IF(C88="","",COUNTA($C$9:C88)) | B88: Dokumentation & Software | C88: Ist die IH-Historie der Anlage vollständig im System erfasst (Störungen, Reparaturen, Kosten)? | D88: Is the maintenance history of the machine fully recorded in the system (breakdowns, repairs, costs)? | E88: IATF 8.5.1.5 | F88: 1 | N88: =IF(OR(H88="N.I.O",H88="bed. OK"),IF(M88="ja","erledigt",IF(AND(L88<>"",L88<TODAY()),"überfällig","offen")),"") | O88: =IF(OR(H88="N.I.O",H88="bed. OK"),COUNTIF($H$9:H88,"N.I.O")+COUNTIF($H$9:H88,"bed. OK"),"") | P88: NEU | Q88: =IF(H88="N.I.O",COUNTIF($H$9:H88,"N.I.O"),"")
A89: =IF(C89="","",COUNTA($C$9:C89)) | B89: Dokumentation & Software | C89: Werden Programme und Parameter (SPS, NC, Roboter, Antriebe) gesichert und versioniert, und ist die Rücksicherung getestet? | D89: Are programs and parameters (PLC, NC, robot, drives) backed up and versioned, and has restoring been tested? | E89: IATF 6.1.2.3 | F89: 3 | N89: =IF(OR(H89="N.I.O",H89="bed. OK"),IF(M89="ja","erledigt",IF(AND(L89<>"",L89<TODAY()),"überfällig","offen")),"") | O89: =IF(OR(H89="N.I.O",H89="bed. OK"),COUNTIF($H$9:H89,"N.I.O")+COUNTIF($H$9:H89,"bed. OK"),"") | P89: NEU | Q89: =IF(H89="N.I.O",COUNTIF($H$9:H89,"N.I.O"),"")
A90: =IF(C90="","",COUNTA($C$9:C90)) | B90: Personal & Know-how | C90: Werden die Instandhalter anlagenspezifisch geschult? | D90: Are maintenance staff trained specifically for this machine? | E90: IATF 7.2.1 | F90: 2 | N90: =IF(OR(H90="N.I.O",H90="bed. OK"),IF(M90="ja","erledigt",IF(AND(L90<>"",L90<TODAY()),"überfällig","offen")),"") | O90: =IF(OR(H90="N.I.O",H90="bed. OK"),COUNTIF($H$9:H90,"N.I.O")+COUNTIF($H$9:H90,"bed. OK"),"") | P90: Vorlage A1 B16 | Q90: =IF(H90="N.I.O",COUNTIF($H$9:H90,"N.I.O"),"")
A91: =IF(C91="","",COUNTA($C$9:C91)) | B91: Personal & Know-how | C91: Ist die technische Betreuung der Anlage geregelt (Anlagenverantwortlicher benannt)? | D91: Is technical responsibility for the machine defined (machine owner appointed)? | E91: IATF 5.3 | F91: 1 | N91: =IF(OR(H91="N.I.O",H91="bed. OK"),IF(M91="ja","erledigt",IF(AND(L91<>"",L91<TODAY()),"überfällig","offen")),"") | O91: =IF(OR(H91="N.I.O",H91="bed. OK"),COUNTIF($H$9:H91,"N.I.O")+COUNTIF($H$9:H91,"bed. OK"),"") | P91: Vorlage A1 B19 (präzisiert) | Q91: =IF(H91="N.I.O",COUNTIF($H$9:H91,"N.I.O"),"")
... A96: =IF(C96="","",COUNTA($C$9:C96)) | B96: Modernisierung & Investition | C96: Ist der Investitions- bzw. Retrofit-Bedarf ermittelt, bewertet (Optionen, Kosten) und in die Investitionsplanung eingebracht? | D96: Has the investment / retrofit need been determined, assessed (options, costs) and included in investment planning? | E96: IATF 7.1.3.1 | F96: 1 | N96: =IF(OR(H96="N.I.O",H96="bed. OK"),IF(M96="ja","erledigt",IF(AND(L96<>"",L96<TODAY()),"überfällig","offen")),"") | O96: =IF(OR(H96="N.I.O",H96="bed. OK"),COUNTIF($H$9:H96,"N.I.O")+COUNTIF($H$9:H96,"bed. OK"),"") | P96: NEU | Q96: =IF(H96="N.I.O",COUNTIF($H$9:H96,"N.I.O"),"")
A97: =IF(C97="","",COUNTA($C$9:C97)) | F97: 1 | N97: =IF(OR(H97="N.I.O",H97="bed. OK"),IF(M97="ja","erledigt",IF(AND(L97<>"",L97<TODAY()),"überfällig","offen")),"") | O97: =IF(OR(H97="N.I.O",H97="bed. OK"),COUNTIF($H$9:H97,"N.I.O")+COUNTIF($H$9:H97,"bed. OK"),"") | Q97: =IF(H97="N.I.O",COUNTIF($H$9:H97,"N.I.O"),"")
A98: =IF(C98="","",COUNTA($C$9:C98)) | F98: 1 | N98: =IF(OR(H98="N.I.O",H98="bed. OK"),IF(M98="ja","erledigt",IF(AND(L98<>"",L98<TODAY()),"überfällig","offen")),"") | O98: =IF(OR(H98="N.I.O",H98="bed. OK"),COUNTIF($H$9:H98,"N.I.O")+COUNTIF($H$9:H98,"bed. OK"),"") | Q98: =IF(H98="N.I.O",COUNTIF($H$9:H98,"N.I.O"),"")
A99: =IF(C99="","",COUNTA($C$9:C99)) | F99: 1 | N99: =IF(OR(H99="N.I.O",H99="bed. OK"),IF(M99="ja","erledigt",IF(AND(L99<>"",L99<TODAY()),"überfällig","offen")),"") | O99: =IF(OR(H99="N.I.O",H99="bed. OK"),COUNTIF($H$9:H99,"N.I.O")+COUNTIF($H$9:H99,"bed. OK"),"") | Q99: =IF(H99="N.I.O",COUNTIF($H$9:H99,"N.I.O"),"")
A100: =IF(C100="","",COUNTA($C$9:C100)) | F100: 1 | N100: =IF(OR(H100="N.I.O",H100="bed. OK"),IF(M100="ja","erledigt",IF(AND(L100<>"",L100<TODAY()),"überfällig","offen")),"") | O100: =IF(OR(H100="N.I.O",H100="bed. OK"),COUNTIF($H$9:H100,"N.I.O")+COUNTIF($H$9:H100,"bed. OK"),"") | Q100: =IF(H100="N.I.O",COUNTIF($H$9:H100,"N.I.O"),"")
A101: =IF(C101="","",COUNTA($C$9:C101)) | F101: 1 | N101: =IF(OR(H101="N.I.O",H101="bed. OK"),IF(M101="ja","erledigt",IF(AND(L101<>"",L101<TODAY()),"überfällig","offen")),"") | O101: =IF(OR(H101="N.I.O",H101="bed. OK"),COUNTIF($H$9:H101,"N.I.O")+COUNTIF($H$9:H101,"bed. OK"),"") | Q101: =IF(H101="N.I.O",COUNTIF($H$9:H101,"N.I.O"),"")
A102: =IF(C102="","",COUNTA($C$9:C102)) | F102: 1 | N102: =IF(OR(H102="N.I.O",H102="bed. OK"),IF(M102="ja","erledigt",IF(AND(L102<>"",L102<TODAY()),"überfällig","offen")),"") | O102: =IF(OR(H102="N.I.O",H102="bed. OK"),COUNTIF($H$9:H102,"N.I.O")+COUNTIF($H$9:H102,"bed. OK"),"") | Q102: =IF(H102="N.I.O",COUNTIF($H$9:H102,"N.I.O"),"")
A103: =IF(C103="","",COUNTA($C$9:C103)) | F103: 1 | N103: =IF(OR(H103="N.I.O",H103="bed. OK"),IF(M103="ja","erledigt",IF(AND(L103<>"",L103<TODAY()),"überfällig","offen")),"") | O103: =IF(OR(H103="N.I.O",H103="bed. OK"),COUNTIF($H$9:H103,"N.I.O")+COUNTIF($H$9:H103,"bed. OK"),"") | Q103: =IF(H103="N.I.O",COUNTIF($H$9:H103,"N.I.O"),"")
A104: =IF(C104="","",COUNTA($C$9:C104)) | F104: 1 | N104: =IF(OR(H104="N.I.O",H104="bed. OK"),IF(M104="ja","erledigt",IF(AND(L104<>"",L104<TODAY()),"überfällig","offen")),"") | O104: =IF(OR(H104="N.I.O",H104="bed. OK"),COUNTIF($H$9:H104,"N.I.O")+COUNTIF($H$9:H104,"bed. OK"),"") | Q104: =IF(H104="N.I.O",COUNTIF($H$9:H104,"N.I.O"),"")
A105: =IF(C105="","",COUNTA($C$9:C105)) | F105: 1 | N105: =IF(OR(H105="N.I.O",H105="bed. OK"),IF(M105="ja","erledigt",IF(AND(L105<>"",L105<TODAY()),"überfällig","offen")),"") | O105: =IF(OR(H105="N.I.O",H105="bed. OK"),COUNTIF($H$9:H105,"N.I.O")+COUNTIF($H$9:H105,"bed. OK"),"") | Q105: =IF(H105="N.I.O",COUNTIF($H$9:H105,"N.I.O"),"")
A106: =IF(C106="","",COUNTA($C$9:C106)) | F106: 1 | N106: =IF(OR(H106="N.I.O",H106="bed. OK"),IF(M106="ja","erledigt",IF(AND(L106<>"",L106<TODAY()),"überfällig","offen")),"") | O106: =IF(OR(H106="N.I.O",H106="bed. OK"),COUNTIF($H$9:H106,"N.I.O")+COUNTIF($H$9:H106,"bed. OK"),"") | Q106: =IF(H106="N.I.O",COUNTIF($H$9:H106,"N.I.O"),"")
A107: Leere Zeilen oberhalb sind für eigene Prüfpunkte vorbereitet. Weitere Zeilen bitte innerhalb der Liste einfügen (siehe Blatt „Anleitung“).

Sheet Maßnahmen
A1: Maßnahmenplan – Anlagenzustandsanalyse
A2: Füllt sich automatisch aus allen Prüfpunkten mit N.I.O oder bed. OK. Eingaben bitte im Blatt „Audit“ machen.
A4: Nr. | B4: Punkt | C4: Kapitel | D4: Check-Punkt | E4: Bewertung | F4: Befund / Maßnahme | G4: Verantwortlich | H4: Termin | I4: Status
A5: =IF(1<=COUNT(Aud_MNr),1,"") | B5: =IFERROR(IF($A5="","",INDEX(Aud_Nr,MATCH($A5,Aud_MNr,0))),"") | C5: =IFERROR(IF($A5="","",INDEX(Aud_Kapitel,MATCH($A5,Aud_MNr,0))),"") | D5: =IFERROR(IF($A5="","",INDEX(Aud_Punkt,MATCH($A5,Aud_MNr,0))),"") | E5: =IFERROR(IF($A5="","",INDEX(Aud_Bew,MATCH($A5,Aud_MNr,0))),"") | F5: =IFERROR(IF($A5="","",IF(INDEX(Aud_Massn,MATCH($A5,Aud_MNr,0))="","",INDEX(Aud_Massn,MATCH($A5,Aud_MNr,0)))),"") | G5: =IFERROR(IF($A5="","",IF(INDEX(Aud_Verantw,MATCH($A5,Aud_MNr,0))="","",INDEX(Aud_Verantw,MATCH($A5,Aud_MNr,0)))),"") | H5: =IFERROR(IF($A5="","",IF(INDEX(Aud_Termin,MATCH($A5,Aud_MNr,0))="","",INDEX(Aud_Termin,MATCH($A5,Aud_MNr,0)))),"") | I5: =IFERROR(IF($A5="","",INDEX(Aud_Status,MATCH($A5,Aud_MNr,0))),"")
A6: =IF(2<=COUNT(Aud_MNr),2,"") | B6: =IFERROR(IF($A6="","",INDEX(Aud_Nr,MATCH($A6,Aud_MNr,0))),"") | C6: =IFERROR(IF($A6="","",INDEX(Aud_Kapitel,MATCH($A6,Aud_MNr,0))),"") | D6: =IFERROR(IF($A6="","",INDEX(Aud_Punkt,MATCH($A6,Aud_MNr,0))),"") | E6: =IFERROR(IF($A6="","",INDEX(Aud_Bew,MATCH($A6,Aud_MNr,0))),"") | F6: =IFERROR(IF($A6="","",IF(INDEX(Aud_Massn,MATCH($A6,Aud_MNr,0))="","",INDEX(Aud_Massn,MATCH($A6,Aud_MNr,0)))),"") | G6: =IFERROR(IF($A6="","",IF(INDEX(Aud_Verantw,MATCH($A6,Aud_MNr,0))="","",INDEX(Aud_Verantw,MATCH($A6,Aud_MNr,0)))),"") | H6: =IFERROR(IF($A6="","",IF(INDEX(Aud_Termin,MATCH($A6,Aud_MNr,0))="","",INDEX(Aud_Termin,MATCH($A6,Aud_MNr,0)))),"") | I6: =IFERROR(IF($A6="","",INDEX(Aud_Status,MATCH($A6,Aud_MNr,0))),"")
A7: =IF(3<=COUNT(Aud_MNr),3,"") | B7: =IFERROR(IF($A7="","",INDEX(Aud_Nr,MATCH($A7,Aud_MNr,0))),"") | C7: =IFERROR(IF($A7="","",INDEX(Aud_Kapitel,MATCH($A7,Aud_MNr,0))),"") | D7: =IFERROR(IF($A7="","",INDEX(Aud_Punkt,MATCH($A7,Aud_MNr,0))),"") | E7: =IFERROR(IF($A7="","",INDEX(Aud_Bew,MATCH($A7,Aud_MNr,0))),"") | F7: =IFERROR(IF($A7="","",IF(INDEX(Aud_Massn,MATCH($A7,Aud_MNr,0))="","",INDEX(Aud_Massn,MATCH($A7,Aud_MNr,0)))),"") | G7: =IFERROR(IF($A7="","",IF(INDEX(Aud_Verantw,MATCH($A7,Aud_MNr,0))="","",INDEX(Aud_Verantw,MATCH($A7,Aud_MNr,0)))),"") | H7: =IFERROR(IF($A7="","",IF(INDEX(Aud_Termin,MATCH($A7,Aud_MNr,0))="","",INDEX(Aud_Termin,MATCH($A7,Aud_MNr,0)))),"") | I7: =IFERROR(IF($A7="","",INDEX(Aud_Status,MATCH($A7,Aud_MNr,0))),"")
A8: =IF(4<=COUNT(Aud_MNr),4,"") | B8: =IFERROR(IF($A8="","",INDEX(Aud_Nr,MATCH($A8,Aud_MNr,0))),"") | C8: =IFERROR(IF($A8="","",INDEX(Aud_Kapitel,MATCH($A8,Aud_MNr,0))),"") | D8: =IFERROR(IF($A8="","",INDEX(Aud_Punkt,MATCH($A8,Aud_MNr,0))),"") | E8: =IFERROR(IF($A8="","",INDEX(Aud_Bew,MATCH($A8,Aud_MNr,0))),"") | F8: =IFERROR(IF($A8="","",IF(INDEX(Aud_Massn,MATCH($A8,Aud_MNr,0))="","",INDEX(Aud_Massn,MATCH($A8,Aud_MNr,0)))),"") | G8: =IFERROR(IF($A8="","",IF(INDEX(Aud_Verantw,MATCH($A8,Aud_MNr,0))="","",INDEX(Aud_Verantw,MATCH($A8,Aud_MNr,0)))),"") | H8: =IFERROR(IF($A8="","",IF(INDEX(Aud_Termin,MATCH($A8,Aud_MNr,0))="","",INDEX(Aud_Termin,MATCH($A8,Aud_MNr,0)))),"") | I8: =IFERROR(IF($A8="","",INDEX(Aud_Status,MATCH($A8,Aud_MNr,0))),"")
A9: =IF(5<=COUNT(Aud_MNr),5,"") | B9: =IFERROR(IF($A9="","",INDEX(Aud_Nr,MATCH($A9,Aud_MNr,0))),"") | C9: =IFERROR(IF($A9="","",INDEX(Aud_Kapitel,MATCH($A9,Aud_MNr,0))),"") | D9: =IFERROR(IF($A9="","",INDEX(Aud_Punkt,MATCH($A9,Aud_MNr,0))),"") | E9: =IFERROR(IF($A9="","",INDEX(Aud_Bew,MATCH($A9,Aud_MNr,0))),"") | F9: =IFERROR(IF($A9="","",IF(INDEX(Aud_Massn,MATCH($A9,Aud_MNr,0))="","",INDEX(Aud_Massn,MATCH($A9,Aud_MNr,0)))),"") | G9: =IFERROR(IF($A9="","",IF(INDEX(Aud_Verantw,MATCH($A9,Aud_MNr,0))="","",INDEX(Aud_Verantw,MATCH($A9,Aud_MNr,0)))),"") | H9: =IFERROR(IF($A9="","",IF(INDEX(Aud_Termin,MATCH($A9,Aud_MNr,0))="","",INDEX(Aud_Termin,MATCH($A9,Aud_MNr,0)))),"") | I9: =IFERROR(IF($A9="","",INDEX(Aud_Status,MATCH($A9,Aud_MNr,0))),"")
A10: =IF(6<=COUNT(Aud_MNr),6,"") | B10: =IFERROR(IF($A10="","",INDEX(Aud_Nr,MATCH($A10,Aud_MNr,0))),"") | C10: =IFERROR(IF($A10="","",INDEX(Aud_Kapitel,MATCH($A10,Aud_MNr,0))),"") | D10: =IFERROR(IF($A10="","",INDEX(Aud_Punkt,MATCH($A10,Aud_MNr,0))),"") | E10: =IFERROR(IF($A10="","",INDEX(Aud_Bew,MATCH($A10,Aud_MNr,0))),"") | F10: =IFERROR(IF($A10="","",IF(INDEX(Aud_Massn,MATCH($A10,Aud_MNr,0))="","",INDEX(Aud_Massn,MATCH($A10,Aud_MNr,0)))),"") | G10: =IFERROR(IF($A10="","",IF(INDEX(Aud_Verantw,MATCH($A10,Aud_MNr,0))="","",INDEX(Aud_Verantw,MATCH($A10,Aud_MNr,0)))),"") | H10: =IFERROR(IF($A10="","",IF(INDEX(Aud_Termin,MATCH($A10,Aud_MNr,0))="","",INDEX(Aud_Termin,MATCH($A10,Aud_MNr,0)))),"") | I10: =IFERROR(IF($A10="","",INDEX(Aud_Status,MATCH($A10,Aud_MNr,0))),"")
A11: =IF(7<=COUNT(Aud_MNr),7,"") | B11: =IFERROR(IF($A11="","",INDEX(Aud_Nr,MATCH($A11,Aud_MNr,0))),"") | C11: =IFERROR(IF($A11="","",INDEX(Aud_Kapitel,MATCH($A11,Aud_MNr,0))),"") | D11: =IFERROR(IF($A11="","",INDEX(Aud_Punkt,MATCH($A11,Aud_MNr,0))),"") | E11: =IFERROR(IF($A11="","",INDEX(Aud_Bew,MATCH($A11,Aud_MNr,0))),"") | F11: =IFERROR(IF($A11="","",IF(INDEX(Aud_Massn,MATCH($A11,Aud_MNr,0))="","",INDEX(Aud_Massn,MATCH($A11,Aud_MNr,0)))),"") | G11: =IFERROR(IF($A11="","",IF(INDEX(Aud_Verantw,MATCH($A11,Aud_MNr,0))="","",INDEX(Aud_Verantw,MATCH($A11,Aud_MNr,0)))),"") | H11: =IFERROR(IF($A11="","",IF(INDEX(Aud_Termin,MATCH($A11,Aud_MNr,0))="","",INDEX(Aud_Termin,MATCH($A11,Aud_MNr,0)))),"") | I11: =IFERROR(IF($A11="","",INDEX(Aud_Status,MATCH($A11,Aud_MNr,0))),"")
A12: =IF(8<=COUNT(Aud_MNr),8,"") | B12: =IFERROR(IF($A12="","",INDEX(Aud_Nr,MATCH($A12,Aud_MNr,0))),"") | C12: =IFERROR(IF($A12="","",INDEX(Aud_Kapitel,MATCH($A12,Aud_MNr,0))),"") | D12: =IFERROR(IF($A12="","",INDEX(Aud_Punkt,MATCH($A12,Aud_MNr,0))),"") | E12: =IFERROR(IF($A12="","",INDEX(Aud_Bew,MATCH($A12,Aud_MNr,0))),"") | F12: =IFERROR(IF($A12="","",IF(INDEX(Aud_Massn,MATCH($A12,Aud_MNr,0))="","",INDEX(Aud_Massn,MATCH($A12,Aud_MNr,0)))),"") | G12: =IFERROR(IF($A12="","",IF(INDEX(Aud_Verantw,MATCH($A12,Aud_MNr,0))="","",INDEX(Aud_Verantw,MATCH($A12,Aud_MNr,0)))),"") | H12: =IFERROR(IF($A12="","",IF(INDEX(Aud_Termin,MATCH($A12,Aud_MNr,0))="","",INDEX(Aud_Termin,MATCH($A12,Aud_MNr,0)))),"") | I12: =IFERROR(IF($A12="","",INDEX(Aud_Status,MATCH($A12,Aud_MNr,0))),"")
A13: =IF(9<=COUNT(Aud_MNr),9,"") | B13: =IFERROR(IF($A13="","",INDEX(Aud_Nr,MATCH($A13,Aud_MNr,0))),"") | C13: =IFERROR(IF($A13="","",INDEX(Aud_Kapitel,MATCH($A13,Aud_MNr,0))),"") | D13: =IFERROR(IF($A13="","",INDEX(Aud_Punkt,MATCH($A13,Aud_MNr,0))),"") | E13: =IFERROR(IF($A13="","",INDEX(Aud_Bew,MATCH($A13,Aud_MNr,0))),"") | F13: =IFERROR(IF($A13="","",IF(INDEX(Aud_Massn,MATCH($A13,Aud_MNr,0))="","",INDEX(Aud_Massn,MATCH($A13,Aud_MNr,0)))),"") | G13: =IFERROR(IF($A13="","",IF(INDEX(Aud_Verantw,MATCH($A13,Aud_MNr,0))="","",INDEX(Aud_Verantw,MATCH($A13,Aud_MNr,0)))),"") | H13: =IFERROR(IF($A13="","",IF(INDEX(Aud_Termin,MATCH($A13,Aud_MNr,0))="","",INDEX(Aud_Termin,MATCH($A13,Aud_MNr,0)))),"") | I13: =IFERROR(IF($A13="","",INDEX(Aud_Status,MATCH($A13,Aud_MNr,0))),"")
A14: =IF(10<=COUNT(Aud_MNr),10,"") | B14: =IFERROR(IF($A14="","",INDEX(Aud_Nr,MATCH($A14,Aud_MNr,0))),"") | C14: =IFERROR(IF($A14="","",INDEX(Aud_Kapitel,MATCH($A14,Aud_MNr,0))),"") | D14: =IFERROR(IF($A14="","",INDEX(Aud_Punkt,MATCH($A14,Aud_MNr,0))),"") | E14: =IFERROR(IF($A14="","",INDEX(Aud_Bew,MATCH($A14,Aud_MNr,0))),"") | F14: =IFERROR(IF($A14="","",IF(INDEX(Aud_Massn,MATCH($A14,Aud_MNr,0))="","",INDEX(Aud_Massn,MATCH($A14,Aud_MNr,0)))),"") | G14: =IFERROR(IF($A14="","",IF(INDEX(Aud_Verantw,MATCH($A14,Aud_MNr,0))="","",INDEX(Aud_Verantw,MATCH($A14,Aud_MNr,0)))),"") | H14: =IFERROR(IF($A14="","",IF(INDEX(Aud_Termin,MATCH($A14,Aud_MNr,0))="","",INDEX(Aud_Termin,MATCH($A14,Aud_MNr,0)))),"") | I14: =IFERROR(IF($A14="","",INDEX(Aud_Status,MATCH($A14,Aud_MNr,0))),"")
A15: =IF(11<=COUNT(Aud_MNr),11,"") | B15: =IFERROR(IF($A15="","",INDEX(Aud_Nr,MATCH($A15,Aud_MNr,0))),"") | C15: =IFERROR(IF($A15="","",INDEX(Aud_Kapitel,MATCH($A15,Aud_MNr,0))),"") | D15: =IFERROR(IF($A15="","",INDEX(Aud_Punkt,MATCH($A15,Aud_MNr,0))),"") | E15: =IFERROR(IF($A15="","",INDEX(Aud_Bew,MATCH($A15,Aud_MNr,0))),"") | F15: =IFERROR(IF($A15="","",IF(INDEX(Aud_Massn,MATCH($A15,Aud_MNr,0))="","",INDEX(Aud_Massn,MATCH($A15,Aud_MNr,0)))),"") | G15: =IFERROR(IF($A15="","",IF(INDEX(Aud_Verantw,MATCH($A15,Aud_MNr,0))="","",INDEX(Aud_Verantw,MATCH($A15,Aud_MNr,0)))),"") | H15: =IFERROR(IF($A15="","",IF(INDEX(Aud_Termin,MATCH($A15,Aud_MNr,0))="","",INDEX(Aud_Termin,MATCH($A15,Aud_MNr,0)))),"") | I15: =IFERROR(IF($A15="","",INDEX(Aud_Status,MATCH($A15,Aud_MNr,0))),"")
A16: =IF(12<=COUNT(Aud_MNr),12,"") | B16: =IFERROR(IF($A16="","",INDEX(Aud_Nr,MATCH($A16,Aud_MNr,0))),"") | C16: =IFERROR(IF($A16="","",INDEX(Aud_Kapitel,MATCH($A16,Aud_MNr,0))),"") | D16: =IFERROR(IF($A16="","",INDEX(Aud_Punkt,MATCH($A16,Aud_MNr,0))),"") | E16: =IFERROR(IF($A16="","",INDEX(Aud_Bew,MATCH($A16,Aud_MNr,0))),"") | F16: =IFERROR(IF($A16="","",IF(INDEX(Aud_Massn,MATCH($A16,Aud_MNr,0))="","",INDEX(Aud_Massn,MATCH($A16,Aud_MNr,0)))),"") | G16: =IFERROR(IF($A16="","",IF(INDEX(Aud_Verantw,MATCH($A16,Aud_MNr,0))="","",INDEX(Aud_Verantw,MATCH($A16,Aud_MNr,0)))),"") | H16: =IFERROR(IF($A16="","",IF(INDEX(Aud_Termin,MATCH($A16,Aud_MNr,0))="","",INDEX(Aud_Termin,MATCH($A16,Aud_MNr,0)))),"") | I16: =IFERROR(IF($A16="","",INDEX(Aud_Status,MATCH($A16,Aud_MNr,0))),"")
A17: =IF(13<=COUNT(Aud_MNr),13,"") | B17: =IFERROR(IF($A17="","",INDEX(Aud_Nr,MATCH($A17,Aud_MNr,0))),"") | C17: =IFERROR(IF($A17="","",INDEX(Aud_Kapitel,MATCH($A17,Aud_MNr,0))),"") | D17: =IFERROR(IF($A17="","",INDEX(Aud_Punkt,MATCH($A17,Aud_MNr,0))),"") | E17: =IFERROR(IF($A17="","",INDEX(Aud_Bew,MATCH($A17,Aud_MNr,0))),"") | F17: =IFERROR(IF($A17="","",IF(INDEX(Aud_Massn,MATCH($A17,Aud_MNr,0))="","",INDEX(Aud_Massn,MATCH($A17,Aud_MNr,0)))),"") | G17: =IFERROR(IF($A17="","",IF(INDEX(Aud_Verantw,MATCH($A17,Aud_MNr,0))="","",INDEX(Aud_Verantw,MATCH($A17,Aud_MNr,0)))),"") | H17: =IFERROR(IF($A17="","",IF(INDEX(Aud_Termin,MATCH($A17,Aud_MNr,0))="","",INDEX(Aud_Termin,MATCH($A17,Aud_MNr,0)))),"") | I17: =IFERROR(IF($A17="","",INDEX(Aud_Status,MATCH($A17,Aud_MNr,0))),"")
A18: =IF(14<=COUNT(Aud_MNr),14,"") | B18: =IFERROR(IF($A18="","",INDEX(Aud_Nr,MATCH($A18,Aud_MNr,0))),"") | C18: =IFERROR(IF($A18="","",INDEX(Aud_Kapitel,MATCH($A18,Aud_MNr,0))),"") | D18: =IFERROR(IF($A18="","",INDEX(Aud_Punkt,MATCH($A18,Aud_MNr,0))),"") | E18: =IFERROR(IF($A18="","",INDEX(Aud_Bew,MATCH($A18,Aud_MNr,0))),"") | F18: =IFERROR(IF($A18="","",IF(INDEX(Aud_Massn,MATCH($A18,Aud_MNr,0))="","",INDEX(Aud_Massn,MATCH($A18,Aud_MNr,0)))),"") | G18: =IFERROR(IF($A18="","",IF(INDEX(Aud_Verantw,MATCH($A18,Aud_MNr,0))="","",INDEX(Aud_Verantw,MATCH($A18,Aud_MNr,0)))),"") | H18: =IFERROR(IF($A18="","",IF(INDEX(Aud_Termin,MATCH($A18,Aud_MNr,0))="","",INDEX(Aud_Termin,MATCH($A18,Aud_MNr,0)))),"") | I18: =IFERROR(IF($A18="","",INDEX(Aud_Status,MATCH($A18,Aud_MNr,0))),"")
A19: =IF(15<=COUNT(Aud_MNr),15,"") | B19: =IFERROR(IF($A19="","",INDEX(Aud_Nr,MATCH($A19,Aud_MNr,0))),"") | C19: =IFERROR(IF($A19="","",INDEX(Aud_Kapitel,MATCH($A19,Aud_MNr,0))),"") | D19: =IFERROR(IF($A19="","",INDEX(Aud_Punkt,MATCH($A19,Aud_MNr,0))),"") | E19: =IFERROR(IF($A19="","",INDEX(Aud_Bew,MATCH($A19,Aud_MNr,0))),"") | F19: =IFERROR(IF($A19="","",IF(INDEX(Aud_Massn,MATCH($A19,Aud_MNr,0))="","",INDEX(Aud_Massn,MATCH($A19,Aud_MNr,0)))),"") | G19: =IFERROR(IF($A19="","",IF(INDEX(Aud_Verantw,MATCH($A19,Aud_MNr,0))="","",INDEX(Aud_Verantw,MATCH($A19,Aud_MNr,0)))),"") | H19: =IFERROR(IF($A19="","",IF(INDEX(Aud_Termin,MATCH($A19,Aud_MNr,0))="","",INDEX(Aud_Termin,MATCH($A19,Aud_MNr,0)))),"") | I19: =IFERROR(IF($A19="","",INDEX(Aud_Status,MATCH($A19,Aud_MNr,0))),"")
A20: =IF(16<=COUNT(Aud_MNr),16,"") | B20: =IFERROR(IF($A20="","",INDEX(Aud_Nr,MATCH($A20,Aud_MNr,0))),"") | C20: =IFERROR(IF($A20="","",INDEX(Aud_Kapitel,MATCH($A20,Aud_MNr,0))),"") | D20: =IFERROR(IF($A20="","",INDEX(Aud_Punkt,MATCH($A20,Aud_MNr,0))),"") | E20: =IFERROR(IF($A20="","",INDEX(Aud_Bew,MATCH($A20,Aud_MNr,0))),"") | F20: =IFERROR(IF($A20="","",IF(INDEX(Aud_Massn,MATCH($A20,Aud_MNr,0))="","",INDEX(Aud_Massn,MATCH($A20,Aud_MNr,0)))),"") | G20: =IFERROR(IF($A20="","",IF(INDEX(Aud_Verantw,MATCH($A20,Aud_MNr,0))="","",INDEX(Aud_Verantw,MATCH($A20,Aud_MNr,0)))),"") | H20: =IFERROR(IF($A20="","",IF(INDEX(Aud_Termin,MATCH($A20,Aud_MNr,0))="","",INDEX(Aud_Termin,MATCH($A20,Aud_MNr,0)))),"") | I20: =IFERROR(IF($A20="","",INDEX(Aud_Status,MATCH($A20,Aud_MNr,0))),"")
A21: =IF(17<=COUNT(Aud_MNr),17,"") | B21: =IFERROR(IF($A21="","",INDEX(Aud_Nr,MATCH($A21,Aud_MNr,0))),"") | C21: =IFERROR(IF($A21="","",INDEX(Aud_Kapitel,MATCH($A21,Aud_MNr,0))),"") | D21: =IFERROR(IF($A21="","",INDEX(Aud_Punkt,MATCH($A21,Aud_MNr,0))),"") | E21: =IFERROR(IF($A21="","",INDEX(Aud_Bew,MATCH($A21,Aud_MNr,0))),"") | F21: =IFERROR(IF($A21="","",IF(INDEX(Aud_Massn,MATCH($A21,Aud_MNr,0))="","",INDEX(Aud_Massn,MATCH($A21,Aud_MNr,0)))),"") | G21: =IFERROR(IF($A21="","",IF(INDEX(Aud_Verantw,MATCH($A21,Aud_MNr,0))="","",INDEX(Aud_Verantw,MATCH($A21,Aud_MNr,0)))),"") | H21: =IFERROR(IF($A21="","",IF(INDEX(Aud_Termin,MATCH($A21,Aud_MNr,0))="","",INDEX(Aud_Termin,MATCH($A21,Aud_MNr,0)))),"") | I21: =IFERROR(IF($A21="","",INDEX(Aud_Status,MATCH($A21,Aud_MNr,0))),"")
A22: =IF(18<=COUNT(Aud_MNr),18,"") | B22: =IFERROR(IF($A22="","",INDEX(Aud_Nr,MATCH($A22,Aud_MNr,0))),"") | C22: =IFERROR(IF($A22="","",INDEX(Aud_Kapitel,MATCH($A22,Aud_MNr,0))),"") | D22: =IFERROR(IF($A22="","",INDEX(Aud_Punkt,MATCH($A22,Aud_MNr,0))),"") | E22: =IFERROR(IF($A22="","",INDEX(Aud_Bew,MATCH($A22,Aud_MNr,0))),"") | F22: =IFERROR(IF($A22="","",IF(INDEX(Aud_Massn,MATCH($A22,Aud_MNr,0))="","",INDEX(Aud_Massn,MATCH($A22,Aud_MNr,0)))),"") | G22: =IFERROR(IF($A22="","",IF(INDEX(Aud_Verantw,MATCH($A22,Aud_MNr,0))="","",INDEX(Aud_Verantw,MATCH($A22,Aud_MNr,0)))),"") | H22: =IFERROR(IF($A22="","",IF(INDEX(Aud_Termin,MATCH($A22,Aud_MNr,0))="","",INDEX(Aud_Termin,MATCH($A22,Aud_MNr,0)))),"") | I22: =IFERROR(IF($A22="","",INDEX(Aud_Status,MATCH($A22,Aud_MNr,0))),"")
A23: =IF(19<=COUNT(Aud_MNr),19,"") | B23: =IFERROR(IF($A23="","",INDEX(Aud_Nr,MATCH($A23,Aud_MNr,0))),"") | C23: =IFERROR(IF($A23="","",INDEX(Aud_Kapitel,MATCH($A23,Aud_MNr,0))),"") | D23: =IFERROR(IF($A23="","",INDEX(Aud_Punkt,MATCH($A23,Aud_MNr,0))),"") | E23: =IFERROR(IF($A23="","",INDEX(Aud_Bew,MATCH($A23,Aud_MNr,0))),"") | F23: =IFERROR(IF($A23="","",IF(INDEX(Aud_Massn,MATCH($A23,Aud_MNr,0))="","",INDEX(Aud_Massn,MATCH($A23,Aud_MNr,0)))),"") | G23: =IFERROR(IF($A23="","",IF(INDEX(Aud_Verantw,MATCH($A23,Aud_MNr,0))="","",INDEX(Aud_Verantw,MATCH($A23,Aud_MNr,0)))),"") | H23: =IFERROR(IF($A23="","",IF(INDEX(Aud_Termin,MATCH($A23,Aud_MNr,0))="","",INDEX(Aud_Termin,MATCH($A23,Aud_MNr,0)))),"") | I23: =IFERROR(IF($A23="","",INDEX(Aud_Status,MATCH($A23,Aud_MNr,0))),"")
A24: =IF(20<=COUNT(Aud_MNr),20,"") | B24: =IFERROR(IF($A24="","",INDEX(Aud_Nr,MATCH($A24,Aud_MNr,0))),"") | C24: =IFERROR(IF($A24="","",INDEX(Aud_Kapitel,MATCH($A24,Aud_MNr,0))),"") | D24: =IFERROR(IF($A24="","",INDEX(Aud_Punkt,MATCH($A24,Aud_MNr,0))),"") | E24: =IFERROR(IF($A24="","",INDEX(Aud_Bew,MATCH($A24,Aud_MNr,0))),"") | F24: =IFERROR(IF($A24="","",IF(INDEX(Aud_Massn,MATCH($A24,Aud_MNr,0))="","",INDEX(Aud_Massn,MATCH($A24,Aud_MNr,0)))),"") | G24: =IFERROR(IF($A24="","",IF(INDEX(Aud_Verantw,MATCH($A24,Aud_MNr,0))="","",INDEX(Aud_Verantw,MATCH($A24,Aud_MNr,0)))),"") | H24: =IFERROR(IF($A24="","",IF(INDEX(Aud_Termin,MATCH($A24,Aud_MNr,0))="","",INDEX(Aud_Termin,MATCH($A24,Aud_MNr,0)))),"") | I24: =IFERROR(IF($A24="","",INDEX(Aud_Status,MATCH($A24,Aud_MNr,0))),"")
A25: =IF(21<=COUNT(Aud_MNr),21,"") | B25: =IFERROR(IF($A25="","",INDEX(Aud_Nr,MATCH($A25,Aud_MNr,0))),"") | C25: =IFERROR(IF($A25="","",INDEX(Aud_Kapitel,MATCH($A25,Aud_MNr,0))),"") | D25: =IFERROR(IF($A25="","",INDEX(Aud_Punkt,MATCH($A25,Aud_MNr,0))),"") | E25: =IFERROR(IF($A25="","",INDEX(Aud_Bew,MATCH($A25,Aud_MNr,0))),"") | F25: =IFERROR(IF($A25="","",IF(INDEX(Aud_Massn,MATCH($A25,Aud_MNr,0))="","",INDEX(Aud_Massn,MATCH($A25,Aud_MNr,0)))),"") | G25: =IFERROR(IF($A25="","",IF(INDEX(Aud_Verantw,MATCH($A25,Aud_MNr,0))="","",INDEX(Aud_Verantw,MATCH($A25,Aud_MNr,0)))),"") | H25: =IFERROR(IF($A25="","",IF(INDEX(Aud_Termin,MATCH($A25,Aud_MNr,0))="","",INDEX(Aud_Termin,MATCH($A25,Aud_MNr,0)))),"") | I25: =IFERROR(IF($A25="","",INDEX(Aud_Status,MATCH($A25,Aud_MNr,0))),"")
A26: =IF(22<=COUNT(Aud_MNr),22,"") | B26: =IFERROR(IF($A26="","",INDEX(Aud_Nr,MATCH($A26,Aud_MNr,0))),"") | C26: =IFERROR(IF($A26="","",INDEX(Aud_Kapitel,MATCH($A26,Aud_MNr,0))),"") | D26: =IFERROR(IF($A26="","",INDEX(Aud_Punkt,MATCH($A26,Aud_MNr,0))),"") | E26: =IFERROR(IF($A26="","",INDEX(Aud_Bew,MATCH($A26,Aud_MNr,0))),"") | F26: =IFERROR(IF($A26="","",IF(INDEX(Aud_Massn,MATCH($A26,Aud_MNr,0))="","",INDEX(Aud_Massn,MATCH($A26,Aud_MNr,0)))),"") | G26: =IFERROR(IF($A26="","",IF(INDEX(Aud_Verantw,MATCH($A26,Aud_MNr,0))="","",INDEX(Aud_Verantw,MATCH($A26,Aud_MNr,0)))),"") | H26: =IFERROR(IF($A26="","",IF(INDEX(Aud_Termin,MATCH($A26,Aud_MNr,0))="","",INDEX(Aud_Termin,MATCH($A26,Aud_MNr,0)))),"") | I26: =IFERROR(IF($A26="","",INDEX(Aud_Status,MATCH($A26,Aud_MNr,0))),"")
A27: =IF(23<=COUNT(Aud_MNr),23,"") | B27: =IFERROR(IF($A27="","",INDEX(Aud_Nr,MATCH($A27,Aud_MNr,0))),"") | C27: =IFERROR(IF($A27="","",INDEX(Aud_Kapitel,MATCH($A27,Aud_MNr,0))),"") | D27: =IFERROR(IF($A27="","",INDEX(Aud_Punkt,MATCH($A27,Aud_MNr,0))),"") | E27: =IFERROR(IF($A27="","",INDEX(Aud_Bew,MATCH($A27,Aud_MNr,0))),"") | F27: =IFERROR(IF($A27="","",IF(INDEX(Aud_Massn,MATCH($A27,Aud_MNr,0))="","",INDEX(Aud_Massn,MATCH($A27,Aud_MNr,0)))),"") | G27: =IFERROR(IF($A27="","",IF(INDEX(Aud_Verantw,MATCH($A27,Aud_MNr,0))="","",INDEX(Aud_Verantw,MATCH($A27,Aud_MNr,0)))),"") | H27: =IFERROR(IF($A27="","",IF(INDEX(Aud_Termin,MATCH($A27,Aud_MNr,0))="","",INDEX(Aud_Termin,MATCH($A27,Aud_MNr,0)))),"") | I27: =IFERROR(IF($A27="","",INDEX(Aud_Status,MATCH($A27,Aud_MNr,0))),"")
A28: =IF(24<=COUNT(Aud_MNr),24,"") | B28: =IFERROR(IF($A28="","",INDEX(Aud_Nr,MATCH($A28,Aud_MNr,0))),"") | C28: =IFERROR(IF($A28="","",INDEX(Aud_Kapitel,MATCH($A28,Aud_MNr,0))),"") | D28: =IFERROR(IF($A28="","",INDEX(Aud_Punkt,MATCH($A28,Aud_MNr,0))),"") | E28: =IFERROR(IF($A28="","",INDEX(Aud_Bew,MATCH($A28,Aud_MNr,0))),"") | F28: =IFERROR(IF($A28="","",IF(INDEX(Aud_Massn,MATCH($A28,Aud_MNr,0))="","",INDEX(Aud_Massn,MATCH($A28,Aud_MNr,0)))),"") | G28: =IFERROR(IF($A28="","",IF(INDEX(Aud_Verantw,MATCH($A28,Aud_MNr,0))="","",INDEX(Aud_Verantw,MATCH($A28,Aud_MNr,0)))),"") | H28: =IFERROR(IF($A28="","",IF(INDEX(Aud_Termin,MATCH($A28,Aud_MNr,0))="","",INDEX(Aud_Termin,MATCH($A28,Aud_MNr,0)))),"") | I28: =IFERROR(IF($A28="","",INDEX(Aud_Status,MATCH($A28,Aud_MNr,0))),"")
A29: =IF(25<=COUNT(Aud_MNr),25,"") | B29: =IFERROR(IF($A29="","",INDEX(Aud_Nr,MATCH($A29,Aud_MNr,0))),"") | C29: =IFERROR(IF($A29="","",INDEX(Aud_Kapitel,MATCH($A29,Aud_MNr,0))),"") | D29: =IFERROR(IF($A29="","",INDEX(Aud_Punkt,MATCH($A29,Aud_MNr,0))),"") | E29: =IFERROR(IF($A29="","",INDEX(Aud_Bew,MATCH($A29,Aud_MNr,0))),"") | F29: =IFERROR(IF($A29="","",IF(INDEX(Aud_Massn,MATCH($A29,Aud_MNr,0))="","",INDEX(Aud_Massn,MATCH($A29,Aud_MNr,0)))),"") | G29: =IFERROR(IF($A29="","",IF(INDEX(Aud_Verantw,MATCH($A29,Aud_MNr,0))="","",INDEX(Aud_Verantw,MATCH($A29,Aud_MNr,0)))),"") | H29: =IFERROR(IF($A29="","",IF(INDEX(Aud_Termin,MATCH($A29,Aud_MNr,0))="","",INDEX(Aud_Termin,MATCH($A29,Aud_MNr,0)))),"") | I29: =IFERROR(IF($A29="","",INDEX(Aud_Status,MATCH($A29,Aud_MNr,0))),"")
A30: =IF(26<=COUNT(Aud_MNr),26,"") | B30: =IFERROR(IF($A30="","",INDEX(Aud_Nr,MATCH($A30,Aud_MNr,0))),"") | C30: =IFERROR(IF($A30="","",INDEX(Aud_Kapitel,MATCH($A30,Aud_MNr,0))),"") | D30: =IFERROR(IF($A30="","",INDEX(Aud_Punkt,MATCH($A30,Aud_MNr,0))),"") | E30: =IFERROR(IF($A30="","",INDEX(Aud_Bew,MATCH($A30,Aud_MNr,0))),"") | F30: =IFERROR(IF($A30="","",IF(INDEX(Aud_Massn,MATCH($A30,Aud_MNr,0))="","",INDEX(Aud_Massn,MATCH($A30,Aud_MNr,0)))),"") | G30: =IFERROR(IF($A30="","",IF(INDEX(Aud_Verantw,MATCH($A30,Aud_MNr,0))="","",INDEX(Aud_Verantw,MATCH($A30,Aud_MNr,0)))),"") | H30: =IFERROR(IF($A30="","",IF(INDEX(Aud_Termin,MATCH($A30,Aud_MNr,0))="","",INDEX(Aud_Termin,MATCH($A30,Aud_MNr,0)))),"") | I30: =IFERROR(IF($A30="","",INDEX(Aud_Status,MATCH($A30,Aud_MNr,0))),"")
A31: =IF(27<=COUNT(Aud_MNr),27,"") | B31: =IFERROR(IF($A31="","",INDEX(Aud_Nr,MATCH($A31,Aud_MNr,0))),"") | C31: =IFERROR(IF($A31="","",INDEX(Aud_Kapitel,MATCH($A31,Aud_MNr,0))),"") | D31: =IFERROR(IF($A31="","",INDEX(Aud_Punkt,MATCH($A31,Aud_MNr,0))),"") | E31: =IFERROR(IF($A31="","",INDEX(Aud_Bew,MATCH($A31,Aud_MNr,0))),"") | F31: =IFERROR(IF($A31="","",IF(INDEX(Aud_Massn,MATCH($A31,Aud_MNr,0))="","",INDEX(Aud_Massn,MATCH($A31,Aud_MNr,0)))),"") | G31: =IFERROR(IF($A31="","",IF(INDEX(Aud_Verantw,MATCH($A31,Aud_MNr,0))="","",INDEX(Aud_Verantw,MATCH($A31,Aud_MNr,0)))),"") | H31: =IFERROR(IF($A31="","",IF(INDEX(Aud_Termin,MATCH($A31,Aud_MNr,0))="","",INDEX(Aud_Termin,MATCH($A31,Aud_MNr,0)))),"") | I31: =IFERROR(IF($A31="","",INDEX(Aud_Status,MATCH($A31,Aud_MNr,0))),"")
A32: =IF(28<=COUNT(Aud_MNr),28,"") | B32: =IFERROR(IF($A32="","",INDEX(Aud_Nr,MATCH($A32,Aud_MNr,0))),"") | C32: =IFERROR(IF($A32="","",INDEX(Aud_Kapitel,MATCH($A32,Aud_MNr,0))),"") | D32: =IFERROR(IF($A32="","",INDEX(Aud_Punkt,MATCH($A32,Aud_MNr,0))),"") | E32: =IFERROR(IF($A32="","",INDEX(Aud_Bew,MATCH($A32,Aud_MNr,0))),"") | F32: =IFERROR(IF($A32="","",IF(INDEX(Aud_Massn,MATCH($A32,Aud_MNr,0))="","",INDEX(Aud_Massn,MATCH($A32,Aud_MNr,0)))),"") | G32: =IFERROR(IF($A32="","",IF(INDEX(Aud_Verantw,MATCH($A32,Aud_MNr,0))="","",INDEX(Aud_Verantw,MATCH($A32,Aud_MNr,0)))),"") | H32: =IFERROR(IF($A32="","",IF(INDEX(Aud_Termin,MATCH($A32,Aud_MNr,0))="","",INDEX(Aud_Termin,MATCH($A32,Aud_MNr,0)))),"") | I32: =IFERROR(IF($A32="","",INDEX(Aud_Status,MATCH($A32,Aud_MNr,0))),"")
A33: =IF(29<=COUNT(Aud_MNr),29,"") | B33: =IFERROR(IF($A33="","",INDEX(Aud_Nr,MATCH($A33,Aud_MNr,0))),"") | C33: =IFERROR(IF($A33="","",INDEX(Aud_Kapitel,MATCH($A33,Aud_MNr,0))),"") | D33: =IFERROR(IF($A33="","",INDEX(Aud_Punkt,MATCH($A33,Aud_MNr,0))),"") | E33: =IFERROR(IF($A33="","",INDEX(Aud_Bew,MATCH($A33,Aud_MNr,0))),"") | F33: =IFERROR(IF($A33="","",IF(INDEX(Aud_Massn,MATCH($A33,Aud_MNr,0))="","",INDEX(Aud_Massn,MATCH($A33,Aud_MNr,0)))),"") | G33: =IFERROR(IF($A33="","",IF(INDEX(Aud_Verantw,MATCH($A33,Aud_MNr,0))="","",INDEX(Aud_Verantw,MATCH($A33,Aud_MNr,0)))),"") | H33: =IFERROR(IF($A33="","",IF(INDEX(Aud_Termin,MATCH($A33,Aud_MNr,0))="","",INDEX(Aud_Termin,MATCH($A33,Aud_MNr,0)))),"") | I33: =IFERROR(IF($A33="","",INDEX(Aud_Status,MATCH($A33,Aud_MNr,0))),"")
A34: =IF(30<=COUNT(Aud_MNr),30,"") | B34: =IFERROR(IF($A34="","",INDEX(Aud_Nr,MATCH($A34,Aud_MNr,0))),"") | C34: =IFERROR(IF($A34="","",INDEX(Aud_Kapitel,MATCH($A34,Aud_MNr,0))),"") | D34: =IFERROR(IF($A34="","",INDEX(Aud_Punkt,MATCH($A34,Aud_MNr,0))),"") | E34: =IFERROR(IF($A34="","",INDEX(Aud_Bew,MATCH($A34,Aud_MNr,0))),"") | F34: =IFERROR(IF($A34="","",IF(INDEX(Aud_Massn,MATCH($A34,Aud_MNr,0))="","",INDEX(Aud_Massn,MATCH($A34,Aud_MNr,0)))),"") | G34: =IFERROR(IF($A34="","",IF(INDEX(Aud_Verantw,MATCH($A34,Aud_MNr,0))="","",INDEX(Aud_Verantw,MATCH($A34,Aud_MNr,0)))),"") | H34: =IFERROR(IF($A34="","",IF(INDEX(Aud_Termin,MATCH($A34,Aud_MNr,0))="","",INDEX(Aud_Termin,MATCH($A34,Aud_MNr,0)))),"") | I34: =IFERROR(IF($A34="","",INDEX(Aud_Status,MATCH($A34,Aud_MNr,0))),"")
A35: =IF(31<=COUNT(Aud_MNr),31,"") | B35: =IFERROR(IF($A35="","",INDEX(Aud_Nr,MATCH($A35,Aud_MNr,0))),"") | C35: =IFERROR(IF($A35="","",INDEX(Aud_Kapitel,MATCH($A35,Aud_MNr,0))),"") | D35: =IFERROR(IF($A35="","",INDEX(Aud_Punkt,MATCH($A35,Aud_MNr,0))),"") | E35: =IFERROR(IF($A35="","",INDEX(Aud_Bew,MATCH($A35,Aud_MNr,0))),"") | F35: =IFERROR(IF($A35="","",IF(INDEX(Aud_Massn,MATCH($A35,Aud_MNr,0))="","",INDEX(Aud_Massn,MATCH($A35,Aud_MNr,0)))),"") | G35: =IFERROR(IF($A35="","",IF(INDEX(Aud_Verantw,MATCH($A35,Aud_MNr,0))="","",INDEX(Aud_Verantw,MATCH($A35,Aud_MNr,0)))),"") | H35: =IFERROR(IF($A35="","",IF(INDEX(Aud_Termin,MATCH($A35,Aud_MNr,0))="","",INDEX(Aud_Termin,MATCH($A35,Aud_MNr,0)))),"") | I35: =IFERROR(IF($A35="","",INDEX(Aud_Status,MATCH($A35,Aud_MNr,0))),"")
A36: =IF(32<=COUNT(Aud_MNr),32,"") | B36: =IFERROR(IF($A36="","",INDEX(Aud_Nr,MATCH($A36,Aud_MNr,0))),"") | C36: =IFERROR(IF($A36="","",INDEX(Aud_Kapitel,MATCH($A36,Aud_MNr,0))),"") | D36: =IFERROR(IF($A36="","",INDEX(Aud_Punkt,MATCH($A36,Aud_MNr,0))),"") | E36: =IFERROR(IF($A36="","",INDEX(Aud_Bew,MATCH($A36,Aud_MNr,0))),"") | F36: =IFERROR(IF($A36="","",IF(INDEX(Aud_Massn,MATCH($A36,Aud_MNr,0))="","",INDEX(Aud_Massn,MATCH($A36,Aud_MNr,0)))),"") | G36: =IFERROR(IF($A36="","",IF(INDEX(Aud_Verantw,MATCH($A36,Aud_MNr,0))="","",INDEX(Aud_Verantw,MATCH($A36,Aud_MNr,0)))),"") | H36: =IFERROR(IF($A36="","",IF(INDEX(Aud_Termin,MATCH($A36,Aud_MNr,0))="","",INDEX(Aud_Termin,MATCH($A36,Aud_MNr,0)))),"") | I36: =IFERROR(IF($A36="","",INDEX(Aud_Status,MATCH($A36,Aud_MNr,0))),"")
A37: =IF(33<=COUNT(Aud_MNr),33,"") | B37: =IFERROR(IF($A37="","",INDEX(Aud_Nr,MATCH($A37,Aud_MNr,0))),"") | C37: =IFERROR(IF($A37="","",INDEX(Aud_Kapitel,MATCH($A37,Aud_MNr,0))),"") | D37: =IFERROR(IF($A37="","",INDEX(Aud_Punkt,MATCH($A37,Aud_MNr,0))),"") | E37: =IFERROR(IF($A37="","",INDEX(Aud_Bew,MATCH($A37,Aud_MNr,0))),"") | F37: =IFERROR(IF($A37="","",IF(INDEX(Aud_Massn,MATCH($A37,Aud_MNr,0))="","",INDEX(Aud_Massn,MATCH($A37,Aud_MNr,0)))),"") | G37: =IFERROR(IF($A37="","",IF(INDEX(Aud_Verantw,MATCH($A37,Aud_MNr,0))="","",INDEX(Aud_Verantw,MATCH($A37,Aud_MNr,0)))),"") | H37: =IFERROR(IF($A37="","",IF(INDEX(Aud_Termin,MATCH($A37,Aud_MNr,0))="","",INDEX(Aud_Termin,MATCH($A37,Aud_MNr,0)))),"") | I37: =IFERROR(IF($A37="","",INDEX(Aud_Status,MATCH($A37,Aud_MNr,0))),"")
A38: =IF(34<=COUNT(Aud_MNr),34,"") | B38: =IFERROR(IF($A38="","",INDEX(Aud_Nr,MATCH($A38,Aud_MNr,0))),"") | C38: =IFERROR(IF($A38="","",INDEX(Aud_Kapitel,MATCH($A38,Aud_MNr,0))),"") | D38: =IFERROR(IF($A38="","",INDEX(Aud_Punkt,MATCH($A38,Aud_MNr,0))),"") | E38: =IFERROR(IF($A38="","",INDEX(Aud_Bew,MATCH($A38,Aud_MNr,0))),"") | F38: =IFERROR(IF($A38="","",IF(INDEX(Aud_Massn,MATCH($A38,Aud_MNr,0))="","",INDEX(Aud_Massn,MATCH($A38,Aud_MNr,0)))),"") | G38: =IFERROR(IF($A38="","",IF(INDEX(Aud_Verantw,MATCH($A38,Aud_MNr,0))="","",INDEX(Aud_Verantw,MATCH($A38,Aud_MNr,0)))),"") | H38: =IFERROR(IF($A38="","",IF(INDEX(Aud_Termin,MATCH($A38,Aud_MNr,0))="","",INDEX(Aud_Termin,MATCH($A38,Aud_MNr,0)))),"") | I38: =IFERROR(IF($A38="","",INDEX(Aud_Status,MATCH($A38,Aud_MNr,0))),"")
A39: =IF(35<=COUNT(Aud_MNr),35,"") | B39: =IFERROR(IF($A39="","",INDEX(Aud_Nr,MATCH($A39,Aud_MNr,0))),"") | C39: =IFERROR(IF($A39="","",INDEX(Aud_Kapitel,MATCH($A39,Aud_MNr,0))),"") | D39: =IFERROR(IF($A39="","",INDEX(Aud_Punkt,MATCH($A39,Aud_MNr,0))),"") | E39: =IFERROR(IF($A39="","",INDEX(Aud_Bew,MATCH($A39,Aud_MNr,0))),"") | F39: =IFERROR(IF($A39="","",IF(INDEX(Aud_Massn,MATCH($A39,Aud_MNr,0))="","",INDEX(Aud_Massn,MATCH($A39,Aud_MNr,0)))),"") | G39: =IFERROR(IF($A39="","",IF(INDEX(Aud_Verantw,MATCH($A39,Aud_MNr,0))="","",INDEX(Aud_Verantw,MATCH($A39,Aud_MNr,0)))),"") | H39: =IFERROR(IF($A39="","",IF(INDEX(Aud_Termin,MATCH($A39,Aud_MNr,0))="","",INDEX(Aud_Termin,MATCH($A39,Aud_MNr,0)))),"") | I39: =IFERROR(IF($A39="","",INDEX(Aud_Status,MATCH($A39,Aud_MNr,0))),"")
A40: =IF(36<=COUNT(Aud_MNr),36,"") | B40: =IFERROR(IF($A40="","",INDEX(Aud_Nr,MATCH($A40,Aud_MNr,0))),"") | C40: =IFERROR(IF($A40="","",INDEX(Aud_Kapitel,MATCH($A40,Aud_MNr,0))),"") | D40: =IFERROR(IF($A40="","",INDEX(Aud_Punkt,MATCH($A40,Aud_MNr,0))),"") | E40: =IFERROR(IF($A40="","",INDEX(Aud_Bew,MATCH($A40,Aud_MNr,0))),"") | F40: =IFERROR(IF($A40="","",IF(INDEX(Aud_Massn,MATCH($A40,Aud_MNr,0))="","",INDEX(Aud_Massn,MATCH($A40,Aud_MNr,0)))),"") | G40: =IFERROR(IF($A40="","",IF(INDEX(Aud_Verantw,MATCH($A40,Aud_MNr,0))="","",INDEX(Aud_Verantw,MATCH($A40,Aud_MNr,0)))),"") | H40: =IFERROR(IF($A40="","",IF(INDEX(Aud_Termin,MATCH($A40,Aud_MNr,0))="","",INDEX(Aud_Termin,MATCH($A40,Aud_MNr,0)))),"") | I40: =IFERROR(IF($A40="","",INDEX(Aud_Status,MATCH($A40,Aud_MNr,0))),"")
A41: =IF(37<=COUNT(Aud_MNr),37,"") | B41: =IFERROR(IF($A41="","",INDEX(Aud_Nr,MATCH($A41,Aud_MNr,0))),"") | C41: =IFERROR(IF($A41="","",INDEX(Aud_Kapitel,MATCH($A41,Aud_MNr,0))),"") | D41: =IFERROR(IF($A41="","",INDEX(Aud_Punkt,MATCH($A41,Aud_MNr,0))),"") | E41: =IFERROR(IF($A41="","",INDEX(Aud_Bew,MATCH($A41,Aud_MNr,0))),"") | F41: =IFERROR(IF($A41="","",IF(INDEX(Aud_Massn,MATCH($A41,Aud_MNr,0))="","",INDEX(Aud_Massn,MATCH($A41,Aud_MNr,0)))),"") | G41: =IFERROR(IF($A41="","",IF(INDEX(Aud_Verantw,MATCH($A41,Aud_MNr,0))="","",INDEX(Aud_Verantw,MATCH($A41,Aud_MNr,0)))),"") | H41: =IFERROR(IF($A41="","",IF(INDEX(Aud_Termin,MATCH($A41,Aud_MNr,0))="","",INDEX(Aud_Termin,MATCH($A41,Aud_MNr,0)))),"") | I41: =IFERROR(IF($A41="","",INDEX(Aud_Status,MATCH($A41,Aud_MNr,0))),"")
A42: =IF(38<=COUNT(Aud_MNr),38,"") | B42: =IFERROR(IF($A42="","",INDEX(Aud_Nr,MATCH($A42,Aud_MNr,0))),"") | C42: =IFERROR(IF($A42="","",INDEX(Aud_Kapitel,MATCH($A42,Aud_MNr,0))),"") | D42: =IFERROR(IF($A42="","",INDEX(Aud_Punkt,MATCH($A42,Aud_MNr,0))),"") | E42: =IFERROR(IF($A42="","",INDEX(Aud_Bew,MATCH($A42,Aud_MNr,0))),"") | F42: =IFERROR(IF($A42="","",IF(INDEX(Aud_Massn,MATCH($A42,Aud_MNr,0))="","",INDEX(Aud_Massn,MATCH($A42,Aud_MNr,0)))),"") | G42: =IFERROR(IF($A42="","",IF(INDEX(Aud_Verantw,MATCH($A42,Aud_MNr,0))="","",INDEX(Aud_Verantw,MATCH($A42,Aud_MNr,0)))),"") | H42: =IFERROR(IF($A42="","",IF(INDEX(Aud_Termin,MATCH($A42,Aud_MNr,0))="","",INDEX(Aud_Termin,MATCH($A42,Aud_MNr,0)))),"") | I42: =IFERROR(IF($A42="","",INDEX(Aud_Status,MATCH($A42,Aud_MNr,0))),"")
A43: =IF(39<=COUNT(Aud_MNr),39,"") | B43: =IFERROR(IF($A43="","",INDEX(Aud_Nr,MATCH($A43,Aud_MNr,0))),"") | C43: =IFERROR(IF($A43="","",INDEX(Aud_Kapitel,MATCH($A43,Aud_MNr,0))),"") | D43: =IFERROR(IF($A43="","",INDEX(Aud_Punkt,MATCH($A43,Aud_MNr,0))),"") | E43: =IFERROR(IF($A43="","",INDEX(Aud_Bew,MATCH($A43,Aud_MNr,0))),"") | F43: =IFERROR(IF($A43="","",IF(INDEX(Aud_Massn,MATCH($A43,Aud_MNr,0))="","",INDEX(Aud_Massn,MATCH($A43,Aud_MNr,0)))),"") | G43: =IFERROR(IF($A43="","",IF(INDEX(Aud_Verantw,MATCH($A43,Aud_MNr,0))="","",INDEX(Aud_Verantw,MATCH($A43,Aud_MNr,0)))),"") | H43: =IFERROR(IF($A43="","",IF(INDEX(Aud_Termin,MATCH($A43,Aud_MNr,0))="","",INDEX(Aud_Termin,MATCH($A43,Aud_MNr,0)))),"") | I43: =IFERROR(IF($A43="","",INDEX(Aud_Status,MATCH($A43,Aud_MNr,0))),"")
A44: =IF(40<=COUNT(Aud_MNr),40,"") | B44: =IFERROR(IF($A44="","",INDEX(Aud_Nr,MATCH($A44,Aud_MNr,0))),"") | C44: =IFERROR(IF($A44="","",INDEX(Aud_Kapitel,MATCH($A44,Aud_MNr,0))),"") | D44: =IFERROR(IF($A44="","",INDEX(Aud_Punkt,MATCH($A44,Aud_MNr,0))),"") | E44: =IFERROR(IF($A44="","",INDEX(Aud_Bew,MATCH($A44,Aud_MNr,0))),"") | F44: =IFERROR(IF($A44="","",IF(INDEX(Aud_Massn,MATCH($A44,Aud_MNr,0))="","",INDEX(Aud_Massn,MATCH($A44,Aud_MNr,0)))),"") | G44: =IFERROR(IF($A44="","",IF(INDEX(Aud_Verantw,MATCH($A44,Aud_MNr,0))="","",INDEX(Aud_Verantw,MATCH($A44,Aud_MNr,0)))),"") | H44: =IFERROR(IF($A44="","",IF(INDEX(Aud_Termin,MATCH($A44,Aud_MNr,0))="","",INDEX(Aud_Termin,MATCH($A44,Aud_MNr,0)))),"") | I44: =IFERROR(IF($A44="","",INDEX(Aud_Status,MATCH($A44,Aud_MNr,0))),"")
A45: =IF(41<=COUNT(Aud_MNr),41,"") | B45: =IFERROR(IF($A45="","",INDEX(Aud_Nr,MATCH($A45,Aud_MNr,0))),"") | C45: =IFERROR(IF($A45="","",INDEX(Aud_Kapitel,MATCH($A45,Aud_MNr,0))),"") | D45: =IFERROR(IF($A45="","",INDEX(Aud_Punkt,MATCH($A45,Aud_MNr,0))),"") | E45: =IFERROR(IF($A45="","",INDEX(Aud_Bew,MATCH($A45,Aud_MNr,0))),"") | F45: =IFERROR(IF($A45="","",IF(INDEX(Aud_Massn,MATCH($A45,Aud_MNr,0))="","",INDEX(Aud_Massn,MATCH($A45,Aud_MNr,0)))),"") | G45: =IFERROR(IF($A45="","",IF(INDEX(Aud_Verantw,MATCH($A45,Aud_MNr,0))="","",INDEX(Aud_Verantw,MATCH($A45,Aud_MNr,0)))),"") | H45: =IFERROR(IF($A45="","",IF(INDEX(Aud_Termin,MATCH($A45,Aud_MNr,0))="","",INDEX(Aud_Termin,MATCH($A45,Aud_MNr,0)))),"") | I45: =IFERROR(IF($A45="","",INDEX(Aud_Status,MATCH($A45,Aud_MNr,0))),"")
A46: =IF(42<=COUNT(Aud_MNr),42,"") | B46: =IFERROR(IF($A46="","",INDEX(Aud_Nr,MATCH($A46,Aud_MNr,0))),"") | C46: =IFERROR(IF($A46="","",INDEX(Aud_Kapitel,MATCH($A46,Aud_MNr,0))),"") | D46: =IFERROR(IF($A46="","",INDEX(Aud_Punkt,MATCH($A46,Aud_MNr,0))),"") | E46: =IFERROR(IF($A46="","",INDEX(Aud_Bew,MATCH($A46,Aud_MNr,0))),"") | F46: =IFERROR(IF($A46="","",IF(INDEX(Aud_Massn,MATCH($A46,Aud_MNr,0))="","",INDEX(Aud_Massn,MATCH($A46,Aud_MNr,0)))),"") | G46: =IFERROR(IF($A46="","",IF(INDEX(Aud_Verantw,MATCH($A46,Aud_MNr,0))="","",INDEX(Aud_Verantw,MATCH($A46,Aud_MNr,0)))),"") | H46: =IFERROR(IF($A46="","",IF(INDEX(Aud_Termin,MATCH($A46,Aud_MNr,0))="","",INDEX(Aud_Termin,MATCH($A46,Aud_MNr,0)))),"") | I46: =IFERROR(IF($A46="","",INDEX(Aud_Status,MATCH($A46,Aud_MNr,0))),"")
A47: =IF(43<=COUNT(Aud_MNr),43,"") | B47: =IFERROR(IF($A47="","",INDEX(Aud_Nr,MATCH($A47,Aud_MNr,0))),"") | C47: =IFERROR(IF($A47="","",INDEX(Aud_Kapitel,MATCH($A47,Aud_MNr,0))),"") | D47: =IFERROR(IF($A47="","",INDEX(Aud_Punkt,MATCH($A47,Aud_MNr,0))),"") | E47: =IFERROR(IF($A47="","",INDEX(Aud_Bew,MATCH($A47,Aud_MNr,0))),"") | F47: =IFERROR(IF($A47="","",IF(INDEX(Aud_Massn,MATCH($A47,Aud_MNr,0))="","",INDEX(Aud_Massn,MATCH($A47,Aud_MNr,0)))),"") | G47: =IFERROR(IF($A47="","",IF(INDEX(Aud_Verantw,MATCH($A47,Aud_MNr,0))="","",INDEX(Aud_Verantw,MATCH($A47,Aud_MNr,0)))),"") | H47: =IFERROR(IF($A47="","",IF(INDEX(Aud_Termin,MATCH($A47,Aud_MNr,0))="","",INDEX(Aud_Termin,MATCH($A47,Aud_MNr,0)))),"") | I47: =IFERROR(IF($A47="","",INDEX(Aud_Status,MATCH($A47,Aud_MNr,0))),"")
A48: =IF(44<=COUNT(Aud_MNr),44,"") | B48: =IFERROR(IF($A48="","",INDEX(Aud_Nr,MATCH($A48,Aud_MNr,0))),"") | C48: =IFERROR(IF($A48="","",INDEX(Aud_Kapitel,MATCH($A48,Aud_MNr,0))),"") | D48: =IFERROR(IF($A48="","",INDEX(Aud_Punkt,MATCH($A48,Aud_MNr,0))),"") | E48: =IFERROR(IF($A48="","",INDEX(Aud_Bew,MATCH($A48,Aud_MNr,0))),"") | F48: =IFERROR(IF($A48="","",IF(INDEX(Aud_Massn,MATCH($A48,Aud_MNr,0))="","",INDEX(Aud_Massn,MATCH($A48,Aud_MNr,0)))),"") | G48: =IFERROR(IF($A48="","",IF(INDEX(Aud_Verantw,MATCH($A48,Aud_MNr,0))="","",INDEX(Aud_Verantw,MATCH($A48,Aud_MNr,0)))),"") | H48: =IFERROR(IF($A48="","",IF(INDEX(Aud_Termin,MATCH($A48,Aud_MNr,0))="","",INDEX(Aud_Termin,MATCH($A48,Aud_MNr,0)))),"") | I48: =IFERROR(IF($A48="","",INDEX(Aud_Status,MATCH($A48,Aud_MNr,0))),"")
A49: =IF(45<=COUNT(Aud_MNr),45,"") | B49: =IFERROR(IF($A49="","",INDEX(Aud_Nr,MATCH($A49,Aud_MNr,0))),"") | C49: =IFERROR(IF($A49="","",INDEX(Aud_Kapitel,MATCH($A49,Aud_MNr,0))),"") | D49: =IFERROR(IF($A49="","",INDEX(Aud_Punkt,MATCH($A49,Aud_MNr,0))),"") | E49: =IFERROR(IF($A49="","",INDEX(Aud_Bew,MATCH($A49,Aud_MNr,0))),"") | F49: =IFERROR(IF($A49="","",IF(INDEX(Aud_Massn,MATCH($A49,Aud_MNr,0))="","",INDEX(Aud_Massn,MATCH($A49,Aud_MNr,0)))),"") | G49: =IFERROR(IF($A49="","",IF(INDEX(Aud_Verantw,MATCH($A49,Aud_MNr,0))="","",INDEX(Aud_Verantw,MATCH($A49,Aud_MNr,0)))),"") | H49: =IFERROR(IF($A49="","",IF(INDEX(Aud_Termin,MATCH($A49,Aud_MNr,0))="","",INDEX(Aud_Termin,MATCH($A49,Aud_MNr,0)))),"") | I49: =IFERROR(IF($A49="","",INDEX(Aud_Status,MATCH($A49,Aud_MNr,0))),"")
A50: =IF(46<=COUNT(Aud_MNr),46,"") | B50: =IFERROR(IF($A50="","",INDEX(Aud_Nr,MATCH($A50,Aud_MNr,0))),"") | C50: =IFERROR(IF($A50="","",INDEX(Aud_Kapitel,MATCH($A50,Aud_MNr,0))),"") | D50: =IFERROR(IF($A50="","",INDEX(Aud_Punkt,MATCH($A50,Aud_MNr,0))),"") | E50: =IFERROR(IF($A50="","",INDEX(Aud_Bew,MATCH($A50,Aud_MNr,0))),"") | F50: =IFERROR(IF($A50="","",IF(INDEX(Aud_Massn,MATCH($A50,Aud_MNr,0))="","",INDEX(Aud_Massn,MATCH($A50,Aud_MNr,0)))),"") | G50: =IFERROR(IF($A50="","",IF(INDEX(Aud_Verantw,MATCH($A50,Aud_MNr,0))="","",INDEX(Aud_Verantw,MATCH($A50,Aud_MNr,0)))),"") | H50: =IFERROR(IF($A50="","",IF(INDEX(Aud_Termin,MATCH($A50,Aud_MNr,0))="","",INDEX(Aud_Termin,MATCH($A50,Aud_MNr,0)))),"") | I50: =IFERROR(IF($A50="","",INDEX(Aud_Status,MATCH($A50,Aud_MNr,0))),"")
A51: =IF(47<=COUNT(Aud_MNr),47,"") | B51: =IFERROR(IF($A51="","",INDEX(Aud_Nr,MATCH($A51,Aud_MNr,0))),"") | C51: =IFERROR(IF($A51="","",INDEX(Aud_Kapitel,MATCH($A51,Aud_MNr,0))),"") | D51: =IFERROR(IF($A51="","",INDEX(Aud_Punkt,MATCH($A51,Aud_MNr,0))),"") | E51: =IFERROR(IF($A51="","",INDEX(Aud_Bew,MATCH($A51,Aud_MNr,0))),"") | F51: =IFERROR(IF($A51="","",IF(INDEX(Aud_Massn,MATCH($A51,Aud_MNr,0))="","",INDEX(Aud_Massn,MATCH($A51,Aud_MNr,0)))),"") | G51: =IFERROR(IF($A51="","",IF(INDEX(Aud_Verantw,MATCH($A51,Aud_MNr,0))="","",INDEX(Aud_Verantw,MATCH($A51,Aud_MNr,0)))),"") | H51: =IFERROR(IF($A51="","",IF(INDEX(Aud_Termin,MATCH($A51,Aud_MNr,0))="","",INDEX(Aud_Termin,MATCH($A51,Aud_MNr,0)))),"") | I51: =IFERROR(IF($A51="","",INDEX(Aud_Status,MATCH($A51,Aud_MNr,0))),"")
A52: =IF(48<=COUNT(Aud_MNr),48,"") | B52: =IFERROR(IF($A52="","",INDEX(Aud_Nr,MATCH($A52,Aud_MNr,0))),"") | C52: =IFERROR(IF($A52="","",INDEX(Aud_Kapitel,MATCH($A52,Aud_MNr,0))),"") | D52: =IFERROR(IF($A52="","",INDEX(Aud_Punkt,MATCH($A52,Aud_MNr,0))),"") | E52: =IFERROR(IF($A52="","",INDEX(Aud_Bew,MATCH($A52,Aud_MNr,0))),"") | F52: =IFERROR(IF($A52="","",IF(INDEX(Aud_Massn,MATCH($A52,Aud_MNr,0))="","",INDEX(Aud_Massn,MATCH($A52,Aud_MNr,0)))),"") | G52: =IFERROR(IF($A52="","",IF(INDEX(Aud_Verantw,MATCH($A52,Aud_MNr,0))="","",INDEX(Aud_Verantw,MATCH($A52,Aud_MNr,0)))),"") | H52: =IFERROR(IF($A52="","",IF(INDEX(Aud_Termin,MATCH($A52,Aud_MNr,0))="","",INDEX(Aud_Termin,MATCH($A52,Aud_MNr,0)))),"") | I52: =IFERROR(IF($A52="","",INDEX(Aud_Status,MATCH($A52,Aud_MNr,0))),"")
A53: =IF(49<=COUNT(Aud_MNr),49,"") | B53: =IFERROR(IF($A53="","",INDEX(Aud_Nr,MATCH($A53,Aud_MNr,0))),"") | C53: =IFERROR(IF($A53="","",INDEX(Aud_Kapitel,MATCH($A53,Aud_MNr,0))),"") | D53: =IFERROR(IF($A53="","",INDEX(Aud_Punkt,MATCH($A53,Aud_MNr,0))),"") | E53: =IFERROR(IF($A53="","",INDEX(Aud_Bew,MATCH($A53,Aud_MNr,0))),"") | F53: =IFERROR(IF($A53="","",IF(INDEX(Aud_Massn,MATCH($A53,Aud_MNr,0))="","",INDEX(Aud_Massn,MATCH($A53,Aud_MNr,0)))),"") | G53: =IFERROR(IF($A53="","",IF(INDEX(Aud_Verantw,MATCH($A53,Aud_MNr,0))="","",INDEX(Aud_Verantw,MATCH($A53,Aud_MNr,0)))),"") | H53: =IFERROR(IF($A53="","",IF(INDEX(Aud_Termin,MATCH($A53,Aud_MNr,0))="","",INDEX(Aud_Termin,MATCH($A53,Aud_MNr,0)))),"") | I53: =IFERROR(IF($A53="","",INDEX(Aud_Status,MATCH($A53,Aud_MNr,0))),"")
A54: =IF(50<=COUNT(Aud_MNr),50,"") | B54: =IFERROR(IF($A54="","",INDEX(Aud_Nr,MATCH($A54,Aud_MNr,0))),"") | C54: =IFERROR(IF($A54="","",INDEX(Aud_Kapitel,MATCH($A54,Aud_MNr,0))),"") | D54: =IFERROR(IF($A54="","",INDEX(Aud_Punkt,MATCH($A54,Aud_MNr,0))),"") | E54: =IFERROR(IF($A54="","",INDEX(Aud_Bew,MATCH($A54,Aud_MNr,0))),"") | F54: =IFERROR(IF($A54="","",IF(INDEX(Aud_Massn,MATCH($A54,Aud_MNr,0))="","",INDEX(Aud_Massn,MATCH($A54,Aud_MNr,0)))),"") | G54: =IFERROR(IF($A54="","",IF(INDEX(Aud_Verantw,MATCH($A54,Aud_MNr,0))="","",INDEX(Aud_Verantw,MATCH($A54,Aud_MNr,0)))),"") | H54: =IFERROR(IF($A54="","",IF(INDEX(Aud_Termin,MATCH($A54,Aud_MNr,0))="","",INDEX(Aud_Termin,MATCH($A54,Aud_MNr,0)))),"") | I54: =IFERROR(IF($A54="","",INDEX(Aud_Status,MATCH($A54,Aud_MNr,0))),"")
A55: =IF(51<=COUNT(Aud_MNr),51,"") | B55: =IFERROR(IF($A55="","",INDEX(Aud_Nr,MATCH($A55,Aud_MNr,0))),"") | C55: =IFERROR(IF($A55="","",INDEX(Aud_Kapitel,MATCH($A55,Aud_MNr,0))),"") | D55: =IFERROR(IF($A55="","",INDEX(Aud_Punkt,MATCH($A55,Aud_MNr,0))),"") | E55: =IFERROR(IF($A55="","",INDEX(Aud_Bew,MATCH($A55,Aud_MNr,0))),"") | F55: =IFERROR(IF($A55="","",IF(INDEX(Aud_Massn,MATCH($A55,Aud_MNr,0))="","",INDEX(Aud_Massn,MATCH($A55,Aud_MNr,0)))),"") | G55: =IFERROR(IF($A55="","",IF(INDEX(Aud_Verantw,MATCH($A55,Aud_MNr,0))="","",INDEX(Aud_Verantw,MATCH($A55,Aud_MNr,0)))),"") | H55: =IFERROR(IF($A55="","",IF(INDEX(Aud_Termin,MATCH($A55,Aud_MNr,0))="","",INDEX(Aud_Termin,MATCH($A55,Aud_MNr,0)))),"") | I55: =IFERROR(IF($A55="","",INDEX(Aud_Status,MATCH($A55,Aud_MNr,0))),"")
A56: =IF(52<=COUNT(Aud_MNr),52,"") | B56: =IFERROR(IF($A56="","",INDEX(Aud_Nr,MATCH($A56,Aud_MNr,0))),"") | C56: =IFERROR(IF($A56="","",INDEX(Aud_Kapitel,MATCH($A56,Aud_MNr,0))),"") | D56: =IFERROR(IF($A56="","",INDEX(Aud_Punkt,MATCH($A56,Aud_MNr,0))),"") | E56: =IFERROR(IF($A56="","",INDEX(Aud_Bew,MATCH($A56,Aud_MNr,0))),"") | F56: =IFERROR(IF($A56="","",IF(INDEX(Aud_Massn,MATCH($A56,Aud_MNr,0))="","",INDEX(Aud_Massn,MATCH($A56,Aud_MNr,0)))),"") | G56: =IFERROR(IF($A56="","",IF(INDEX(Aud_Verantw,MATCH($A56,Aud_MNr,0))="","",INDEX(Aud_Verantw,MATCH($A56,Aud_MNr,0)))),"") | H56: =IFERROR(IF($A56="","",IF(INDEX(Aud_Termin,MATCH($A56,Aud_MNr,0))="","",INDEX(Aud_Termin,MATCH($A56,Aud_MNr,0)))),"") | I56: =IFERROR(IF($A56="","",INDEX(Aud_Status,MATCH($A56,Aud_MNr,0))),"")
A57: =IF(53<=COUNT(Aud_MNr),53,"") | B57: =IFERROR(IF($A57="","",INDEX(Aud_Nr,MATCH($A57,Aud_MNr,0))),"") | C57: =IFERROR(IF($A57="","",INDEX(Aud_Kapitel,MATCH($A57,Aud_MNr,0))),"") | D57: =IFERROR(IF($A57="","",INDEX(Aud_Punkt,MATCH($A57,Aud_MNr,0))),"") | E57: =IFERROR(IF($A57="","",INDEX(Aud_Bew,MATCH($A57,Aud_MNr,0))),"") | F57: =IFERROR(IF($A57="","",IF(INDEX(Aud_Massn,MATCH($A57,Aud_MNr,0))="","",INDEX(Aud_Massn,MATCH($A57,Aud_MNr,0)))),"") | G57: =IFERROR(IF($A57="","",IF(INDEX(Aud_Verantw,MATCH($A57,Aud_MNr,0))="","",INDEX(Aud_Verantw,MATCH($A57,Aud_MNr,0)))),"") | H57: =IFERROR(IF($A57="","",IF(INDEX(Aud_Termin,MATCH($A57,Aud_MNr,0))="","",INDEX(Aud_Termin,MATCH($A57,Aud_MNr,0)))),"") | I57: =IFERROR(IF($A57="","",INDEX(Aud_Status,MATCH($A57,Aud_MNr,0))),"")
A58: =IF(54<=COUNT(Aud_MNr),54,"") | B58: =IFERROR(IF($A58="","",INDEX(Aud_Nr,MATCH($A58,Aud_MNr,0))),"") | C58: =IFERROR(IF($A58="","",INDEX(Aud_Kapitel,MATCH($A58,Aud_MNr,0))),"") | D58: =IFERROR(IF($A58="","",INDEX(Aud_Punkt,MATCH($A58,Aud_MNr,0))),"") | E58: =IFERROR(IF($A58="","",INDEX(Aud_Bew,MATCH($A58,Aud_MNr,0))),"") | F58: =IFERROR(IF($A58="","",IF(INDEX(Aud_Massn,MATCH($A58,Aud_MNr,0))="","",INDEX(Aud_Massn,MATCH($A58,Aud_MNr,0)))),"") | G58: =IFERROR(IF($A58="","",IF(INDEX(Aud_Verantw,MATCH($A58,Aud_MNr,0))="","",INDEX(Aud_Verantw,MATCH($A58,Aud_MNr,0)))),"") | H58: =IFERROR(IF($A58="","",IF(INDEX(Aud_Termin,MATCH($A58,Aud_MNr,0))="","",INDEX(Aud_Termin,MATCH($A58,Aud_MNr,0)))),"") | I58: =IFERROR(IF($A58="","",INDEX(Aud_Status,MATCH($A58,Aud_MNr,0))),"")
A59: =IF(55<=COUNT(Aud_MNr),55,"") | B59: =IFERROR(IF($A59="","",INDEX(Aud_Nr,MATCH($A59,Aud_MNr,0))),"") | C59: =IFERROR(IF($A59="","",INDEX(Aud_Kapitel,MATCH($A59,Aud_MNr,0))),"") | D59: =IFERROR(IF($A59="","",INDEX(Aud_Punkt,MATCH($A59,Aud_MNr,0))),"") | E59: =IFERROR(IF($A59="","",INDEX(Aud_Bew,MATCH($A59,Aud_MNr,0))),"") | F59: =IFERROR(IF($A59="","",IF(INDEX(Aud_Massn,MATCH($A59,Aud_MNr,0))="","",INDEX(Aud_Massn,MATCH($A59,Aud_MNr,0)))),"") | G59: =IFERROR(IF($A59="","",IF(INDEX(Aud_Verantw,MATCH($A59,Aud_MNr,0))="","",INDEX(Aud_Verantw,MATCH($A59,Aud_MNr,0)))),"") | H59: =IFERROR(IF($A59="","",IF(INDEX(Aud_Termin,MATCH($A59,Aud_MNr,0))="","",INDEX(Aud_Termin,MATCH($A59,Aud_MNr,0)))),"") | I59: =IFERROR(IF($A59="","",INDEX(Aud_Status,MATCH($A59,Aud_MNr,0))),"")
A60: =IF(56<=COUNT(Aud_MNr),56,"") | B60: =IFERROR(IF($A60="","",INDEX(Aud_Nr,MATCH($A60,Aud_MNr,0))),"") | C60: =IFERROR(IF($A60="","",INDEX(Aud_Kapitel,MATCH($A60,Aud_MNr,0))),"") | D60: =IFERROR(IF($A60="","",INDEX(Aud_Punkt,MATCH($A60,Aud_MNr,0))),"") | E60: =IFERROR(IF($A60="","",INDEX(Aud_Bew,MATCH($A60,Aud_MNr,0))),"") | F60: =IFERROR(IF($A60="","",IF(INDEX(Aud_Massn,MATCH($A60,Aud_MNr,0))="","",INDEX(Aud_Massn,MATCH($A60,Aud_MNr,0)))),"") | G60: =IFERROR(IF($A60="","",IF(INDEX(Aud_Verantw,MATCH($A60,Aud_MNr,0))="","",INDEX(Aud_Verantw,MATCH($A60,Aud_MNr,0)))),"") | H60: =IFERROR(IF($A60="","",IF(INDEX(Aud_Termin,MATCH($A60,Aud_MNr,0))="","",INDEX(Aud_Termin,MATCH($A60,Aud_MNr,0)))),"") | I60: =IFERROR(IF($A60="","",INDEX(Aud_Status,MATCH($A60,Aud_MNr,0))),"")
A61: =IF(57<=COUNT(Aud_MNr),57,"") | B61: =IFERROR(IF($A61="","",INDEX(Aud_Nr,MATCH($A61,Aud_MNr,0))),"") | C61: =IFERROR(IF($A61="","",INDEX(Aud_Kapitel,MATCH($A61,Aud_MNr,0))),"") | D61: =IFERROR(IF($A61="","",INDEX(Aud_Punkt,MATCH($A61,Aud_MNr,0))),"") | E61: =IFERROR(IF($A61="","",INDEX(Aud_Bew,MATCH($A61,Aud_MNr,0))),"") | F61: =IFERROR(IF($A61="","",IF(INDEX(Aud_Massn,MATCH($A61,Aud_MNr,0))="","",INDEX(Aud_Massn,MATCH($A61,Aud_MNr,0)))),"") | G61: =IFERROR(IF($A61="","",IF(INDEX(Aud_Verantw,MATCH($A61,Aud_MNr,0))="","",INDEX(Aud_Verantw,MATCH($A61,Aud_MNr,0)))),"") | H61: =IFERROR(IF($A61="","",IF(INDEX(Aud_Termin,MATCH($A61,Aud_MNr,0))="","",INDEX(Aud_Termin,MATCH($A61,Aud_MNr,0)))),"") | I61: =IFERROR(IF($A61="","",INDEX(Aud_Status,MATCH($A61,Aud_MNr,0))),"")
A62: =IF(58<=COUNT(Aud_MNr),58,"") | B62: =IFERROR(IF($A62="","",INDEX(Aud_Nr,MATCH($A62,Aud_MNr,0))),"") | C62: =IFERROR(IF($A62="","",INDEX(Aud_Kapitel,MATCH($A62,Aud_MNr,0))),"") | D62: =IFERROR(IF($A62="","",INDEX(Aud_Punkt,MATCH($A62,Aud_MNr,0))),"") | E62: =IFERROR(IF($A62="","",INDEX(Aud_Bew,MATCH($A62,Aud_MNr,0))),"") | F62: =IFERROR(IF($A62="","",IF(INDEX(Aud_Massn,MATCH($A62,Aud_MNr,0))="","",INDEX(Aud_Massn,MATCH($A62,Aud_MNr,0)))),"") | G62: =IFERROR(IF($A62="","",IF(INDEX(Aud_Verantw,MATCH($A62,Aud_MNr,0))="","",INDEX(Aud_Verantw,MATCH($A62,Aud_MNr,0)))),"") | H62: =IFERROR(IF($A62="","",IF(INDEX(Aud_Termin,MATCH($A62,Aud_MNr,0))="","",INDEX(Aud_Termin,MATCH($A62,Aud_MNr,0)))),"") | I62: =IFERROR(IF($A62="","",INDEX(Aud_Status,MATCH($A62,Aud_MNr,0))),"")
A63: =IF(59<=COUNT(Aud_MNr),59,"") | B63: =IFERROR(IF($A63="","",INDEX(Aud_Nr,MATCH($A63,Aud_MNr,0))),"") | C63: =IFERROR(IF($A63="","",INDEX(Aud_Kapitel,MATCH($A63,Aud_MNr,0))),"") | D63: =IFERROR(IF($A63="","",INDEX(Aud_Punkt,MATCH($A63,Aud_MNr,0))),"") | E63: =IFERROR(IF($A63="","",INDEX(Aud_Bew,MATCH($A63,Aud_MNr,0))),"") | F63: =IFERROR(IF($A63="","",IF(INDEX(Aud_Massn,MATCH($A63,Aud_MNr,0))="","",INDEX(Aud_Massn,MATCH($A63,Aud_MNr,0)))),"") | G63: =IFERROR(IF($A63="","",IF(INDEX(Aud_Verantw,MATCH($A63,Aud_MNr,0))="","",INDEX(Aud_Verantw,MATCH($A63,Aud_MNr,0)))),"") | H63: =IFERROR(IF($A63="","",IF(INDEX(Aud_Termin,MATCH($A63,Aud_MNr,0))="","",INDEX(Aud_Termin,MATCH($A63,Aud_MNr,0)))),"") | I63: =IFERROR(IF($A63="","",INDEX(Aud_Status,MATCH($A63,Aud_MNr,0))),"")
A64: =IF(60<=COUNT(Aud_MNr),60,"") | B64: =IFERROR(IF($A64="","",INDEX(Aud_Nr,MATCH($A64,Aud_MNr,0))),"") | C64: =IFERROR(IF($A64="","",INDEX(Aud_Kapitel,MATCH($A64,Aud_MNr,0))),"") | D64: =IFERROR(IF($A64="","",INDEX(Aud_Punkt,MATCH($A64,Aud_MNr,0))),"") | E64: =IFERROR(IF($A64="","",INDEX(Aud_Bew,MATCH($A64,Aud_MNr,0))),"") | F64: =IFERROR(IF($A64="","",IF(INDEX(Aud_Massn,MATCH($A64,Aud_MNr,0))="","",INDEX(Aud_Massn,MATCH($A64,Aud_MNr,0)))),"") | G64: =IFERROR(IF($A64="","",IF(INDEX(Aud_Verantw,MATCH($A64,Aud_MNr,0))="","",INDEX(Aud_Verantw,MATCH($A64,Aud_MNr,0)))),"") | H64: =IFERROR(IF($A64="","",IF(INDEX(Aud_Termin,MATCH($A64,Aud_MNr,0))="","",INDEX(Aud_Termin,MATCH($A64,Aud_MNr,0)))),"") | I64: =IFERROR(IF($A64="","",INDEX(Aud_Status,MATCH($A64,Aud_MNr,0))),"")
A65: =IF(61<=COUNT(Aud_MNr),61,"") | B65: =IFERROR(IF($A65="","",INDEX(Aud_Nr,MATCH($A65,Aud_MNr,0))),"") | C65: =IFERROR(IF($A65="","",INDEX(Aud_Kapitel,MATCH($A65,Aud_MNr,0))),"") | D65: =IFERROR(IF($A65="","",INDEX(Aud_Punkt,MATCH($A65,Aud_MNr,0))),"") | E65: =IFERROR(IF($A65="","",INDEX(Aud_Bew,MATCH($A65,Aud_MNr,0))),"") | F65: =IFERROR(IF($A65="","",IF(INDEX(Aud_Massn,MATCH($A65,Aud_MNr,0))="","",INDEX(Aud_Massn,MATCH($A65,Aud_MNr,0)))),"") | G65: =IFERROR(IF($A65="","",IF(INDEX(Aud_Verantw,MATCH($A65,Aud_MNr,0))="","",INDEX(Aud_Verantw,MATCH($A65,Aud_MNr,0)))),"") | H65: =IFERROR(IF($A65="","",IF(INDEX(Aud_Termin,MATCH($A65,Aud_MNr,0))="","",INDEX(Aud_Termin,MATCH($A65,Aud_MNr,0)))),"") | I65: =IFERROR(IF($A65="","",INDEX(Aud_Status,MATCH($A65,Aud_MNr,0))),"")
A66: =IF(62<=COUNT(Aud_MNr),62,"") | B66: =IFERROR(IF($A66="","",INDEX(Aud_Nr,MATCH($A66,Aud_MNr,0))),"") | C66: =IFERROR(IF($A66="","",INDEX(Aud_Kapitel,MATCH($A66,Aud_MNr,0))),"") | D66: =IFERROR(IF($A66="","",INDEX(Aud_Punkt,MATCH($A66,Aud_MNr,0))),"") | E66: =IFERROR(IF($A66="","",INDEX(Aud_Bew,MATCH($A66,Aud_MNr,0))),"") | F66: =IFERROR(IF($A66="","",IF(INDEX(Aud_Massn,MATCH($A66,Aud_MNr,0))="","",INDEX(Aud_Massn,MATCH($A66,Aud_MNr,0)))),"") | G66: =IFERROR(IF($A66="","",IF(INDEX(Aud_Verantw,MATCH($A66,Aud_MNr,0))="","",INDEX(Aud_Verantw,MATCH($A66,Aud_MNr,0)))),"") | H66: =IFERROR(IF($A66="","",IF(INDEX(Aud_Termin,MATCH($A66,Aud_MNr,0))="","",INDEX(Aud_Termin,MATCH($A66,Aud_MNr,0)))),"") | I66: =IFERROR(IF($A66="","",INDEX(Aud_Status,MATCH($A66,Aud_MNr,0))),"")
A67: =IF(63<=COUNT(Aud_MNr),63,"") | B67: =IFERROR(IF($A67="","",INDEX(Aud_Nr,MATCH($A67,Aud_MNr,0))),"") | C67: =IFERROR(IF($A67="","",INDEX(Aud_Kapitel,MATCH($A67,Aud_MNr,0))),"") | D67: =IFERROR(IF($A67="","",INDEX(Aud_Punkt,MATCH($A67,Aud_MNr,0))),"") | E67: =IFERROR(IF($A67="","",INDEX(Aud_Bew,MATCH($A67,Aud_MNr,0))),"") | F67: =IFERROR(IF($A67="","",IF(INDEX(Aud_Massn,MATCH($A67,Aud_MNr,0))="","",INDEX(Aud_Massn,MATCH($A67,Aud_MNr,0)))),"") | G67: =IFERROR(IF($A67="","",IF(INDEX(Aud_Verantw,MATCH($A67,Aud_MNr,0))="","",INDEX(Aud_Verantw,MATCH($A67,Aud_MNr,0)))),"") | H67: =IFERROR(IF($A67="","",IF(INDEX(Aud_Termin,MATCH($A67,Aud_MNr,0))="","",INDEX(Aud_Termin,MATCH($A67,Aud_MNr,0)))),"") | I67: =IFERROR(IF($A67="","",INDEX(Aud_Status,MATCH($A67,Aud_MNr,0))),"")
A68: =IF(64<=COUNT(Aud_MNr),64,"") | B68: =IFERROR(IF($A68="","",INDEX(Aud_Nr,MATCH($A68,Aud_MNr,0))),"") | C68: =IFERROR(IF($A68="","",INDEX(Aud_Kapitel,MATCH($A68,Aud_MNr,0))),"") | D68: =IFERROR(IF($A68="","",INDEX(Aud_Punkt,MATCH($A68,Aud_MNr,0))),"") | E68: =IFERROR(IF($A68="","",INDEX(Aud_Bew,MATCH($A68,Aud_MNr,0))),"") | F68: =IFERROR(IF($A68="","",IF(INDEX(Aud_Massn,MATCH($A68,Aud_MNr,0))="","",INDEX(Aud_Massn,MATCH($A68,Aud_MNr,0)))),"") | G68: =IFERROR(IF($A68="","",IF(INDEX(Aud_Verantw,MATCH($A68,Aud_MNr,0))="","",INDEX(Aud_Verantw,MATCH($A68,Aud_MNr,0)))),"") | H68: =IFERROR(IF($A68="","",IF(INDEX(Aud_Termin,MATCH($A68,Aud_MNr,0))="","",INDEX(Aud_Termin,MATCH($A68,Aud_MNr,0)))),"") | I68: =IFERROR(IF($A68="","",INDEX(Aud_Status,MATCH($A68,Aud_MNr,0))),"")
A69: =IF(65<=COUNT(Aud_MNr),65,"") | B69: =IFERROR(IF($A69="","",INDEX(Aud_Nr,MATCH($A69,Aud_MNr,0))),"") | C69: =IFERROR(IF($A69="","",INDEX(Aud_Kapitel,MATCH($A69,Aud_MNr,0))),"") | D69: =IFERROR(IF($A69="","",INDEX(Aud_Punkt,MATCH($A69,Aud_MNr,0))),"") | E69: =IFERROR(IF($A69="","",INDEX(Aud_Bew,MATCH($A69,Aud_MNr,0))),"") | F69: =IFERROR(IF($A69="","",IF(INDEX(Aud_Massn,MATCH($A69,Aud_MNr,0))="","",INDEX(Aud_Massn,MATCH($A69,Aud_MNr,0)))),"") | G69: =IFERROR(IF($A69="","",IF(INDEX(Aud_Verantw,MATCH($A69,Aud_MNr,0))="","",INDEX(Aud_Verantw,MATCH($A69,Aud_MNr,0)))),"") | H69: =IFERROR(IF($A69="","",IF(INDEX(Aud_Termin,MATCH($A69,Aud_MNr,0))="","",INDEX(Aud_Termin,MATCH($A69,Aud_MNr,0)))),"") | I69: =IFERROR(IF($A69="","",INDEX(Aud_Status,MATCH($A69,Aud_MNr,0))),"")
A70: =IF(66<=COUNT(Aud_MNr),66,"") | B70: =IFERROR(IF($A70="","",INDEX(Aud_Nr,MATCH($A70,Aud_MNr,0))),"") | C70: =IFERROR(IF($A70="","",INDEX(Aud_Kapitel,MATCH($A70,Aud_MNr,0))),"") | D70: =IFERROR(IF($A70="","",INDEX(Aud_Punkt,MATCH($A70,Aud_MNr,0))),"") | E70: =IFERROR(IF($A70="","",INDEX(Aud_Bew,MATCH($A70,Aud_MNr,0))),"") | F70: =IFERROR(IF($A70="","",IF(INDEX(Aud_Massn,MATCH($A70,Aud_MNr,0))="","",INDEX(Aud_Massn,MATCH($A70,Aud_MNr,0)))),"") | G70: =IFERROR(IF($A70="","",IF(INDEX(Aud_Verantw,MATCH($A70,Aud_MNr,0))="","",INDEX(Aud_Verantw,MATCH($A70,Aud_MNr,0)))),"") | H70: =IFERROR(IF($A70="","",IF(INDEX(Aud_Termin,MATCH($A70,Aud_MNr,0))="","",INDEX(Aud_Termin,MATCH($A70,Aud_MNr,0)))),"") | I70: =IFERROR(IF($A70="","",INDEX(Aud_Status,MATCH($A70,Aud_MNr,0))),"")
A71: =IF(67<=COUNT(Aud_MNr),67,"") | B71: =IFERROR(IF($A71="","",INDEX(Aud_Nr,MATCH($A71,Aud_MNr,0))),"") | C71: =IFERROR(IF($A71="","",INDEX(Aud_Kapitel,MATCH($A71,Aud_MNr,0))),"") | D71: =IFERROR(IF($A71="","",INDEX(Aud_Punkt,MATCH($A71,Aud_MNr,0))),"") | E71: =IFERROR(IF($A71="","",INDEX(Aud_Bew,MATCH($A71,Aud_MNr,0))),"") | F71: =IFERROR(IF($A71="","",IF(INDEX(Aud_Massn,MATCH($A71,Aud_MNr,0))="","",INDEX(Aud_Massn,MATCH($A71,Aud_MNr,0)))),"") | G71: =IFERROR(IF($A71="","",IF(INDEX(Aud_Verantw,MATCH($A71,Aud_MNr,0))="","",INDEX(Aud_Verantw,MATCH($A71,Aud_MNr,0)))),"") | H71: =IFERROR(IF($A71="","",IF(INDEX(Aud_Termin,MATCH($A71,Aud_MNr,0))="","",INDEX(Aud_Termin,MATCH($A71,Aud_MNr,0)))),"") | I71: =IFERROR(IF($A71="","",INDEX(Aud_Status,MATCH($A71,Aud_MNr,0))),"")
A72: =IF(68<=COUNT(Aud_MNr),68,"") | B72: =IFERROR(IF($A72="","",INDEX(Aud_Nr,MATCH($A72,Aud_MNr,0))),"") | C72: =IFERROR(IF($A72="","",INDEX(Aud_Kapitel,MATCH($A72,Aud_MNr,0))),"") | D72: =IFERROR(IF($A72="","",INDEX(Aud_Punkt,MATCH($A72,Aud_MNr,0))),"") | E72: =IFERROR(IF($A72="","",INDEX(Aud_Bew,MATCH($A72,Aud_MNr,0))),"") | F72: =IFERROR(IF($A72="","",IF(INDEX(Aud_Massn,MATCH($A72,Aud_MNr,0))="","",INDEX(Aud_Massn,MATCH($A72,Aud_MNr,0)))),"") | G72: =IFERROR(IF($A72="","",IF(INDEX(Aud_Verantw,MATCH($A72,Aud_MNr,0))="","",INDEX(Aud_Verantw,MATCH($A72,Aud_MNr,0)))),"") | H72: =IFERROR(IF($A72="","",IF(INDEX(Aud_Termin,MATCH($A72,Aud_MNr,0))="","",INDEX(Aud_Termin,MATCH($A72,Aud_MNr,0)))),"") | I72: =IFERROR(IF($A72="","",INDEX(Aud_Status,MATCH($A72,Aud_MNr,0))),"")
A73: =IF(69<=COUNT(Aud_MNr),69,"") | B73: =IFERROR(IF($A73="","",INDEX(Aud_Nr,MATCH($A73,Aud_MNr,0))),"") | C73: =IFERROR(IF($A73="","",INDEX(Aud_Kapitel,MATCH($A73,Aud_MNr,0))),"") | D73: =IFERROR(IF($A73="","",INDEX(Aud_Punkt,MATCH($A73,Aud_MNr,0))),"") | E73: =IFERROR(IF($A73="","",INDEX(Aud_Bew,MATCH($A73,Aud_MNr,0))),"") | F73: =IFERROR(IF($A73="","",IF(INDEX(Aud_Massn,MATCH($A73,Aud_MNr,0))="","",INDEX(Aud_Massn,MATCH($A73,Aud_MNr,0)))),"") | G73: =IFERROR(IF($A73="","",IF(INDEX(Aud_Verantw,MATCH($A73,Aud_MNr,0))="","",INDEX(Aud_Verantw,MATCH($A73,Aud_MNr,0)))),"") | H73: =IFERROR(IF($A73="","",IF(INDEX(Aud_Termin,MATCH($A73,Aud_MNr,0))="","",INDEX(Aud_Termin,MATCH($A73,Aud_MNr,0)))),"") | I73: =IFERROR(IF($A73="","",INDEX(Aud_Status,MATCH($A73,Aud_MNr,0))),"")
A74: =IF(70<=COUNT(Aud_MNr),70,"") | B74: =IFERROR(IF($A74="","",INDEX(Aud_Nr,MATCH($A74,Aud_MNr,0))),"") | C74: =IFERROR(IF($A74="","",INDEX(Aud_Kapitel,MATCH($A74,Aud_MNr,0))),"") | D74: =IFERROR(IF($A74="","",INDEX(Aud_Punkt,MATCH($A74,Aud_MNr,0))),"") | E74: =IFERROR(IF($A74="","",INDEX(Aud_Bew,MATCH($A74,Aud_MNr,0))),"") | F74: =IFERROR(IF($A74="","",IF(INDEX(Aud_Massn,MATCH($A74,Aud_MNr,0))="","",INDEX(Aud_Massn,MATCH($A74,Aud_MNr,0)))),"") | G74: =IFERROR(IF($A74="","",IF(INDEX(Aud_Verantw,MATCH($A74,Aud_MNr,0))="","",INDEX(Aud_Verantw,MATCH($A74,Aud_MNr,0)))),"") | H74: =IFERROR(IF($A74="","",IF(INDEX(Aud_Termin,MATCH($A74,Aud_MNr,0))="","",INDEX(Aud_Termin,MATCH($A74,Aud_MNr,0)))),"") | I74: =IFERROR(IF($A74="","",INDEX(Aud_Status,MATCH($A74,Aud_MNr,0))),"")
A75: =IF(71<=COUNT(Aud_MNr),71,"") | B75: =IFERROR(IF($A75="","",INDEX(Aud_Nr,MATCH($A75,Aud_MNr,0))),"") | C75: =IFERROR(IF($A75="","",INDEX(Aud_Kapitel,MATCH($A75,Aud_MNr,0))),"") | D75: =IFERROR(IF($A75="","",INDEX(Aud_Punkt,MATCH($A75,Aud_MNr,0))),"") | E75: =IFERROR(IF($A75="","",INDEX(Aud_Bew,MATCH($A75,Aud_MNr,0))),"") | F75: =IFERROR(IF($A75="","",IF(INDEX(Aud_Massn,MATCH($A75,Aud_MNr,0))="","",INDEX(Aud_Massn,MATCH($A75,Aud_MNr,0)))),"") | G75: =IFERROR(IF($A75="","",IF(INDEX(Aud_Verantw,MATCH($A75,Aud_MNr,0))="","",INDEX(Aud_Verantw,MATCH($A75,Aud_MNr,0)))),"") | H75: =IFERROR(IF($A75="","",IF(INDEX(Aud_Termin,MATCH($A75,Aud_MNr,0))="","",INDEX(Aud_Termin,MATCH($A75,Aud_MNr,0)))),"") | I75: =IFERROR(IF($A75="","",INDEX(Aud_Status,MATCH($A75,Aud_MNr,0))),"")
A76: =IF(72<=COUNT(Aud_MNr),72,"") | B76: =IFERROR(IF($A76="","",INDEX(Aud_Nr,MATCH($A76,Aud_MNr,0))),"") | C76: =IFERROR(IF($A76="","",INDEX(Aud_Kapitel,MATCH($A76,Aud_MNr,0))),"") | D76: =IFERROR(IF($A76="","",INDEX(Aud_Punkt,MATCH($A76,Aud_MNr,0))),"") | E76: =IFERROR(IF($A76="","",INDEX(Aud_Bew,MATCH($A76,Aud_MNr,0))),"") | F76: =IFERROR(IF($A76="","",IF(INDEX(Aud_Massn,MATCH($A76,Aud_MNr,0))="","",INDEX(Aud_Massn,MATCH($A76,Aud_MNr,0)))),"") | G76: =IFERROR(IF($A76="","",IF(INDEX(Aud_Verantw,MATCH($A76,Aud_MNr,0))="","",INDEX(Aud_Verantw,MATCH($A76,Aud_MNr,0)))),"") | H76: =IFERROR(IF($A76="","",IF(INDEX(Aud_Termin,MATCH($A76,Aud_MNr,0))="","",INDEX(Aud_Termin,MATCH($A76,Aud_MNr,0)))),"") | I76: =IFERROR(IF($A76="","",INDEX(Aud_Status,MATCH($A76,Aud_MNr,0))),"")
A77: =IF(73<=COUNT(Aud_MNr),73,"") | B77: =IFERROR(IF($A77="","",INDEX(Aud_Nr,MATCH($A77,Aud_MNr,0))),"") | C77: =IFERROR(IF($A77="","",INDEX(Aud_Kapitel,MATCH($A77,Aud_MNr,0))),"") | D77: =IFERROR(IF($A77="","",INDEX(Aud_Punkt,MATCH($A77,Aud_MNr,0))),"") | E77: =IFERROR(IF($A77="","",INDEX(Aud_Bew,MATCH($A77,Aud_MNr,0))),"") | F77: =IFERROR(IF($A77="","",IF(INDEX(Aud_Massn,MATCH($A77,Aud_MNr,0))="","",INDEX(Aud_Massn,MATCH($A77,Aud_MNr,0)))),"") | G77: =IFERROR(IF($A77="","",IF(INDEX(Aud_Verantw,MATCH($A77,Aud_MNr,0))="","",INDEX(Aud_Verantw,MATCH($A77,Aud_MNr,0)))),"") | H77: =IFERROR(IF($A77="","",IF(INDEX(Aud_Termin,MATCH($A77,Aud_MNr,0))="","",INDEX(Aud_Termin,MATCH($A77,Aud_MNr,0)))),"") | I77: =IFERROR(IF($A77="","",INDEX(Aud_Status,MATCH($A77,Aud_MNr,0))),"")
A78: =IF(74<=COUNT(Aud_MNr),74,"") | B78: =IFERROR(IF($A78="","",INDEX(Aud_Nr,MATCH($A78,Aud_MNr,0))),"") | C78: =IFERROR(IF($A78="","",INDEX(Aud_Kapitel,MATCH($A78,Aud_MNr,0))),"") | D78: =IFERROR(IF($A78="","",INDEX(Aud_Punkt,MATCH($A78,Aud_MNr,0))),"") | E78: =IFERROR(IF($A78="","",INDEX(Aud_Bew,MATCH($A78,Aud_MNr,0))),"") | F78: =IFERROR(IF($A78="","",IF(INDEX(Aud_Massn,MATCH($A78,Aud_MNr,0))="","",INDEX(Aud_Massn,MATCH($A78,Aud_MNr,0)))),"") | G78: =IFERROR(IF($A78="","",IF(INDEX(Aud_Verantw,MATCH($A78,Aud_MNr,0))="","",INDEX(Aud_Verantw,MATCH($A78,Aud_MNr,0)))),"") | H78: =IFERROR(IF($A78="","",IF(INDEX(Aud_Termin,MATCH($A78,Aud_MNr,0))="","",INDEX(Aud_Termin,MATCH($A78,Aud_MNr,0)))),"") | I78: =IFERROR(IF($A78="","",INDEX(Aud_Status,MATCH($A78,Aud_MNr,0))),"")
A79: =IF(75<=COUNT(Aud_MNr),75,"") | B79: =IFERROR(IF($A79="","",INDEX(Aud_Nr,MATCH($A79,Aud_MNr,0))),"") | C79: =IFERROR(IF($A79="","",INDEX(Aud_Kapitel,MATCH($A79,Aud_MNr,0))),"") | D79: =IFERROR(IF($A79="","",INDEX(Aud_Punkt,MATCH($A79,Aud_MNr,0))),"") | E79: =IFERROR(IF($A79="","",INDEX(Aud_Bew,MATCH($A79,Aud_MNr,0))),"") | F79: =IFERROR(IF($A79="","",IF(INDEX(Aud_Massn,MATCH($A79,Aud_MNr,0))="","",INDEX(Aud_Massn,MATCH($A79,Aud_MNr,0)))),"") | G79: =IFERROR(IF($A79="","",IF(INDEX(Aud_Verantw,MATCH($A79,Aud_MNr,0))="","",INDEX(Aud_Verantw,MATCH($A79,Aud_MNr,0)))),"") | H79: =IFERROR(IF($A79="","",IF(INDEX(Aud_Termin,MATCH($A79,Aud_MNr,0))="","",INDEX(Aud_Termin,MATCH($A79,Aud_MNr,0)))),"") | I79: =IFERROR(IF($A79="","",INDEX(Aud_Status,MATCH($A79,Aud_MNr,0))),"")
A80: =IF(76<=COUNT(Aud_MNr),76,"") | B80: =IFERROR(IF($A80="","",INDEX(Aud_Nr,MATCH($A80,Aud_MNr,0))),"") | C80: =IFERROR(IF($A80="","",INDEX(Aud_Kapitel,MATCH($A80,Aud_MNr,0))),"") | D80: =IFERROR(IF($A80="","",INDEX(Aud_Punkt,MATCH($A80,Aud_MNr,0))),"") | E80: =IFERROR(IF($A80="","",INDEX(Aud_Bew,MATCH($A80,Aud_MNr,0))),"") | F80: =IFERROR(IF($A80="","",IF(INDEX(Aud_Massn,MATCH($A80,Aud_MNr,0))="","",INDEX(Aud_Massn,MATCH($A80,Aud_MNr,0)))),"") | G80: =IFERROR(IF($A80="","",IF(INDEX(Aud_Verantw,MATCH($A80,Aud_MNr,0))="","",INDEX(Aud_Verantw,MATCH($A80,Aud_MNr,0)))),"") | H80: =IFERROR(IF($A80="","",IF(INDEX(Aud_Termin,MATCH($A80,Aud_MNr,0))="","",INDEX(Aud_Termin,MATCH($A80,Aud_MNr,0)))),"") | I80: =IFERROR(IF($A80="","",INDEX(Aud_Status,MATCH($A80,Aud_MNr,0))),"")
A81: =IF(77<=COUNT(Aud_MNr),77,"") | B81: =IFERROR(IF($A81="","",INDEX(Aud_Nr,MATCH($A81,Aud_MNr,0))),"") | C81: =IFERROR(IF($A81="","",INDEX(Aud_Kapitel,MATCH($A81,Aud_MNr,0))),"") | D81: =IFERROR(IF($A81="","",INDEX(Aud_Punkt,MATCH($A81,Aud_MNr,0))),"") | E81: =IFERROR(IF($A81="","",INDEX(Aud_Bew,MATCH($A81,Aud_MNr,0))),"") | F81: =IFERROR(IF($A81="","",IF(INDEX(Aud_Massn,MATCH($A81,Aud_MNr,0))="","",INDEX(Aud_Massn,MATCH($A81,Aud_MNr,0)))),"") | G81: =IFERROR(IF($A81="","",IF(INDEX(Aud_Verantw,MATCH($A81,Aud_MNr,0))="","",INDEX(Aud_Verantw,MATCH($A81,Aud_MNr,0)))),"") | H81: =IFERROR(IF($A81="","",IF(INDEX(Aud_Termin,MATCH($A81,Aud_MNr,0))="","",INDEX(Aud_Termin,MATCH($A81,Aud_MNr,0)))),"") | I81: =IFERROR(IF($A81="","",INDEX(Aud_Status,MATCH($A81,Aud_MNr,0))),"")
A82: =IF(78<=COUNT(Aud_MNr),78,"") | B82: =IFERROR(IF($A82="","",INDEX(Aud_Nr,MATCH($A82,Aud_MNr,0))),"") | C82: =IFERROR(IF($A82="","",INDEX(Aud_Kapitel,MATCH($A82,Aud_MNr,0))),"") | D82: =IFERROR(IF($A82="","",INDEX(Aud_Punkt,MATCH($A82,Aud_MNr,0))),"") | E82: =IFERROR(IF($A82="","",INDEX(Aud_Bew,MATCH($A82,Aud_MNr,0))),"") | F82: =IFERROR(IF($A82="","",IF(INDEX(Aud_Massn,MATCH($A82,Aud_MNr,0))="","",INDEX(Aud_Massn,MATCH($A82,Aud_MNr,0)))),"") | G82: =IFERROR(IF($A82="","",IF(INDEX(Aud_Verantw,MATCH($A82,Aud_MNr,0))="","",INDEX(Aud_Verantw,MATCH($A82,Aud_MNr,0)))),"") | H82: =IFERROR(IF($A82="","",IF(INDEX(Aud_Termin,MATCH($A82,Aud_MNr,0))="","",INDEX(Aud_Termin,MATCH($A82,Aud_MNr,0)))),"") | I82: =IFERROR(IF($A82="","",INDEX(Aud_Status,MATCH($A82,Aud_MNr,0))),"")
A83: =IF(79<=COUNT(Aud_MNr),79,"") | B83: =IFERROR(IF($A83="","",INDEX(Aud_Nr,MATCH($A83,Aud_MNr,0))),"") | C83: =IFERROR(IF($A83="","",INDEX(Aud_Kapitel,MATCH($A83,Aud_MNr,0))),"") | D83: =IFERROR(IF($A83="","",INDEX(Aud_Punkt,MATCH($A83,Aud_MNr,0))),"") | E83: =IFERROR(IF($A83="","",INDEX(Aud_Bew,MATCH($A83,Aud_MNr,0))),"") | F83: =IFERROR(IF($A83="","",IF(INDEX(Aud_Massn,MATCH($A83,Aud_MNr,0))="","",INDEX(Aud_Massn,MATCH($A83,Aud_MNr,0)))),"") | G83: =IFERROR(IF($A83="","",IF(INDEX(Aud_Verantw,MATCH($A83,Aud_MNr,0))="","",INDEX(Aud_Verantw,MATCH($A83,Aud_MNr,0)))),"") | H83: =IFERROR(IF($A83="","",IF(INDEX(Aud_Termin,MATCH($A83,Aud_MNr,0))="","",INDEX(Aud_Termin,MATCH($A83,Aud_MNr,0)))),"") | I83: =IFERROR(IF($A83="","",INDEX(Aud_Status,MATCH($A83,Aud_MNr,0))),"")
A84: =IF(80<=COUNT(Aud_MNr),80,"") | B84: =IFERROR(IF($A84="","",INDEX(Aud_Nr,MATCH($A84,Aud_MNr,0))),"") | C84: =IFERROR(IF($A84="","",INDEX(Aud_Kapitel,MATCH($A84,Aud_MNr,0))),"") | D84: =IFERROR(IF($A84="","",INDEX(Aud_Punkt,MATCH($A84,Aud_MNr,0))),"") | E84: =IFERROR(IF($A84="","",INDEX(Aud_Bew,MATCH($A84,Aud_MNr,0))),"") | F84: =IFERROR(IF($A84="","",IF(INDEX(Aud_Massn,MATCH($A84,Aud_MNr,0))="","",INDEX(Aud_Massn,MATCH($A84,Aud_MNr,0)))),"") | G84: =IFERROR(IF($A84="","",IF(INDEX(Aud_Verantw,MATCH($A84,Aud_MNr,0))="","",INDEX(Aud_Verantw,MATCH($A84,Aud_MNr,0)))),"") | H84: =IFERROR(IF($A84="","",IF(INDEX(Aud_Termin,MATCH($A84,Aud_MNr,0))="","",INDEX(Aud_Termin,MATCH($A84,Aud_MNr,0)))),"") | I84: =IFERROR(IF($A84="","",INDEX(Aud_Status,MATCH($A84,Aud_MNr,0))),"")
A85: =IF(81<=COUNT(Aud_MNr),81,"") | B85: =IFERROR(IF($A85="","",INDEX(Aud_Nr,MATCH($A85,Aud_MNr,0))),"") | C85: =IFERROR(IF($A85="","",INDEX(Aud_Kapitel,MATCH($A85,Aud_MNr,0))),"") | D85: =IFERROR(IF($A85="","",INDEX(Aud_Punkt,MATCH($A85,Aud_MNr,0))),"") | E85: =IFERROR(IF($A85="","",INDEX(Aud_Bew,MATCH($A85,Aud_MNr,0))),"") | F85: =IFERROR(IF($A85="","",IF(INDEX(Aud_Massn,MATCH($A85,Aud_MNr,0))="","",INDEX(Aud_Massn,MATCH($A85,Aud_MNr,0)))),"") | G85: =IFERROR(IF($A85="","",IF(INDEX(Aud_Verantw,MATCH($A85,Aud_MNr,0))="","",INDEX(Aud_Verantw,MATCH($A85,Aud_MNr,0)))),"") | H85: =IFERROR(IF($A85="","",IF(INDEX(Aud_Termin,MATCH($A85,Aud_MNr,0))="","",INDEX(Aud_Termin,MATCH($A85,Aud_MNr,0)))),"") | I85: =IFERROR(IF($A85="","",INDEX(Aud_Status,MATCH($A85,Aud_MNr,0))),"")
A86: =IF(82<=COUNT(Aud_MNr),82,"") | B86: =IFERROR(IF($A86="","",INDEX(Aud_Nr,MATCH($A86,Aud_MNr,0))),"") | C86: =IFERROR(IF($A86="","",INDEX(Aud_Kapitel,MATCH($A86,Aud_MNr,0))),"") | D86: =IFERROR(IF($A86="","",INDEX(Aud_Punkt,MATCH($A86,Aud_MNr,0))),"") | E86: =IFERROR(IF($A86="","",INDEX(Aud_Bew,MATCH($A86,Aud_MNr,0))),"") | F86: =IFERROR(IF($A86="","",IF(INDEX(Aud_Massn,MATCH($A86,Aud_MNr,0))="","",INDEX(Aud_Massn,MATCH($A86,Aud_MNr,0)))),"") | G86: =IFERROR(IF($A86="","",IF(INDEX(Aud_Verantw,MATCH($A86,Aud_MNr,0))="","",INDEX(Aud_Verantw,MATCH($A86,Aud_MNr,0)))),"") | H86: =IFERROR(IF($A86="","",IF(INDEX(Aud_Termin,MATCH($A86,Aud_MNr,0))="","",INDEX(Aud_Termin,MATCH($A86,Aud_MNr,0)))),"") | I86: =IFERROR(IF($A86="","",INDEX(Aud_Status,MATCH($A86,Aud_MNr,0))),"")
A87: =IF(83<=COUNT(Aud_MNr),83,"") | B87: =IFERROR(IF($A87="","",INDEX(Aud_Nr,MATCH($A87,Aud_MNr,0))),"") | C87: =IFERROR(IF($A87="","",INDEX(Aud_Kapitel,MATCH($A87,Aud_MNr,0))),"") | D87: =IFERROR(IF($A87="","",INDEX(Aud_Punkt,MATCH($A87,Aud_MNr,0))),"") | E87: =IFERROR(IF($A87="","",INDEX(Aud_Bew,MATCH($A87,Aud_MNr,0))),"") | F87: =IFERROR(IF($A87="","",IF(INDEX(Aud_Massn,MATCH($A87,Aud_MNr,0))="","",INDEX(Aud_Massn,MATCH($A87,Aud_MNr,0)))),"") | G87: =IFERROR(IF($A87="","",IF(INDEX(Aud_Verantw,MATCH($A87,Aud_MNr,0))="","",INDEX(Aud_Verantw,MATCH($A87,Aud_MNr,0)))),"") | H87: =IFERROR(IF($A87="","",IF(INDEX(Aud_Termin,MATCH($A87,Aud_MNr,0))="","",INDEX(Aud_Termin,MATCH($A87,Aud_MNr,0)))),"") | I87: =IFERROR(IF($A87="","",INDEX(Aud_Status,MATCH($A87,Aud_MNr,0))),"")
A88: =IF(84<=COUNT(Aud_MNr),84,"") | B88: =IFERROR(IF($A88="","",INDEX(Aud_Nr,MATCH($A88,Aud_MNr,0))),"") | C88: =IFERROR(IF($A88="","",INDEX(Aud_Kapitel,MATCH($A88,Aud_MNr,0))),"") | D88: =IFERROR(IF($A88="","",INDEX(Aud_Punkt,MATCH($A88,Aud_MNr,0))),"") | E88: =IFERROR(IF($A88="","",INDEX(Aud_Bew,MATCH($A88,Aud_MNr,0))),"") | F88: =IFERROR(IF($A88="","",IF(INDEX(Aud_Massn,MATCH($A88,Aud_MNr,0))="","",INDEX(Aud_Massn,MATCH($A88,Aud_MNr,0)))),"") | G88: =IFERROR(IF($A88="","",IF(INDEX(Aud_Verantw,MATCH($A88,Aud_MNr,0))="","",INDEX(Aud_Verantw,MATCH($A88,Aud_MNr,0)))),"") | H88: =IFERROR(IF($A88="","",IF(INDEX(Aud_Termin,MATCH($A88,Aud_MNr,0))="","",INDEX(Aud_Termin,MATCH($A88,Aud_MNr,0)))),"") | I88: =IFERROR(IF($A88="","",INDEX(Aud_Status,MATCH($A88,Aud_MNr,0))),"")
A89: =IF(85<=COUNT(Aud_MNr),85,"") | B89: =IFERROR(IF($A89="","",INDEX(Aud_Nr,MATCH($A89,Aud_MNr,0))),"") | C89: =IFERROR(IF($A89="","",INDEX(Aud_Kapitel,MATCH($A89,Aud_MNr,0))),"") | D89: =IFERROR(IF($A89="","",INDEX(Aud_Punkt,MATCH($A89,Aud_MNr,0))),"") | E89: =IFERROR(IF($A89="","",INDEX(Aud_Bew,MATCH($A89,Aud_MNr,0))),"") | F89: =IFERROR(IF($A89="","",IF(INDEX(Aud_Massn,MATCH($A89,Aud_MNr,0))="","",INDEX(Aud_Massn,MATCH($A89,Aud_MNr,0)))),"") | G89: =IFERROR(IF($A89="","",IF(INDEX(Aud_Verantw,MATCH($A89,Aud_MNr,0))="","",INDEX(Aud_Verantw,MATCH($A89,Aud_MNr,0)))),"") | H89: =IFERROR(IF($A89="","",IF(INDEX(Aud_Termin,MATCH($A89,Aud_MNr,0))="","",INDEX(Aud_Termin,MATCH($A89,Aud_MNr,0)))),"") | I89: =IFERROR(IF($A89="","",INDEX(Aud_Status,MATCH($A89,Aud_MNr,0))),"")
A90: =IF(86<=COUNT(Aud_MNr),86,"") | B90: =IFERROR(IF($A90="","",INDEX(Aud_Nr,MATCH($A90,Aud_MNr,0))),"") | C90: =IFERROR(IF($A90="","",INDEX(Aud_Kapitel,MATCH($A90,Aud_MNr,0))),"") | D90: =IFERROR(IF($A90="","",INDEX(Aud_Punkt,MATCH($A90,Aud_MNr,0))),"") | E90: =IFERROR(IF($A90="","",INDEX(Aud_Bew,MATCH($A90,Aud_MNr,0))),"") | F90: =IFERROR(IF($A90="","",IF(INDEX(Aud_Massn,MATCH($A90,Aud_MNr,0))="","",INDEX(Aud_Massn,MATCH($A90,Aud_MNr,0)))),"") | G90: =IFERROR(IF($A90="","",IF(INDEX(Aud_Verantw,MATCH($A90,Aud_MNr,0))="","",INDEX(Aud_Verantw,MATCH($A90,Aud_MNr,0)))),"") | H90: =IFERROR(IF($A90="","",IF(INDEX(Aud_Termin,MATCH($A90,Aud_MNr,0))="","",INDEX(Aud_Termin,MATCH($A90,Aud_MNr,0)))),"") | I90: =IFERROR(IF($A90="","",INDEX(Aud_Status,MATCH($A90,Aud_MNr,0))),"")
A91: =IF(87<=COUNT(Aud_MNr),87,"") | B91: =IFERROR(IF($A91="","",INDEX(Aud_Nr,MATCH($A91,Aud_MNr,0))),"") | C91: =IFERROR(IF($A91="","",INDEX(Aud_Kapitel,MATCH($A91,Aud_MNr,0))),"") | D91: =IFERROR(IF($A91="","",INDEX(Aud_Punkt,MATCH($A91,Aud_MNr,0))),"") | E91: =IFERROR(IF($A91="","",INDEX(Aud_Bew,MATCH($A91,Aud_MNr,0))),"") | F91: =IFERROR(IF($A91="","",IF(INDEX(Aud_Massn,MATCH($A91,Aud_MNr,0))="","",INDEX(Aud_Massn,MATCH($A91,Aud_MNr,0)))),"") | G91: =IFERROR(IF($A91="","",IF(INDEX(Aud_Verantw,MATCH($A91,Aud_MNr,0))="","",INDEX(Aud_Verantw,MATCH($A91,Aud_MNr,0)))),"") | H91: =IFERROR(IF($A91="","",IF(INDEX(Aud_Termin,MATCH($A91,Aud_MNr,0))="","",INDEX(Aud_Termin,MATCH($A91,Aud_MNr,0)))),"") | I91: =IFERROR(IF($A91="","",INDEX(Aud_Status,MATCH($A91,Aud_MNr,0))),"")
A92: =IF(88<=COUNT(Aud_MNr),88,"") | B92: =IFERROR(IF($A92="","",INDEX(Aud_Nr,MATCH($A92,Aud_MNr,0))),"") | C92: =IFERROR(IF($A92="","",INDEX(Aud_Kapitel,MATCH($A92,Aud_MNr,0))),"") | D92: =IFERROR(IF($A92="","",INDEX(Aud_Punkt,MATCH($A92,Aud_MNr,0))),"") | E92: =IFERROR(IF($A92="","",INDEX(Aud_Bew,MATCH($A92,Aud_MNr,0))),"") | F92: =IFERROR(IF($A92="","",IF(INDEX(Aud_Massn,MATCH($A92,Aud_MNr,0))="","",INDEX(Aud_Massn,MATCH($A92,Aud_MNr,0)))),"") | G92: =IFERROR(IF($A92="","",IF(INDEX(Aud_Verantw,MATCH($A92,Aud_MNr,0))="","",INDEX(Aud_Verantw,MATCH($A92,Aud_MNr,0)))),"") | H92: =IFERROR(IF($A92="","",IF(INDEX(Aud_Termin,MATCH($A92,Aud_MNr,0))="","",INDEX(Aud_Termin,MATCH($A92,Aud_MNr,0)))),"") | I92: =IFERROR(IF($A92="","",INDEX(Aud_Status,MATCH($A92,Aud_MNr,0))),"")
A93: =IF(89<=COUNT(Aud_MNr),89,"") | B93: =IFERROR(IF($A93="","",INDEX(Aud_Nr,MATCH($A93,Aud_MNr,0))),"") | C93: =IFERROR(IF($A93="","",INDEX(Aud_Kapitel,MATCH($A93,Aud_MNr,0))),"") | D93: =IFERROR(IF($A93="","",INDEX(Aud_Punkt,MATCH($A93,Aud_MNr,0))),"") | E93: =IFERROR(IF($A93="","",INDEX(Aud_Bew,MATCH($A93,Aud_MNr,0))),"") | F93: =IFERROR(IF($A93="","",IF(INDEX(Aud_Massn,MATCH($A93,Aud_MNr,0))="","",INDEX(Aud_Massn,MATCH($A93,Aud_MNr,0)))),"") | G93: =IFERROR(IF($A93="","",IF(INDEX(Aud_Verantw,MATCH($A93,Aud_MNr,0))="","",INDEX(Aud_Verantw,MATCH($A93,Aud_MNr,0)))),"") | H93: =IFERROR(IF($A93="","",IF(INDEX(Aud_Termin,MATCH($A93,Aud_MNr,0))="","",INDEX(Aud_Termin,MATCH($A93,Aud_MNr,0)))),"") | I93: =IFERROR(IF($A93="","",INDEX(Aud_Status,MATCH($A93,Aud_MNr,0))),"")
A94: =IF(90<=COUNT(Aud_MNr),90,"") | B94: =IFERROR(IF($A94="","",INDEX(Aud_Nr,MATCH($A94,Aud_MNr,0))),"") | C94: =IFERROR(IF($A94="","",INDEX(Aud_Kapitel,MATCH($A94,Aud_MNr,0))),"") | D94: =IFERROR(IF($A94="","",INDEX(Aud_Punkt,MATCH($A94,Aud_MNr,0))),"") | E94: =IFERROR(IF($A94="","",INDEX(Aud_Bew,MATCH($A94,Aud_MNr,0))),"") | F94: =IFERROR(IF($A94="","",IF(INDEX(Aud_Massn,MATCH($A94,Aud_MNr,0))="","",INDEX(Aud_Massn,MATCH($A94,Aud_MNr,0)))),"") | G94: =IFERROR(IF($A94="","",IF(INDEX(Aud_Verantw,MATCH($A94,Aud_MNr,0))="","",INDEX(Aud_Verantw,MATCH($A94,Aud_MNr,0)))),"") | H94: =IFERROR(IF($A94="","",IF(INDEX(Aud_Termin,MATCH($A94,Aud_MNr,0))="","",INDEX(Aud_Termin,MATCH($A94,Aud_MNr,0)))),"") | I94: =IFERROR(IF($A94="","",INDEX(Aud_Status,MATCH($A94,Aud_MNr,0))),"")
A95: =IF(91<=COUNT(Aud_MNr),91,"") | B95: =IFERROR(IF($A95="","",INDEX(Aud_Nr,MATCH($A95,Aud_MNr,0))),"") | C95: =IFERROR(IF($A95="","",INDEX(Aud_Kapitel,MATCH($A95,Aud_MNr,0))),"") | D95: =IFERROR(IF($A95="","",INDEX(Aud_Punkt,MATCH($A95,Aud_MNr,0))),"") | E95: =IFERROR(IF($A95="","",INDEX(Aud_Bew,MATCH($A95,Aud_MNr,0))),"") | F95: =IFERROR(IF($A95="","",IF(INDEX(Aud_Massn,MATCH($A95,Aud_MNr,0))="","",INDEX(Aud_Massn,MATCH($A95,Aud_MNr,0)))),"") | G95: =IFERROR(IF($A95="","",IF(INDEX(Aud_Verantw,MATCH($A95,Aud_MNr,0))="","",INDEX(Aud_Verantw,MATCH($A95,Aud_MNr,0)))),"") | H95: =IFERROR(IF($A95="","",IF(INDEX(Aud_Termin,MATCH($A95,Aud_MNr,0))="","",INDEX(Aud_Termin,MATCH($A95,Aud_MNr,0)))),"") | I95: =IFERROR(IF($A95="","",INDEX(Aud_Status,MATCH($A95,Aud_MNr,0))),"")
A96: =IF(92<=COUNT(Aud_MNr),92,"") | B96: =IFERROR(IF($A96="","",INDEX(Aud_Nr,MATCH($A96,Aud_MNr,0))),"") | C96: =IFERROR(IF($A96="","",INDEX(Aud_Kapitel,MATCH($A96,Aud_MNr,0))),"") | D96: =IFERROR(IF($A96="","",INDEX(Aud_Punkt,MATCH($A96,Aud_MNr,0))),"") | E96: =IFERROR(IF($A96="","",INDEX(Aud_Bew,MATCH($A96,Aud_MNr,0))),"") | F96: =IFERROR(IF($A96="","",IF(INDEX(Aud_Massn,MATCH($A96,Aud_MNr,0))="","",INDEX(Aud_Massn,MATCH($A96,Aud_MNr,0)))),"") | G96: =IFERROR(IF($A96="","",IF(INDEX(Aud_Verantw,MATCH($A96,Aud_MNr,0))="","",INDEX(Aud_Verantw,MATCH($A96,Aud_MNr,0)))),"") | H96: =IFERROR(IF($A96="","",IF(INDEX(Aud_Termin,MATCH($A96,Aud_MNr,0))="","",INDEX(Aud_Termin,MATCH($A96,Aud_MNr,0)))),"") | I96: =IFERROR(IF($A96="","",INDEX(Aud_Status,MATCH($A96,Aud_MNr,0))),"")
A97: =IF(93<=COUNT(Aud_MNr),93,"") | B97: =IFERROR(IF($A97="","",INDEX(Aud_Nr,MATCH($A97,Aud_MNr,0))),"") | C97: =IFERROR(IF($A97="","",INDEX(Aud_Kapitel,MATCH($A97,Aud_MNr,0))),"") | D97: =IFERROR(IF($A97="","",INDEX(Aud_Punkt,MATCH($A97,Aud_MNr,0))),"") | E97: =IFERROR(IF($A97="","",INDEX(Aud_Bew,MATCH($A97,Aud_MNr,0))),"") | F97: =IFERROR(IF($A97="","",IF(INDEX(Aud_Massn,MATCH($A97,Aud_MNr,0))="","",INDEX(Aud_Massn,MATCH($A97,Aud_MNr,0)))),"") | G97: =IFERROR(IF($A97="","",IF(INDEX(Aud_Verantw,MATCH($A97,Aud_MNr,0))="","",INDEX(Aud_Verantw,MATCH($A97,Aud_MNr,0)))),"") | H97: =IFERROR(IF($A97="","",IF(INDEX(Aud_Termin,MATCH($A97,Aud_MNr,0))="","",INDEX(Aud_Termin,MATCH($A97,Aud_MNr,0)))),"") | I97: =IFERROR(IF($A97="","",INDEX(Aud_Status,MATCH($A97,Aud_MNr,0))),"")
A98: =IF(94<=COUNT(Aud_MNr),94,"") | B98: =IFERROR(IF($A98="","",INDEX(Aud_Nr,MATCH($A98,Aud_MNr,0))),"") | C98: =IFERROR(IF($A98="","",INDEX(Aud_Kapitel,MATCH($A98,Aud_MNr,0))),"") | D98: =IFERROR(IF($A98="","",INDEX(Aud_Punkt,MATCH($A98,Aud_MNr,0))),"") | E98: =IFERROR(IF($A98="","",INDEX(Aud_Bew,MATCH($A98,Aud_MNr,0))),"") | F98: =IFERROR(IF($A98="","",IF(INDEX(Aud_Massn,MATCH($A98,Aud_MNr,0))="","",INDEX(Aud_Massn,MATCH($A98,Aud_MNr,0)))),"") | G98: =IFERROR(IF($A98="","",IF(INDEX(Aud_Verantw,MATCH($A98,Aud_MNr,0))="","",INDEX(Aud_Verantw,MATCH($A98,Aud_MNr,0)))),"") | H98: =IFERROR(IF($A98="","",IF(INDEX(Aud_Termin,MATCH($A98,Aud_MNr,0))="","",INDEX(Aud_Termin,MATCH($A98,Aud_MNr,0)))),"") | I98: =IFERROR(IF($A98="","",INDEX(Aud_Status,MATCH($A98,Aud_MNr,0))),"")
A99: =IF(95<=COUNT(Aud_MNr),95,"") | B99: =IFERROR(IF($A99="","",INDEX(Aud_Nr,MATCH($A99,Aud_MNr,0))),"") | C99: =IFERROR(IF($A99="","",INDEX(Aud_Kapitel,MATCH($A99,Aud_MNr,0))),"") | D99: =IFERROR(IF($A99="","",INDEX(Aud_Punkt,MATCH($A99,Aud_MNr,0))),"") | E99: =IFERROR(IF($A99="","",INDEX(Aud_Bew,MATCH($A99,Aud_MNr,0))),"") | F99: =IFERROR(IF($A99="","",IF(INDEX(Aud_Massn,MATCH($A99,Aud_MNr,0))="","",INDEX(Aud_Massn,MATCH($A99,Aud_MNr,0)))),"") | G99: =IFERROR(IF($A99="","",IF(INDEX(Aud_Verantw,MATCH($A99,Aud_MNr,0))="","",INDEX(Aud_Verantw,MATCH($A99,Aud_MNr,0)))),"") | H99: =IFERROR(IF($A99="","",IF(INDEX(Aud_Termin,MATCH($A99,Aud_MNr,0))="","",INDEX(Aud_Termin,MATCH($A99,Aud_MNr,0)))),"") | I99: =IFERROR(IF($A99="","",INDEX(Aud_Status,MATCH($A99,Aud_MNr,0))),"")
A100: =IF(96<=COUNT(Aud_MNr),96,"") | B100: =IFERROR(IF($A100="","",INDEX(Aud_Nr,MATCH($A100,Aud_MNr,0))),"") | C100: =IFERROR(IF($A100="","",INDEX(Aud_Kapitel,MATCH($A100,Aud_MNr,0))),"") | D100: =IFERROR(IF($A100="","",INDEX(Aud_Punkt,MATCH($A100,Aud_MNr,0))),"") | E100: =IFERROR(IF($A100="","",INDEX(Aud_Bew,MATCH($A100,Aud_MNr,0))),"") | F100: =IFERROR(IF($A100="","",IF(INDEX(Aud_Massn,MATCH($A100,Aud_MNr,0))="","",INDEX(Aud_Massn,MATCH($A100,Aud_MNr,0)))),"") | G100: =IFERROR(IF($A100="","",IF(INDEX(Aud_Verantw,MATCH($A100,Aud_MNr,0))="","",INDEX(Aud_Verantw,MATCH($A100,Aud_MNr,0)))),"") | H100: =IFERROR(IF($A100="","",IF(INDEX(Aud_Termin,MATCH($A100,Aud_MNr,0))="","",INDEX(Aud_Termin,MATCH($A100,Aud_MNr,0)))),"") | I100: =IFERROR(IF($A100="","",INDEX(Aud_Status,MATCH($A100,Aud_MNr,0))),"")
A101: =IF(97<=COUNT(Aud_MNr),97,"") | B101: =IFERROR(IF($A101="","",INDEX(Aud_Nr,MATCH($A101,Aud_MNr,0))),"") | C101: =IFERROR(IF($A101="","",INDEX(Aud_Kapitel,MATCH($A101,Aud_MNr,0))),"") | D101: =IFERROR(IF($A101="","",INDEX(Aud_Punkt,MATCH($A101,Aud_MNr,0))),"") | E101: =IFERROR(IF($A101="","",INDEX(Aud_Bew,MATCH($A101,Aud_MNr,0))),"") | F101: =IFERROR(IF($A101="","",IF(INDEX(Aud_Massn,MATCH($A101,Aud_MNr,0))="","",INDEX(Aud_Massn,MATCH($A101,Aud_MNr,0)))),"") | G101: =IFERROR(IF($A101="","",IF(INDEX(Aud_Verantw,MATCH($A101,Aud_MNr,0))="","",INDEX(Aud_Verantw,MATCH($A101,Aud_MNr,0)))),"") | H101: =IFERROR(IF($A101="","",IF(INDEX(Aud_Termin,MATCH($A101,Aud_MNr,0))="","",INDEX(Aud_Termin,MATCH($A101,Aud_MNr,0)))),"") | I101: =IFERROR(IF($A101="","",INDEX(Aud_Status,MATCH($A101,Aud_MNr,0))),"")
...

Sheet Anlagenübersicht
A1: Anlagenübersicht – Risiko, Obsoleszenz und Investition (NEU)
A2: Eine Zeile je Anlage: für eine Einzelanlage nur die erste Zeile, für eine Maschinengruppe alle Anlagen der Gruppe. Gelbe Felder sind Eingaben; Skalen und Klassen im Blatt „Einstellungen“.
A4: Nr. | B4: Equipment-Nr. | C4: Anlagenbezeichnung | D4: Hersteller / Typ | E4: Baujahr | F4: Alter (Jahre) | G4: Steuerung / Hauptkomponente | H4: Kritikalität (A/B/C) | I4: Engpass- / Schlüsselanlage | J4: Techn. Verfügbarkeit (Ist) | K4: MTBF (h) | L4: MTTR (h) | M4: Obsoleszenzstatus | N4: Hersteller-unterstützung | O4: Ausweich-fertigung | P4: Notfallplan vorhanden | Q4: Ausfallwahr-scheinlichkeit W (1–5) | R4: Auswirkung A (1–5) | S4: Risikozahl W × A | T4: Risikoklasse | U4: Empfohlene Option | V4: Investition geschätzt (€) | W4: Umsetzung bis (Jahr) | X4: Auffälligkeiten (automatisch) | Y4: Bemerkung | Z4: Rang-Schlüssel (Hilfswert)
A5: =IF(B5="","",COUNTA($B$5:B5)) | F5: =IF(E5="","",YEAR(IF(Audit!$E$3="",TODAY(),Audit!$E$3))-E5) | S5: =IF(OR(Q5="",R5=""),"",Q5*R5) | T5: =IF(S5="","",IF(S5>=Risiko_hoch,"hoch",IF(S5>=Risiko_mittel,"mittel","gering"))) | X5: =IF(B5="","",MID(IF(AND(H5="A",P5="nein"),"· A-Anlage ohne Notfallplan ","")&IF(AND(OR(H5="A",I5="ja"),O5="keine"),"· keine Ausweichfertigung ","")&IF(OR(M5="abgekündigt",M5="nicht mehr lieferbar"),"· Obsoleszenz: "&M5&" ","")&IF(N5="keiner","· kein Herstellersupport ","")&IF(AND(J5<>"",J5<Ziel_Verfuegbarkeit),"· Verfügbarkeit unter Ziel ","")&IF(AND(F5<>"",F5>=25),"· Alter ≥ 25 Jahre ",""),3,300)) | Z5: =IF(S5="","",S5+(1000-ROW())/100000)
A6: =IF(B6="","",COUNTA($B$5:B6)) | F6: =IF(E6="","",YEAR(IF(Audit!$E$3="",TODAY(),Audit!$E$3))-E6) | S6: =IF(OR(Q6="",R6=""),"",Q6*R6) | T6: =IF(S6="","",IF(S6>=Risiko_hoch,"hoch",IF(S6>=Risiko_mittel,"mittel","gering"))) | X6: =IF(B6="","",MID(IF(AND(H6="A",P6="nein"),"· A-Anlage ohne Notfallplan ","")&IF(AND(OR(H6="A",I6="ja"),O6="keine"),"· keine Ausweichfertigung ","")&IF(OR(M6="abgekündigt",M6="nicht mehr lieferbar"),"· Obsoleszenz: "&M6&" ","")&IF(N6="keiner","· kein Herstellersupport ","")&IF(AND(J6<>"",J6<Ziel_Verfuegbarkeit),"· Verfügbarkeit unter Ziel ","")&IF(AND(F6<>"",F6>=25),"· Alter ≥ 25 Jahre ",""),3,300)) | Z6: =IF(S6="","",S6+(1000-ROW())/100000)
A7: =IF(B7="","",COUNTA($B$5:B7)) | F7: =IF(E7="","",YEAR(IF(Audit!$E$3="",TODAY(),Audit!$E$3))-E7) | S7: =IF(OR(Q7="",R7=""),"",Q7*R7) | T7: =IF(S7="","",IF(S7>=Risiko_hoch,"hoch",IF(S7>=Risiko_mittel,"mittel","gering"))) | X7: =IF(B7="","",MID(IF(AND(H7="A",P7="nein"),"· A-Anlage ohne Notfallplan ","")&IF(AND(OR(H7="A",I7="ja"),O7="keine"),"· keine Ausweichfertigung ","")&IF(OR(M7="abgekündigt",M7="nicht mehr lieferbar"),"· Obsoleszenz: "&M7&" ","")&IF(N7="keiner","· kein Herstellersupport ","")&IF(AND(J7<>"",J7<Ziel_Verfuegbarkeit),"· Verfügbarkeit unter Ziel ","")&IF(AND(F7<>"",F7>=25),"· Alter ≥ 25 Jahre ",""),3,300)) | Z7: =IF(S7="","",S7+(1000-ROW())/100000)
A8: =IF(B8="","",COUNTA($B$5:B8)) | F8: =IF(E8="","",YEAR(IF(Audit!$E$3="",TODAY(),Audit!$E$3))-E8) | S8: =IF(OR(Q8="",R8=""),"",Q8*R8) | T8: =IF(S8="","",IF(S8>=Risiko_hoch,"hoch",IF(S8>=Risiko_mittel,"mittel","gering"))) | X8: =IF(B8="","",MID(IF(AND(H8="A",P8="nein"),"· A-Anlage ohne Notfallplan ","")&IF(AND(OR(H8="A",I8="ja"),O8="keine"),"· keine Ausweichfertigung ","")&IF(OR(M8="abgekündigt",M8="nicht mehr lieferbar"),"· Obsoleszenz: "&M8&" ","")&IF(N8="keiner","· kein Herstellersupport ","")&IF(AND(J8<>"",J8<Ziel_Verfuegbarkeit),"· Verfügbarkeit unter Ziel ","")&IF(AND(F8<>"",F8>=25),"· Alter ≥ 25 Jahre ",""),3,300)) | Z8: =IF(S8="","",S8+(1000-ROW())/100000)
A9: =IF(B9="","",COUNTA($B$5:B9)) | F9: =IF(E9="","",YEAR(IF(Audit!$E$3="",TODAY(),Audit!$E$3))-E9) | S9: =IF(OR(Q9="",R9=""),"",Q9*R9) | T9: =IF(S9="","",IF(S9>=Risiko_hoch,"hoch",IF(S9>=Risiko_mittel,"mittel","gering"))) | X9: =IF(B9="","",MID(IF(AND(H9="A",P9="nein"),"· A-Anlage ohne Notfallplan ","")&IF(AND(OR(H9="A",I9="ja"),O9="keine"),"· keine Ausweichfertigung ","")&IF(OR(M9="abgekündigt",M9="nicht mehr lieferbar"),"· Obsoleszenz: "&M9&" ","")&IF(N9="keiner","· kein Herstellersupport ","")&IF(AND(J9<>"",J9<Ziel_Verfuegbarkeit),"· Verfügbarkeit unter Ziel ","")&IF(AND(F9<>"",F9>=25),"· Alter ≥ 25 Jahre ",""),3,300)) | Z9: =IF(S9="","",S9+(1000-ROW())/100000)
A10: =IF(B10="","",COUNTA($B$5:B10)) | F10: =IF(E10="","",YEAR(IF(Audit!$E$3="",TODAY(),Audit!$E$3))-E10) | S10: =IF(OR(Q10="",R10=""),"",Q10*R10) | T10: =IF(S10="","",IF(S10>=Risiko_hoch,"hoch",IF(S10>=Risiko_mittel,"mittel","gering"))) | X10: =IF(B10="","",MID(IF(AND(H10="A",P10="nein"),"· A-Anlage ohne Notfallplan ","")&IF(AND(OR(H10="A",I10="ja"),O10="keine"),"· keine Ausweichfertigung ","")&IF(OR(M10="abgekündigt",M10="nicht mehr lieferbar"),"· Obsoleszenz: "&M10&" ","")&IF(N10="keiner","· kein Herstellersupport ","")&IF(AND(J10<>"",J10<Ziel_Verfuegbarkeit),"· Verfügbarkeit unter Ziel ","")&IF(AND(F10<>"",F10>=25),"· Alter ≥ 25 Jahre ",""),3,300)) | Z10: =IF(S10="","",S10+(1000-ROW())/100000)
A11: =IF(B11="","",COUNTA($B$5:B11)) | F11: =IF(E11="","",YEAR(IF(Audit!$E$3="",TODAY(),Audit!$E$3))-E11) | S11: =IF(OR(Q11="",R11=""),"",Q11*R11) | T11: =IF(S11="","",IF(S11>=Risiko_hoch,"hoch",IF(S11>=Risiko_mittel,"mittel","gering"))) | X11: =IF(B11="","",MID(IF(AND(H11="A",P11="nein"),"· A-Anlage ohne Notfallplan ","")&IF(AND(OR(H11="A",I11="ja"),O11="keine"),"· keine Ausweichfertigung ","")&IF(OR(M11="abgekündigt",M11="nicht mehr lieferbar"),"· Obsoleszenz: "&M11&" ","")&IF(N11="keiner","· kein Herstellersupport ","")&IF(AND(J11<>"",J11<Ziel_Verfuegbarkeit),"· Verfügbarkeit unter Ziel ","")&IF(AND(F11<>"",F11>=25),"· Alter ≥ 25 Jahre ",""),3,300)) | Z11: =IF(S11="","",S11+(1000-ROW())/100000)
A12: =IF(B12="","",COUNTA($B$5:B12)) | F12: =IF(E12="","",YEAR(IF(Audit!$E$3="",TODAY(),Audit!$E$3))-E12) | S12: =IF(OR(Q12="",R12=""),"",Q12*R12) | T12: =IF(S12="","",IF(S12>=Risiko_hoch,"hoch",IF(S12>=Risiko_mittel,"mittel","gering"))) | X12: =IF(B12="","",MID(IF(AND(H12="A",P12="nein"),"· A-Anlage ohne Notfallplan ","")&IF(AND(OR(H12="A",I12="ja"),O12="keine"),"· keine Ausweichfertigung ","")&IF(OR(M12="abgekündigt",M12="nicht mehr lieferbar"),"· Obsoleszenz: "&M12&" ","")&IF(N12="keiner","· kein Herstellersupport ","")&IF(AND(J12<>"",J12<Ziel_Verfuegbarkeit),"· Verfügbarkeit unter Ziel ","")&IF(AND(F12<>"",F12>=25),"· Alter ≥ 25 Jahre ",""),3,300)) | Z12: =IF(S12="","",S12+(1000-ROW())/100000)
A13: =IF(B13="","",COUNTA($B$5:B13)) | F13: =IF(E13="","",YEAR(IF(Audit!$E$3="",TODAY(),Audit!$E$3))-E13) | S13: =IF(OR(Q13="",R13=""),"",Q13*R13) | T13: =IF(S13="","",IF(S13>=Risiko_hoch,"hoch",IF(S13>=Risiko_mittel,"mittel","gering"))) | X13: =IF(B13="","",MID(IF(AND(H13="A",P13="nein"),"· A-Anlage ohne Notfallplan ","")&IF(AND(OR(H13="A",I13="ja"),O13="keine"),"· keine Ausweichfertigung ","")&IF(OR(M13="abgekündigt",M13="nicht mehr lieferbar"),"· Obsoleszenz: "&M13&" ","")&IF(N13="keiner","· kein Herstellersupport ","")&IF(AND(J13<>"",J13<Ziel_Verfuegbarkeit),"· Verfügbarkeit unter Ziel ","")&IF(AND(F13<>"",F13>=25),"· Alter ≥ 25 Jahre ",""),3,300)) | Z13: =IF(S13="","",S13+(1000-ROW())/100000)
A14: =IF(B14="","",COUNTA($B$5:B14)) | F14: =IF(E14="","",YEAR(IF(Audit!$E$3="",TODAY(),Audit!$E$3))-E14) | S14: =IF(OR(Q14="",R14=""),"",Q14*R14) | T14: =IF(S14="","",IF(S14>=Risiko_hoch,"hoch",IF(S14>=Risiko_mittel,"mittel","gering"))) | X14: =IF(B14="","",MID(IF(AND(H14="A",P14="nein"),"· A-Anlage ohne Notfallplan ","")&IF(AND(OR(H14="A",I14="ja"),O14="keine"),"· keine Ausweichfertigung ","")&IF(OR(M14="abgekündigt",M14="nicht mehr lieferbar"),"· Obsoleszenz: "&M14&" ","")&IF(N14="keiner","· kein Herstellersupport ","")&IF(AND(J14<>"",J14<Ziel_Verfuegbarkeit),"· Verfügbarkeit unter Ziel ","")&IF(AND(F14<>"",F14>=25),"· Alter ≥ 25 Jahre ",""),3,300)) | Z14: =IF(S14="","",S14+(1000-ROW())/100000)
A15: =IF(B15="","",COUNTA($B$5:B15)) | F15: =IF(E15="","",YEAR(IF(Audit!$E$3="",TODAY(),Audit!$E$3))-E15) | S15: =IF(OR(Q15="",R15=""),"",Q15*R15) | T15: =IF(S15="","",IF(S15>=Risiko_hoch,"hoch",IF(S15>=Risiko_mittel,"mittel","gering"))) | X15: =IF(B15="","",MID(IF(AND(H15="A",P15="nein"),"· A-Anlage ohne Notfallplan ","")&IF(AND(OR(H15="A",I15="ja"),O15="keine"),"· keine Ausweichfertigung ","")&IF(OR(M15="abgekündigt",M15="nicht mehr lieferbar"),"· Obsoleszenz: "&M15&" ","")&IF(N15="keiner","· kein Herstellersupport ","")&IF(AND(J15<>"",J15<Ziel_Verfuegbarkeit),"· Verfügbarkeit unter Ziel ","")&IF(AND(F15<>"",F15>=25),"· Alter ≥ 25 Jahre ",""),3,300)) | Z15: =IF(S15="","",S15+(1000-ROW())/100000)
A16: =IF(B16="","",COUNTA($B$5:B16)) | F16: =IF(E16="","",YEAR(IF(Audit!$E$3="",TODAY(),Audit!$E$3))-E16) | S16: =IF(OR(Q16="",R16=""),"",Q16*R16) | T16: =IF(S16="","",IF(S16>=Risiko_hoch,"hoch",IF(S16>=Risiko_mittel,"mittel","gering"))) | X16: =IF(B16="","",MID(IF(AND(H16="A",P16="nein"),"· A-Anlage ohne Notfallplan ","")&IF(AND(OR(H16="A",I16="ja"),O16="keine"),"· keine Ausweichfertigung ","")&IF(OR(M16="abgekündigt",M16="nicht mehr lieferbar"),"· Obsoleszenz: "&M16&" ","")&IF(N16="keiner","· kein Herstellersupport ","")&IF(AND(J16<>"",J16<Ziel_Verfuegbarkeit),"· Verfügbarkeit unter Ziel ","")&IF(AND(F16<>"",F16>=25),"· Alter ≥ 25 Jahre ",""),3,300)) | Z16: =IF(S16="","",S16+(1000-ROW())/100000)
... A34: =IF(B34="","",COUNTA($B$5:B34)) | F34: =IF(E34="","",YEAR(IF(Audit!$E$3="",TODAY(),Audit!$E$3))-E34) | S34: =IF(OR(Q34="",R34=""),"",Q34*R34) | T34: =IF(S34="","",IF(S34>=Risiko_hoch,"hoch",IF(S34>=Risiko_mittel,"mittel","gering"))) | X34: =IF(B34="","",MID(IF(AND(H34="A",P34="nein"),"· A-Anlage ohne Notfallplan ","")&IF(AND(OR(H34="A",I34="ja"),O34="keine"),"· keine Ausweichfertigung ","")&IF(OR(M34="abgekündigt",M34="nicht mehr lieferbar"),"· Obsoleszenz: "&M34&" ","")&IF(N34="keiner","· kein Herstellersupport ","")&IF(AND(J34<>"",J34<Ziel_Verfuegbarkeit),"· Verfügbarkeit unter Ziel ","")&IF(AND(F34<>"",F34>=25),"· Alter ≥ 25 Jahre ",""),3,300)) | Z34: =IF(S34="","",S34+(1000-ROW())/100000)
A35: Auffälligkeiten werden automatisch erkannt: A-Anlage ohne Notfallplan, A- / Engpassanlage ohne Ausweichfertigung, Obsoleszenz, kein Herstellersupport, Verfügbarkeit unter Ziel (Einstellungen), Alter ≥ 25 Jahre.

Sheet Kritische Ersatzteile
A1: Kritische Ersatzteile und Obsoleszenz (NEU)
A2: Teile, deren Fehlen die Anlage stilllegt: lange Lieferzeit, Alleinlieferant oder abgekündigt. Gelbe Felder sind Eingaben; die Bewertung rechnet automatisch.
A4: Nr. | B4: Equipment-Nr. (Anlage) | C4: Bauteil / Bezeichnung | D4: Material-Nr. / Herst.-Art.-Nr. | E4: Hersteller / Lieferant | F4: Allein-lieferant | G4: Wiederbe-schaffungszeit (Wochen) | H4: Mindest-bestand | I4: Ist-Bestand | J4: Lagerort | K4: Lebenszyklus-status | L4: Ersatzlösung / Alternative | M4: Bewertung (automatisch) | N4: Bemerkung
A5: =IF(C5="","",COUNTA($C$5:C5)) | M5: =IF(C5="","",IF(AND(H5<>"",I5=""),"Bestand nicht erfasst",IF(AND(H5<>"",I5<H5),"Bestand unter Minimum",IF(AND(K5="nicht mehr lieferbar",L5=""),"obsolet ohne Ersatzlösung",IF(K5="abgekündigt","abgekündigt – Endbevorratung prüfen",IF(F5="ja","Alleinlieferant – Lieferung absichern","in Ordnung"))))))
A6: =IF(C6="","",COUNTA($C$5:C6)) | M6: =IF(C6="","",IF(AND(H6<>"",I6=""),"Bestand nicht erfasst",IF(AND(H6<>"",I6<H6),"Bestand unter Minimum",IF(AND(K6="nicht mehr lieferbar",L6=""),"obsolet ohne Ersatzlösung",IF(K6="abgekündigt","abgekündigt – Endbevorratung prüfen",IF(F6="ja","Alleinlieferant – Lieferung absichern","in Ordnung"))))))
A7: =IF(C7="","",COUNTA($C$5:C7)) | M7: =IF(C7="","",IF(AND(H7<>"",I7=""),"Bestand nicht erfasst",IF(AND(H7<>"",I7<H7),"Bestand unter Minimum",IF(AND(K7="nicht mehr lieferbar",L7=""),"obsolet ohne Ersatzlösung",IF(K7="abgekündigt","abgekündigt – Endbevorratung prüfen",IF(F7="ja","Alleinlieferant – Lieferung absichern","in Ordnung"))))))
A8: =IF(C8="","",COUNTA($C$5:C8)) | M8: =IF(C8="","",IF(AND(H8<>"",I8=""),"Bestand nicht erfasst",IF(AND(H8<>"",I8<H8),"Bestand unter Minimum",IF(AND(K8="nicht mehr lieferbar",L8=""),"obsolet ohne Ersatzlösung",IF(K8="abgekündigt","abgekündigt – Endbevorratung prüfen",IF(F8="ja","Alleinlieferant – Lieferung absichern","in Ordnung"))))))
A9: =IF(C9="","",COUNTA($C$5:C9)) | M9: =IF(C9="","",IF(AND(H9<>"",I9=""),"Bestand nicht erfasst",IF(AND(H9<>"",I9<H9),"Bestand unter Minimum",IF(AND(K9="nicht mehr lieferbar",L9=""),"obsolet ohne Ersatzlösung",IF(K9="abgekündigt","abgekündigt – Endbevorratung prüfen",IF(F9="ja","Alleinlieferant – Lieferung absichern","in Ordnung"))))))
A10: =IF(C10="","",COUNTA($C$5:C10)) | M10: =IF(C10="","",IF(AND(H10<>"",I10=""),"Bestand nicht erfasst",IF(AND(H10<>"",I10<H10),"Bestand unter Minimum",IF(AND(K10="nicht mehr lieferbar",L10=""),"obsolet ohne Ersatzlösung",IF(K10="abgekündigt","abgekündigt – Endbevorratung prüfen",IF(F10="ja","Alleinlieferant – Lieferung absichern","in Ordnung"))))))
A11: =IF(C11="","",COUNTA($C$5:C11)) | M11: =IF(C11="","",IF(AND(H11<>"",I11=""),"Bestand nicht erfasst",IF(AND(H11<>"",I11<H11),"Bestand unter Minimum",IF(AND(K11="nicht mehr lieferbar",L11=""),"obsolet ohne Ersatzlösung",IF(K11="abgekündigt","abgekündigt – Endbevorratung prüfen",IF(F11="ja","Alleinlieferant – Lieferung absichern","in Ordnung"))))))
A12: =IF(C12="","",COUNTA($C$5:C12)) | M12: =IF(C12="","",IF(AND(H12<>"",I12=""),"Bestand nicht erfasst",IF(AND(H12<>"",I12<H12),"Bestand unter Minimum",IF(AND(K12="nicht mehr lieferbar",L12=""),"obsolet ohne Ersatzlösung",IF(K12="abgekündigt","abgekündigt – Endbevorratung prüfen",IF(F12="ja","Alleinlieferant – Lieferung absichern","in Ordnung"))))))
A13: =IF(C13="","",COUNTA($C$5:C13)) | M13: =IF(C13="","",IF(AND(H13<>"",I13=""),"Bestand nicht erfasst",IF(AND(H13<>"",I13<H13),"Bestand unter Minimum",IF(AND(K13="nicht mehr lieferbar",L13=""),"obsolet ohne Ersatzlösung",IF(K13="abgekündigt","abgekündigt – Endbevorratung prüfen",IF(F13="ja","Alleinlieferant – Lieferung absichern","in Ordnung"))))))
A14: =IF(C14="","",COUNTA($C$5:C14)) | M14: =IF(C14="","",IF(AND(H14<>"",I14=""),"Bestand nicht erfasst",IF(AND(H14<>"",I14<H14),"Bestand unter Minimum",IF(AND(K14="nicht mehr lieferbar",L14=""),"obsolet ohne Ersatzlösung",IF(K14="abgekündigt","abgekündigt – Endbevorratung prüfen",IF(F14="ja","Alleinlieferant – Lieferung absichern","in Ordnung"))))))
A15: =IF(C15="","",COUNTA($C$5:C15)) | M15: =IF(C15="","",IF(AND(H15<>"",I15=""),"Bestand nicht erfasst",IF(AND(H15<>"",I15<H15),"Bestand unter Minimum",IF(AND(K15="nicht mehr lieferbar",L15=""),"obsolet ohne Ersatzlösung",IF(K15="abgekündigt","abgekündigt – Endbevorratung prüfen",IF(F15="ja","Alleinlieferant – Lieferung absichern","in Ordnung"))))))
A16: =IF(C16="","",COUNTA($C$5:C16)) | M16: =IF(C16="","",IF(AND(H16<>"",I16=""),"Bestand nicht erfasst",IF(AND(H16<>"",I16<H16),"Bestand unter Minimum",IF(AND(K16="nicht mehr lieferbar",L16=""),"obsolet ohne Ersatzlösung",IF(K16="abgekündigt","abgekündigt – Endbevorratung prüfen",IF(F16="ja","Alleinlieferant – Lieferung absichern","in Ordnung"))))))
... A44: =IF(C44="","",COUNTA($C$5:C44)) | M44: =IF(C44="","",IF(AND(H44<>"",I44=""),"Bestand nicht erfasst",IF(AND(H44<>"",I44<H44),"Bestand unter Minimum",IF(AND(K44="nicht mehr lieferbar",L44=""),"obsolet ohne Ersatzlösung",IF(K44="abgekündigt","abgekündigt – Endbevorratung prüfen",IF(F44="ja","Alleinlieferant – Lieferung absichern","in Ordnung"))))))

Sheet Einstellungen
A1: Einstellungen
A2: Gelbe Felder sind Eingaben. Alle Auswertungen greifen auf diese Werte zu.
A4: Bewertung
A5: Gewicht „bed. OK“ | C5: 0.5 | D5: Aus der Vorlage „2026_Audit_Instandhaltung_Allgemein“ übernommen: „bed. OK“ zählt zur Hälfte. Frei änderbar.
A6: Ampel grün ab | C6: 0.85 | D6: Aus der Vorlage übernommen, frei änderbar. Ab diesem Erfüllungsgrad: „gut“.
A7: Ampel gelb ab | C7: 0.6 | D7: Aus der Vorlage übernommen, frei änderbar. Ab diesem Erfüllungsgrad: „mittel“, darunter „kritisch“.
A8: K.O.-Regel aktiv | C8: ja | D8: NEU: Ist ein K.O.-Prüfpunkt mit N.I.O bewertet, lautet die Gesamtbewertung „kritisch (K.O.)“ – unabhängig vom Erfüllungsgrad.
A10: Zielwerte und Grenzwerte (NEU)
A11: Ziel technische Verfügbarkeit | C11: 0.92 | D11: Annahme: 92 % wie im Vorlage-Punkt 24 der Datei „2026_Audit_Instandhaltung_Allgemein“ (dort Hinweis 90 % / 80 %). Bitte gültigen Zielwert bestätigen.
A12: Grenzwert IH-Kostenquote | C12: 0.05 | D12: Annahme (Vorschlag), frei änderbar: IH-Kosten pro Jahr ÷ Wiederbeschaffungswert. Darüber ist eine Ersatz- oder Retrofit-Prüfung angeraten.
A13: Risiko „hoch“ ab Risikozahl | C13: 15 | D13: Annahme (Vorschlag), frei änderbar. Risikozahl = Ausfallwahrscheinlichkeit (1–5) × Auswirkung (1–5), maximal 25.
A14: Risiko „mittel“ ab Risikozahl | C14: 8 | D14: Annahme (Vorschlag), frei änderbar. Darunter: „gering“.
A16: Kapitel
A17: Nr. | B17: Kapitel
A18: 1 | B18: Technischer Zustand | D18: Diese Liste steuert das Dashboard und die Auswahlliste im Blatt „Audit“. Wird ein Name geändert, die Prüfpunkte im Blatt „Audit“ (Spalte Kapitel) neu zuordnen.
A19: 2 | B19: Betriebsbereitschaft
A20: 3 | B20: Verfügbarkeit & Störanfälligkeit
A21: 4 | B21: Wartungszustand
A22: 5 | B22: Ersatzteilverfügbarkeit
A23: 6 | B23: Kritische Ersatzteile
A24: 7 | B24: Werkzeugzustand & -verfügbarkeit
A25: 8 | B25: Obsoleszenz & Herstellersupport
A26: 9 | B26: Sicherheit & Umwelt
A27: 10 | B27: Produktionsrelevanz & Engpass
A28: 11 | B28: Ausweichfertigung & Notfall
A29: 12 | B29: Dokumentation & Software
A30: 13 | B30: Personal & Know-how
A31: 14 | B31: Modernisierung & Investition
A34: Bewertungsskala
A35: Bewertung | B35: Bedeutung | C35: Wertung
A36: N.I.O | B36: nicht in Ordnung – Anforderung nicht erfüllt | C36: 0 | D36: Maßnahme, Verantwortlicher und Termin erforderlich.
A37: bed. OK | B37: bedingt in Ordnung – teilweise erfüllt | C37: =Gewicht_bedOK | D37: Maßnahme zur Verbesserung festlegen.
A38: OK | B38: in Ordnung – Anforderung erfüllt | C38: 1 | D38: Nachweis in Spalte „Nachweis / Evidenz“ eintragen.
A39: n. b. | B39: nicht bewertet / nicht zutreffend | C39: zählt nicht | D39: Geht nicht in den Erfüllungsgrad ein.
A41: Gewichtung der Prüfpunkte (NEU)
A42: Gewicht | B42: Bedeutung | C42: Beispiel
A43: 1 | B43: normal | C43: Ordnung, Kennzeichnung, Nachweise mit geringer Ausfallwirkung
A44: 2 | B44: wichtig – direkte Wirkung auf Verfügbarkeit oder Qualität | C44: Zustand Hydraulik, Ersatzteillisten, Wartungsnachweise
A45: 3 | B45: sehr wichtig – Sicherheit, Notfall, Ausfall ohne Ersatz | C45: Schutzeinrichtungen, Notfallplan, kritische Ersatzteile, Datensicherung
A46: Erfüllungsgrad = Σ(Gewicht × Wertung) ÷ Σ(Gewicht) über alle mit N.I.O, bed. OK oder OK bewerteten Punkte. Mit Gewicht 1 für alle Punkte entspricht das der Berechnung der Vorlage.
A48: Risikoskalen (NEU) – für das Blatt „Anlagenübersicht“
A49: Stufe | B49: Ausfallwahrscheinlichkeit (W) | D49: Auswirkung (A)
A50: 1 | B50: sehr gering – neuwertiger Zustand, keine Störungen in 12 Monaten, Ersatzteile verfügbar | D50: unbedeutend – C-Anlage, Ausweichfertigung freigegeben, kein Kundeneinfluss
A51: 2 | B51: gering – guter Zustand, vereinzelte Störungen, MTBF stabil | D51: gering – Ausfall über Puffer / Ausweichfertigung ohne Lieferverzug abfangbar
A52: 3 | B52: mittel – Verschleiß sichtbar, wiederkehrende Störungen oder einzelne abgekündigte Komponenten | D52: mittel – B-Anlage, Ausweichfertigung nur eingeschränkt, Sonderschichten nötig
A53: 4 | B53: hoch – deutlicher Verschleiß, häufige Störungen, Obsoleszenz ohne Ersatzlösung | D53: hoch – A- / Engpassanlage, Lieferverzug beim Kunden möglich
A54: 5 | B54: sehr hoch – Ausfall jederzeit zu erwarten, kein Herstellersupport, kritische Teile nicht beschaffbar | D54: sehr hoch – Bandstillstand beim Kunden, Sicherheits- / Sondermerkmale, keine Ausweichfertigung
A55: Risikozahl = W × A. Klassen: „hoch“ ab dem Wert in Zeile 13, „mittel“ ab dem Wert in Zeile 14, darunter „gering“.
A57: Kritikalitätsklassen (NEU)
A58: Klasse | B58: Bedeutung | D58: Folge für die IH-Strategie
A59: A | B59: Schlüssel- oder Engpassanlage, keine freigegebene Ausweichfertigung, Ausfall stoppt Kundenlieferung | D59: vorbeugend + zustandsorientiert, kritische Ersatzteile bevorratet, Notfallplan Pflicht
A60: B | B60: wichtige Anlage, Ausweichfertigung eingeschränkt möglich | D60: vorbeugend nach Plan, Ersatzteile mit gesicherter Lieferzeit
A61: C | B61: unkritisch, redundant oder Ausweichfertigung freigegeben | D61: ausfallorientiert / Basiswartung
A63: Auswahllisten (NEU) | B63: Werte können ergänzt werden; die Auswahlfelder in den anderen Blättern greifen darauf zu.
A64: Geltungsbereich | B64: ja / nein | C64: Kritikalität | D64: Obsoleszenzstatus | E64: Herstellerunterstützung | F64: Ausweichfertigung | G64: Empfohlene Option
A65: Einzelanlage | B65: ja | C65: A | D65: aktiv | E65: vollständig | F65: freigegeben | G65: Weiterbetrieb
A66: Maschinengruppe | B66: nein | C66: B | D66: abgekündigt | E66: eingeschränkt | F66: möglich, nicht freigegeben | G66: Instandsetzung
C67: C | D67: nicht mehr lieferbar | E67: keiner | F67: keine | G67: Generalüberholung
D68: unbekannt | E68: unbekannt | G68: Retrofit
G69: Ersatzinvestition

Sheet Anleitung
A1: Anleitung
A2: Anlagenzustandsanalyse für Einzelanlagen und Maschinengruppen – Aufbau und Formatierung nach „2026_Audit_Instandhaltung_Allgemein“, Prüfpunkte aus „Vorlage_Audit_Instandhaltung_01“ ergänzt. Ohne Makros.
A4: So geht's
A5: 1. Kopfdaten | B5: Im Blatt „Audit“ Werk / Standort, Anlage bzw. Maschinengruppe, Equipment-Nr. (bei Gruppen alle), Geltungsbereich, Teilnehmer, Datum, Auditor und Kostenstelle ausfüllen.
A6: 2. Bewerten | B6: In Spalte „Bewertung“ je Prüfpunkt wählen: N.I.O, bed. OK, OK oder n. b. In „Nachweis / Evidenz“ festhalten, welches Dokument bzw. welcher Befund gesehen wurde (z. B. „Wartungsplan SAP-Auftrag 4711, Stand 05/2026“).
A7: 3. Maßnahmen | B7: Bei N.I.O und bed. OK: Maßnahme, Verantwortlich und Termin eintragen. „Erledigt = ja“ setzt den Status auf „erledigt“, ein überschrittener Termin auf „überfällig“. Der Maßnahmenplan füllt sich automatisch.
A8: 4. Anlagen erfassen | B8: Im Blatt „Anlagenübersicht“ je Anlage eine Zeile: Stammdaten, Kritikalität, Kennzahlen, Obsoleszenz, Support, Ausweichfertigung, Notfallplan, Risiko (W und A nach Skala in „Einstellungen“), empfohlene Option und Investition. Bei einer Einzelanlage nur Zeile 1.
A9: 5. Kritische Ersatzteile | B9: Im Blatt „Kritische Ersatzteile“ die Teile erfassen, deren Fehlen die Anlage stilllegt. Die Spalte „Bewertung“ zeigt automatisch Bestand unter Minimum, Obsoleszenz und Alleinlieferant.
A10: 6. Auswertung | B10: Das Blatt „Dashboard“ rechnet sich automatisch: Seite 1 Gesamtergebnis, Kapitel und Diagramme · Seite 2 Handlungsbedarf, Maßnahmenstand, N.I.O-Liste · Seite 3 Risikomatrix, Top-5-Risiken, kritische Ersatzteile, Investitionsbedarf.
A11: 7. Drucken | B11: Dashboard: 3 Seiten A4 quer. Audit, Maßnahmen, Anlagenübersicht und Ersatzteile: A4 quer, auf Seitenbreite skaliert, Kopfzeile der Tabelle wiederholt sich.
A13: Farben
A14: Gelbe Zellen, blaue Schrift | B14: Eingabefelder – nur hier eintragen.
A15: Weiße Zellen | B15: Texte und Formeln. Formeln (Nr., Status, Maßn.-Nr., Alter, Risikozahl, Auffälligkeiten, Bewertung, Dashboard, Maßnahmen) nicht überschreiben.
A16: Blau markiert: „NEU“ | B16: Ergänzter Prüfpunkt, der in der Ursprungsdatei nicht enthalten war (Spalte „Herkunft“ im Blatt „Audit“).
A17: Herkunft „Vorlage …“ | B17: „M x“ = Blatt „Auditcheckliste_Maschine“, Nr. x · „A1 Zn“ = Blatt „Auditcheckliste_1“, Zelle Zn der Datei „Vorlage_Audit_Instandhaltung_01.xlsm“. „(präzisiert)“ = Text geschärft, „(Teil)“ = Teilaspekt eines Vorlage-Punkts.
A18: Rot „K.O.“ | B18: K.O.-Prüfpunkt (Sicherheit, Notfallplan). Ein N.I.O führt zur Gesamtbewertung „kritisch (K.O.)“ (abschaltbar im Blatt „Einstellungen“).
A20: Beispiele (nur Format)
A21: Eine Zeile im Blatt „Audit“ | B21: Bewertung: bed. OK · Nachweis: Schmierplan liegt im SAP vor, nicht an der Maschine · Maßnahme: Schmierplan an der Maschine aushängen · Verantwortlich: Meister IH · Termin: 31.12.2026 · Erledigt: nein
A22: Eine Zeile „Anlagenübersicht“ | B22: Equipment-Nr. 10004711 · Rundtaktanlage RT 12 · Hersteller XY / RT12 · Baujahr 2003 · Steuerung S7-300 · Kritikalität A · Engpass ja · Verfügbarkeit 88 % · MTBF 120 h · MTTR 3,5 h · Obsoleszenz abgekündigt · Support eingeschränkt · Ausweichfertigung keine · Notfallplan nein · W 4 · A 5 · Option Retrofit · 180.000 € · 2027
A23: Eine Zeile „Kritische Ersatzteile“ | B23: Equipment-Nr. 10004711 · CPU 315-2DP · 6ES7315-2AG10-0AB0 · Siemens · Alleinlieferant nein · 12 Wochen · Mindestbestand 1 · Ist-Bestand 0 · Lager IH-E-03 · abgekündigt ⇒ Bewertung „Bestand unter Minimum“
A25: Prüfpunkte
A26: Umfang | B26: 88 Prüfpunkte in 14 Kapiteln: 29 aus der Ursprungsdatei (Herkunft „Vorlage …“, sprachlich bereinigt, alle 23 Kriterien der Ursprungsdatei abgedeckt) und 59 ergänzte Punkte (Herkunft „NEU“). Alle Punkte noch unbewertet.
A27: Einzelanlage / Gruppe | B27: Bei einer Maschinengruppe gilt die Checkliste für die Gruppe als Ganzes (schlechtester relevanter Zustand bestimmt die Bewertung, Abweichungen einzelner Anlagen in „Nachweis“ bzw. „Maßnahmen“ benennen). Die anlagenbezogenen Werte (Risiko, Obsoleszenz, Investition) stehen je Anlage in der „Anlagenübersicht“.
A28: Nicht benötigte Punkte | B28: Ganze Zeile markieren (Zeilenkopf) und löschen oder mit „n. b.“ bewerten. Nummerierung, Dashboard und Maßnahmenplan passen sich automatisch an.
A29: Eigene Punkte ergänzen | B29: Die 10 leeren Zeilen am Ende der Liste nutzen: Kapitel wählen, Check-Punkt und Gewicht eintragen. Für weitere Punkte eine Zeile innerhalb der Liste einfügen und die Formeln der Zeile darüber übernehmen.
A30: Kapitel | B30: Die Kapitelnamen stehen im Blatt „Einstellungen“. Die Zuordnung eines Punkts erfolgt über die Spalte „Kapitel“ im Blatt „Audit“.
A32: Berechnung
A33: Erfüllungsgrad | B33: Σ(Gewicht × Wertung) ÷ Σ(Gewicht) über die mit N.I.O, bed. OK oder OK bewerteten Punkte; OK = 100 %, bed. OK = 50 % (Einstellung), N.I.O = 0 %. „n. b.“ und offene Punkte zählen nicht.
A34: Ampel | B34: „gut“ ab der grünen Grenze (85 %), „mittel“ ab der gelben Grenze (60 %), darunter „kritisch“. Ein K.O.-Punkt mit N.I.O ergibt „kritisch (K.O.)“. Ohne bewertete Punkte: „nicht bewertet“.
A35: Maßnahmenstatus | B35: Nur für N.I.O und bed. OK: „erledigt“ bei Erledigt = ja, „überfällig“ bei Termin vor dem heutigen Datum, sonst „offen“.
A36: Risiko | B36: Risikozahl = W × A (1–25). Klassen „hoch“ ab 15, „mittel“ ab 8, sonst „gering“ (Annahmen, änderbar). Die Risikomatrix im Dashboard zählt die Anlagen je Feld.
A38: Neu gegenüber den Vorlagen (NEU)
A39: Gewichtung 1–3 | B39: Wichtige und sicherheitsrelevante Punkte zählen stärker. Mit Gewicht 1 überall ergibt sich die Berechnung der Vorlage.
A40: K.O.-Kriterien | B40: Sicherheit und Notfallplan: ein N.I.O kann nicht durch gute Bewertungen anderer Punkte ausgeglichen werden (wie die Abwertungsregel in VDA 6.3).
A41: Normbezug und Nachweis | B41: Jeder Punkt nennt seine Grundlage (IATF 16949, BetrSichV, DIN EN 13306 …) und hat ein Nachweisfeld – für die Auditfähigkeit nach IATF 16949.
A42: Anlagenübersicht | B42: Risikobewertung, Obsoleszenz, Herstellersupport, Ausweichfertigung, Notfallplan und Investitionsbedarf je Anlage – Grundlage für Management- und Investitionsentscheidungen, auch für Maschinengruppen.
A43: Kritische Ersatzteile | B43: Liste mit Lieferzeit, Bestand, Alleinlieferant und Lebenszyklusstatus mit automatischer Bewertung.
A44: Dashboard Seite 3 | B44: Risikomatrix, Top-5-Risikoanlagen, Auffälligkeiten und Investitionssumme je Option.
A46: Offene Punkte / Annahmen
A47: Ziel Verfügbarkeit | B47: 92 % aus Vorlage-Punkt 24 der Datei „2026_Audit_Instandhaltung_Allgemein“ übernommen; dort ist der Wert zwischen deutscher und englischer Fassung uneinheitlich. Bitte bestätigen (Blatt „Einstellungen“).
A48: Grenzwerte | B48: IH-Kostenquote 5 %, Risiko „hoch“ ab 15 und „mittel“ ab 8 sind Vorschläge und frei änderbar.
A50: Normbezüge
A51: IATF 16949 | B51: 6.1.2.3 Notfallpläne · 7.1.3.1 Anlagenplanung · 7.1.4.1 Arbeitsumgebung · 7.1.6 Wissen · 7.2.1 Kompetenz · 7.5 Dokumentierte Information · 8.3.3.3 Besondere Merkmale · 8.5.1.3 Verifizierung von Einrichtvorgängen · 8.5.1.4 Verifizierung nach Stillstand · 8.5.1.5 TPM · 8.5.1.6 Produktionswerkzeuge · 8.5.3 Eigentum der Kunden · 8.5.6.1.1 Zeitweilige Änderung von Prozesslenkungen · 9.1.1.1 Prozessüberwachung · 10.2.3 Problemlösung
A52: Weitere | B52: DIN 31051 und DIN EN 13306 (Grundlagen, Begriffe) · DIN EN 15341 (Kennzahlen) · IEC 62402 (Obsoleszenzmanagement) · BetrSichV · ArbSchG § 5 · DGUV Vorschrift 3 · AwSV / ISO 14001 · ASR A2.2 (Brandschutz)
